Workbook

Sheet The Plan
B2: THE PLAN | G2: Updated Apr 30, 2026
B3: Hubele family debt-free roadmap
A5: =("$"&TEXT('Debt Tracker'!E30-'Debt Tracker'!L30,"#,##0")&" of $"&TEXT('Debt Tracker'!E30,"#,##0")&" paid off") -> $6,379 of $85,142 paid off | C5: =VLOOKUP($C$15,$I$100:$K$103,2,FALSE()) -> 15 | E5: =DATE(2026,5+VLOOKUP($C$15,$I$100:$K$103,2,FALSE())-1,1) -> 46569 | G5: =IF(('Debt Tracker'!E30-'Debt Tracker'!L30)/'Debt Tracker'!E30=0,"🚦 NOT STARTED",IF(('Debt Tracker'!E30-'Debt Tracker'!L30)/'Debt Tracker'!E30>=1,"🎉 DEBT FREE!","✓ IN PROGRESS")) -> ✓ IN PROGRESS
A6: =REPT("█",ROUND(50*(('Debt Tracker'!E30-'Debt Tracker'!L30)/'Debt Tracker'!E30),0))&REPT("░",50-ROUND(50*(('Debt Tracker'!E30-'Debt Tracker'!L30)/'Debt Tracker'!E30),0)) -> ████░░░░░░░░░░░░░░░░░░░░░░░░░░░░░░░░░░░░░░░░░░░░░░ | G6: =("("&TEXT(('Debt Tracker'!E30-'Debt Tracker'!L30)/'Debt Tracker'!E30,"0.0%")&" complete)") -> (7.5% complete)
A7: NEXT UP | B7: 1️⃣ THIS MONTH | D7: 2️⃣ NEXT | F7: 3️⃣ AFTER
B8: =VLOOKUP($C$15,$I$100:$T$103,4,FALSE()) -> Mattress Firm / Synchrony Home | D8: =VLOOKUP($C$15,$I$100:$T$103,5,FALSE()) -> Ashley Furniture / Synchrony | F8: =VLOOKUP($C$15,$I$100:$T$103,6,FALSE()) -> Best Buy / Citi
A9: 💰 Cash on Hand: | B9: =Payments!E2 -> 3408.09 | C9: 📈 Income (CSV): | D9: =SUMIFS(Payments!F:F,Payments!D:D,"Income") -> 12540.19 | E9: 📉 Expenses (CSV): | F9: =SUMIFS(Payments!F:F,Payments!D:D,"Expense") -> 13224.39 | G9: 💵 Net: | H9: =D9-F9 -> -684.2
B10: 💡 DO THIS NOW
B11: =VLOOKUP($C$15,$I$100:$T$103,10,FALSE()) -> Pay $1,583 → Mattress Firm / Synchrony Home AND $934 → Ashley Furniture / Synchrony
B12: =VLOOKUP($C$15,$I$100:$T$103,11,FALSE()) -> You have $3,472/mo extra. Kills BOTH this month — over $2,517 of debt gone.
B14: 🔧 PLAY WITH YOUR PLAN
B15: Pick a scenario: | C15: Current Plan | E15: 👆 changes the numbers above
B16: JUST MINIMUMS | C16: CONSERVATIVE | D16: CURRENT | E16: AGGRESSIVE | F16: WHAT IT MEANS
B17: $0 extra | C17: +$1,500/mo | D17: +$3,472/mo | E17: +$3,472 +$20K | F17: • Minimums = 3.5 yrs of paying interest, no progress • Conservative = realistic if cash gets tight • Current = your full $3,472/mo budget surplus • Aggressive = use $20K savings to wipe out 8 highest-APR debts day 1
B18: 37 mo | C18: 22 mo | D18: 15 mo | E18: 11 mo
B19: May 2029 | C19: Feb 2028 | D19: Jul 2027 | E19: Mar 2027
B20: $34,132 interest | C20: $18,273 interest | D20: $11,780 interest | E20: $6,046 interest
B21: +22mo, +$22,352 | C21: +7mo, +$6,492 | D21: (your active) | E21: -4mo, −$5,735
B22: 🗓️ FULL PAYOFF SCHEDULE — DEBTS DIE IN THIS ORDER
B23: # | C23: Debt | D23: When | E23: Balance Today | F23: Pay This Much | G23: What Happens After
B24: =IFERROR(INDEX($U$200:$AR$224,1,VLOOKUP($C$15,$I$100:$T$103,12,FALSE())+1),"") -> 1 | C24: =IFERROR(INDEX($U$200:$AR$224,1,VLOOKUP($C$15,$I$100:$T$103,12,FALSE())+2),"") -> Mattress Firm / Synchrony Home | D24: =IFERROR(INDEX($U$200:$AR$224,1,VLOOKUP($C$15,$I$100:$T$103,12,FALSE())+3),"") -> 46143 | E24: =IFERROR(INDEX($U$200:$AR$224,1,VLOOKUP($C$15,$I$100:$T$103,12,FALSE())+4),"") -> 1583.49 | F24: =IFERROR(INDEX($U$200:$AR$224,1,VLOOKUP($C$15,$I$100:$T$103,12,FALSE())+5),"") -> 1712.49 | G24: =IFERROR(INDEX($U$200:$AR$224,1,VLOOKUP($C$15,$I$100:$T$103,12,FALSE())+6),"") -> First win! Frees up $129/mo.
B25: =IFERROR(INDEX($U$200:$AR$224,2,VLOOKUP($C$15,$I$100:$T$103,12,FALSE())+1),"") -> 2 | C25: =IFERROR(INDEX($U$200:$AR$224,2,VLOOKUP($C$15,$I$100:$T$103,12,FALSE())+2),"") -> Ashley Furniture / Synchrony | D25: =IFERROR(INDEX($U$200:$AR$224,2,VLOOKUP($C$15,$I$100:$T$103,12,FALSE())+3),"") -> 46143 | E25: =IFERROR(INDEX($U$200:$AR$224,2,VLOOKUP($C$15,$I$100:$T$103,12,FALSE())+4),"") -> 933.82 | F25: =IFERROR(INDEX($U$200:$AR$224,2,VLOOKUP($C$15,$I$100:$T$103,12,FALSE())+5),"") -> 966.82 | G25: =IFERROR(INDEX($U$200:$AR$224,2,VLOOKUP($C$15,$I$100:$T$103,12,FALSE())+6),"") -> Same-month kill! +$33/mo.
B26: =IFERROR(INDEX($U$200:$AR$224,3,VLOOKUP($C$15,$I$100:$T$103,12,FALSE())+1),"") -> 3 | C26: =IFERROR(INDEX($U$200:$AR$224,3,VLOOKUP($C$15,$I$100:$T$103,12,FALSE())+2),"") -> Best Buy / Citi | D26: =IFERROR(INDEX($U$200:$AR$224,3,VLOOKUP($C$15,$I$100:$T$103,12,FALSE())+3),"") -> 46174 | E26: =IFERROR(INDEX($U$200:$AR$224,3,VLOOKUP($C$15,$I$100:$T$103,12,FALSE())+4),"") -> 1200 | F26: =IFERROR(INDEX($U$200:$AR$224,3,VLOOKUP($C$15,$I$100:$T$103,12,FALSE())+5),"") -> 1229 | G26: =IFERROR(INDEX($U$200:$AR$224,3,VLOOKUP($C$15,$I$100:$T$103,12,FALSE())+6),"") -> +$29/mo to next attack.
B27: =IFERROR(INDEX($U$200:$AR$224,4,VLOOKUP($C$15,$I$100:$T$103,12,FALSE())+1),"") -> 4 | C27: =IFERROR(INDEX($U$200:$AR$224,4,VLOOKUP($C$15,$I$100:$T$103,12,FALSE())+2),"") -> Capital One Platinum | D27: =IFERROR(INDEX($U$200:$AR$224,4,VLOOKUP($C$15,$I$100:$T$103,12,FALSE())+3),"") -> 46204 | E27: =IFERROR(INDEX($U$200:$AR$224,4,VLOOKUP($C$15,$I$100:$T$103,12,FALSE())+4),"") -> 5930.94 | F27: =IFERROR(INDEX($U$200:$AR$224,4,VLOOKUP($C$15,$I$100:$T$103,12,FALSE())+5),"") -> 6130.94 | G27: =IFERROR(INDEX($U$200:$AR$224,4,VLOOKUP($C$15,$I$100:$T$103,12,FALSE())+6),"") -> Big payoff — $200/mo joins war chest.
B28: =IFERROR(INDEX($U$200:$AR$224,5,VLOOKUP($C$15,$I$100:$T$103,12,FALSE())+1),"") -> 5 | C28: =IFERROR(INDEX($U$200:$AR$224,5,VLOOKUP($C$15,$I$100:$T$103,12,FALSE())+2),"") -> Amex Delta SkyMiles Gold | D28: =IFERROR(INDEX($U$200:$AR$224,5,VLOOKUP($C$15,$I$100:$T$103,12,FALSE())+3),"") -> 46266 | E28: =IFERROR(INDEX($U$200:$AR$224,5,VLOOKUP($C$15,$I$100:$T$103,12,FALSE())+4),"") -> 7294.06 | F28: =IFERROR(INDEX($U$200:$AR$224,5,VLOOKUP($C$15,$I$100:$T$103,12,FALSE())+5),"") -> 7499.93 | G28: =IFERROR(INDEX($U$200:$AR$224,5,VLOOKUP($C$15,$I$100:$T$103,12,FALSE())+6),"") -> Big payoff — $206/mo joins war chest.
B29: =IFERROR(INDEX($U$200:$AR$224,6,VLOOKUP($C$15,$I$100:$T$103,12,FALSE())+1),"") -> 6 | C29: =IFERROR(INDEX($U$200:$AR$224,6,VLOOKUP($C$15,$I$100:$T$103,12,FALSE())+2),"") -> Menards Big Card (Cap One) | D29: =IFERROR(INDEX($U$200:$AR$224,6,VLOOKUP($C$15,$I$100:$T$103,12,FALSE())+3),"") -> 46296 | E29: =IFERROR(INDEX($U$200:$AR$224,6,VLOOKUP($C$15,$I$100:$T$103,12,FALSE())+4),"") -> 2758.32 | F29: =IFERROR(INDEX($U$200:$AR$224,6,VLOOKUP($C$15,$I$100:$T$103,12,FALSE())+5),"") -> 2850.32 | G29: =IFERROR(INDEX($U$200:$AR$224,6,VLOOKUP($C$15,$I$100:$T$103,12,FALSE())+6),"") -> +$92/mo to next attack.
B30: =IFERROR(INDEX($U$200:$AR$224,7,VLOOKUP($C$15,$I$100:$T$103,12,FALSE())+1),"") -> 7 | C30: =IFERROR(INDEX($U$200:$AR$224,7,VLOOKUP($C$15,$I$100:$T$103,12,FALSE())+2),"") -> Amex Platinum (Pay Over Time) | D30: =IFERROR(INDEX($U$200:$AR$224,7,VLOOKUP($C$15,$I$100:$T$103,12,FALSE())+3),"") -> 46296 | E30: =IFERROR(INDEX($U$200:$AR$224,7,VLOOKUP($C$15,$I$100:$T$103,12,FALSE())+4),"") -> 1406.09 | F30: =IFERROR(INDEX($U$200:$AR$224,7,VLOOKUP($C$15,$I$100:$T$103,12,FALSE())+5),"") -> 1446.09 | G30: =IFERROR(INDEX($U$200:$AR$224,7,VLOOKUP($C$15,$I$100:$T$103,12,FALSE())+6),"") -> Same-month kill! +$40/mo.
B31: =IFERROR(INDEX($U$200:$AR$224,8,VLOOKUP($C$15,$I$100:$T$103,12,FALSE())+1),"") -> 8 | C31: =IFERROR(INDEX($U$200:$AR$224,8,VLOOKUP($C$15,$I$100:$T$103,12,FALSE())+2),"") -> Affirm — Best Buy (Dec) | D31: =IFERROR(INDEX($U$200:$AR$224,8,VLOOKUP($C$15,$I$100:$T$103,12,FALSE())+3),"") -> 46327 | E31: =IFERROR(INDEX($U$200:$AR$224,8,VLOOKUP($C$15,$I$100:$T$103,12,FALSE())+4),"") -> 3020.12 | F31: =IFERROR(INDEX($U$200:$AR$224,8,VLOOKUP($C$15,$I$100:$T$103,12,FALSE())+5),"") -> 3171.13 | G31: =IFERROR(INDEX($U$200:$AR$224,8,VLOOKUP($C$15,$I$100:$T$103,12,FALSE())+6),"") -> +$151/mo to next attack.
B32: =IFERROR(INDEX($U$200:$AR$224,9,VLOOKUP($C$15,$I$100:$T$103,12,FALSE())+1),"") -> 9 | C32: =IFERROR(INDEX($U$200:$AR$224,9,VLOOKUP($C$15,$I$100:$T$103,12,FALSE())+2),"") -> Capital One Quicksilver | D32: =IFERROR(INDEX($U$200:$AR$224,9,VLOOKUP($C$15,$I$100:$T$103,12,FALSE())+3),"") -> 46327 | E32: =IFERROR(INDEX($U$200:$AR$224,9,VLOOKUP($C$15,$I$100:$T$103,12,FALSE())+4),"") -> 1169.64 | F32: =IFERROR(INDEX($U$200:$AR$224,9,VLOOKUP($C$15,$I$100:$T$103,12,FALSE())+5),"") -> 1207.64 | G32: =IFERROR(INDEX($U$200:$AR$224,9,VLOOKUP($C$15,$I$100:$T$103,12,FALSE())+6),"") -> Same-month kill! +$38/mo.
B33: =IFERROR(INDEX($U$200:$AR$224,10,VLOOKUP($C$15,$I$100:$T$103,12,FALSE())+1),"") -> 10 | C33: =IFERROR(INDEX($U$200:$AR$224,10,VLOOKUP($C$15,$I$100:$T$103,12,FALSE())+2),"") -> Affirm — Best Buy (Feb) | D33: =IFERROR(INDEX($U$200:$AR$224,10,VLOOKUP($C$15,$I$100:$T$103,12,FALSE())+3),"") -> 46327 | E33: =IFERROR(INDEX($U$200:$AR$224,10,VLOOKUP($C$15,$I$100:$T$103,12,FALSE())+4),"") -> 1160.62 | F33: =IFERROR(INDEX($U$200:$AR$224,10,VLOOKUP($C$15,$I$100:$T$103,12,FALSE())+5),"") -> 1233.16 | G33: =IFERROR(INDEX($U$200:$AR$224,10,VLOOKUP($C$15,$I$100:$T$103,12,FALSE())+6),"") -> Same-month kill! +$73/mo.
B34: =IFERROR(INDEX($U$200:$AR$224,11,VLOOKUP($C$15,$I$100:$T$103,12,FALSE())+1),"") -> 11 | C34: =IFERROR(INDEX($U$200:$AR$224,11,VLOOKUP($C$15,$I$100:$T$103,12,FALSE())+2),"") -> Affirm — Shady Rays | D34: =IFERROR(INDEX($U$200:$AR$224,11,VLOOKUP($C$15,$I$100:$T$103,12,FALSE())+3),"") -> 46327 | E34: =IFERROR(INDEX($U$200:$AR$224,11,VLOOKUP($C$15,$I$100:$T$103,12,FALSE())+4),"") -> 114.71 | F34: =IFERROR(INDEX($U$200:$AR$224,11,VLOOKUP($C$15,$I$100:$T$103,12,FALSE())+5),"") -> 133.82 | G34: =IFERROR(INDEX($U$200:$AR$224,11,VLOOKUP($C$15,$I$100:$T$103,12,FALSE())+6),"") -> Same-month kill! +$19/mo.
B35: =IFERROR(INDEX($U$200:$AR$224,12,VLOOKUP($C$15,$I$100:$T$103,12,FALSE())+1),"") -> 12 | C35: =IFERROR(INDEX($U$200:$AR$224,12,VLOOKUP($C$15,$I$100:$T$103,12,FALSE())+2),"") -> Discover | D35: =IFERROR(INDEX($U$200:$AR$224,12,VLOOKUP($C$15,$I$100:$T$103,12,FALSE())+3),"") -> 46357 | E35: =IFERROR(INDEX($U$200:$AR$224,12,VLOOKUP($C$15,$I$100:$T$103,12,FALSE())+4),"") -> 2758 | F35: =IFERROR(INDEX($U$200:$AR$224,12,VLOOKUP($C$15,$I$100:$T$103,12,FALSE())+5),"") -> 2838 | G35: =IFERROR(INDEX($U$200:$AR$224,12,VLOOKUP($C$15,$I$100:$T$103,12,FALSE())+6),"") -> +$80/mo to next attack.
B36: =IFERROR(INDEX($U$200:$AR$224,13,VLOOKUP($C$15,$I$100:$T$103,12,FALSE())+1),"") -> 13 | C36: =IFERROR(INDEX($U$200:$AR$224,13,VLOOKUP($C$15,$I$100:$T$103,12,FALSE())+2),"") -> Credit One Bank | D36: =IFERROR(INDEX($U$200:$AR$224,13,VLOOKUP($C$15,$I$100:$T$103,12,FALSE())+3),"") -> 46357 | E36: =IFERROR(INDEX($U$200:$AR$224,13,VLOOKUP($C$15,$I$100:$T$103,12,FALSE())+4),"") -> 300 | F36: =IFERROR(INDEX($U$200:$AR$224,13,VLOOKUP($C$15,$I$100:$T$103,12,FALSE())+5),"") -> 308.25 | G36: =IFERROR(INDEX($U$200:$AR$224,13,VLOOKUP($C$15,$I$100:$T$103,12,FALSE())+6),"") -> Same-month kill! +$8/mo.
B37: =IFERROR(INDEX($U$200:$AR$224,14,VLOOKUP($C$15,$I$100:$T$103,12,FALSE())+1),"") -> 14 | C37: =IFERROR(INDEX($U$200:$AR$224,14,VLOOKUP($C$15,$I$100:$T$103,12,FALSE())+2),"") -> PayPal Credit (Hannah) / Synchrony | D37: =IFERROR(INDEX($U$200:$AR$224,14,VLOOKUP($C$15,$I$100:$T$103,12,FALSE())+3),"") -> 46357 | E37: =IFERROR(INDEX($U$200:$AR$224,14,VLOOKUP($C$15,$I$100:$T$103,12,FALSE())+4),"") -> 3116.13 | F37: =IFERROR(INDEX($U$200:$AR$224,14,VLOOKUP($C$15,$I$100:$T$103,12,FALSE())+5),"") -> 3215.13 | G37: =IFERROR(INDEX($U$200:$AR$224,14,VLOOKUP($C$15,$I$100:$T$103,12,FALSE())+6),"") -> Same-month kill! +$99/mo.
B38: =IFERROR(INDEX($U$200:$AR$224,15,VLOOKUP($C$15,$I$100:$T$103,12,FALSE())+1),"") -> 15 | C38: =IFERROR(INDEX($U$200:$AR$224,15,VLOOKUP($C$15,$I$100:$T$103,12,FALSE())+2),"") -> PayPal Credit (Brad) / Synchrony | D38: =IFERROR(INDEX($U$200:$AR$224,15,VLOOKUP($C$15,$I$100:$T$103,12,FALSE())+3),"") -> 46388 | E38: =IFERROR(INDEX($U$200:$AR$224,15,VLOOKUP($C$15,$I$100:$T$103,12,FALSE())+4),"") -> 1570.31 | F38: =IFERROR(INDEX($U$200:$AR$224,15,VLOOKUP($C$15,$I$100:$T$103,12,FALSE())+5),"") -> 1614.31 | G38: =IFERROR(INDEX($U$200:$AR$224,15,VLOOKUP($C$15,$I$100:$T$103,12,FALSE())+6),"") -> +$44/mo to next attack.
B39: =IFERROR(INDEX($U$200:$AR$224,16,VLOOKUP($C$15,$I$100:$T$103,12,FALSE())+1),"") -> 16 | C39: =IFERROR(INDEX($U$200:$AR$224,16,VLOOKUP($C$15,$I$100:$T$103,12,FALSE())+2),"") -> Amex Blue Cash Preferred | D39: =IFERROR(INDEX($U$200:$AR$224,16,VLOOKUP($C$15,$I$100:$T$103,12,FALSE())+3),"") -> 46388 | E39: =IFERROR(INDEX($U$200:$AR$224,16,VLOOKUP($C$15,$I$100:$T$103,12,FALSE())+4),"") -> 1015.61 | F39: =IFERROR(INDEX($U$200:$AR$224,16,VLOOKUP($C$15,$I$100:$T$103,12,FALSE())+5),"") -> 1055.61 | G39: =IFERROR(INDEX($U$200:$AR$224,16,VLOOKUP($C$15,$I$100:$T$103,12,FALSE())+6),"") -> Same-month kill! +$40/mo.
B40: =IFERROR(INDEX($U$200:$AR$224,17,VLOOKUP($C$15,$I$100:$T$103,12,FALSE())+1),"") -> 17 | C40: =IFERROR(INDEX($U$200:$AR$224,17,VLOOKUP($C$15,$I$100:$T$103,12,FALSE())+2),"") -> Chase Amazon Prime Visa | D40: =IFERROR(INDEX($U$200:$AR$224,17,VLOOKUP($C$15,$I$100:$T$103,12,FALSE())+3),"") -> 46388 | E40: =IFERROR(INDEX($U$200:$AR$224,17,VLOOKUP($C$15,$I$100:$T$103,12,FALSE())+4),"") -> 654.42 | F40: =IFERROR(INDEX($U$200:$AR$224,17,VLOOKUP($C$15,$I$100:$T$103,12,FALSE())+5),"") -> 708.41 | G40: =IFERROR(INDEX($U$200:$AR$224,17,VLOOKUP($C$15,$I$100:$T$103,12,FALSE())+6),"") -> Same-month kill! +$54/mo.
B41: =IFERROR(INDEX($U$200:$AR$224,18,VLOOKUP($C$15,$I$100:$T$103,12,FALSE())+1),"") -> 18 | C41: =IFERROR(INDEX($U$200:$AR$224,18,VLOOKUP($C$15,$I$100:$T$103,12,FALSE())+2),"") -> Apple Card (Goldman Sachs) | D41: =IFERROR(INDEX($U$200:$AR$224,18,VLOOKUP($C$15,$I$100:$T$103,12,FALSE())+3),"") -> 46419 | E41: =IFERROR(INDEX($U$200:$AR$224,18,VLOOKUP($C$15,$I$100:$T$103,12,FALSE())+4),"") -> 7477.57 | F41: =IFERROR(INDEX($U$200:$AR$224,18,VLOOKUP($C$15,$I$100:$T$103,12,FALSE())+5),"") -> 7743.07 | G41: =IFERROR(INDEX($U$200:$AR$224,18,VLOOKUP($C$15,$I$100:$T$103,12,FALSE())+6),"") -> Big payoff — $266/mo joins war chest.
B42: =IFERROR(INDEX($U$200:$AR$224,19,VLOOKUP($C$15,$I$100:$T$103,12,FALSE())+1),"") -> 19 | C42: =IFERROR(INDEX($U$200:$AR$224,19,VLOOKUP($C$15,$I$100:$T$103,12,FALSE())+2),"") -> Affirm — Ridge | D42: =IFERROR(INDEX($U$200:$AR$224,19,VLOOKUP($C$15,$I$100:$T$103,12,FALSE())+3),"") -> 46419 | E42: =IFERROR(INDEX($U$200:$AR$224,19,VLOOKUP($C$15,$I$100:$T$103,12,FALSE())+4),"") -> 504.15 | F42: =IFERROR(INDEX($U$200:$AR$224,19,VLOOKUP($C$15,$I$100:$T$103,12,FALSE())+5),"") -> 560.17 | G42: =IFERROR(INDEX($U$200:$AR$224,19,VLOOKUP($C$15,$I$100:$T$103,12,FALSE())+6),"") -> Same-month kill! +$56/mo.
B43: =IFERROR(INDEX($U$200:$AR$224,20,VLOOKUP($C$15,$I$100:$T$103,12,FALSE())+1),"") -> 20 | C43: =IFERROR(INDEX($U$200:$AR$224,20,VLOOKUP($C$15,$I$100:$T$103,12,FALSE())+2),"") -> Affirm — Target | D43: =IFERROR(INDEX($U$200:$AR$224,20,VLOOKUP($C$15,$I$100:$T$103,12,FALSE())+3),"") -> 46419 | E43: =IFERROR(INDEX($U$200:$AR$224,20,VLOOKUP($C$15,$I$100:$T$103,12,FALSE())+4),"") -> 183.47 | F43: =IFERROR(INDEX($U$200:$AR$224,20,VLOOKUP($C$15,$I$100:$T$103,12,FALSE())+5),"") -> 203.85 | G43: =IFERROR(INDEX($U$200:$AR$224,20,VLOOKUP($C$15,$I$100:$T$103,12,FALSE())+6),"") -> Same-month kill! +$20/mo.
B44: =IFERROR(INDEX($U$200:$AR$224,21,VLOOKUP($C$15,$I$100:$T$103,12,FALSE())+1),"") -> 21 | C44: =IFERROR(INDEX($U$200:$AR$224,21,VLOOKUP($C$15,$I$100:$T$103,12,FALSE())+2),"") -> Affirm — Shokz | D44: =IFERROR(INDEX($U$200:$AR$224,21,VLOOKUP($C$15,$I$100:$T$103,12,FALSE())+3),"") -> 46419 | E44: =IFERROR(INDEX($U$200:$AR$224,21,VLOOKUP($C$15,$I$100:$T$103,12,FALSE())+4),"") -> 182.14 | F44: =IFERROR(INDEX($U$200:$AR$224,21,VLOOKUP($C$15,$I$100:$T$103,12,FALSE())+5),"") -> 200.36 | G44: =IFERROR(INDEX($U$200:$AR$224,21,VLOOKUP($C$15,$I$100:$T$103,12,FALSE())+6),"") -> Same-month kill! +$18/mo.
B45: =IFERROR(INDEX($U$200:$AR$224,22,VLOOKUP($C$15,$I$100:$T$103,12,FALSE())+1),"") -> 22 | C45: =IFERROR(INDEX($U$200:$AR$224,22,VLOOKUP($C$15,$I$100:$T$103,12,FALSE())+2),"") -> Upstart Loan | D45: =IFERROR(INDEX($U$200:$AR$224,22,VLOOKUP($C$15,$I$100:$T$103,12,FALSE())+3),"") -> 46539 | E45: =IFERROR(INDEX($U$200:$AR$224,22,VLOOKUP($C$15,$I$100:$T$103,12,FALSE())+4),"") -> 32000 | F45: =IFERROR(INDEX($U$200:$AR$224,22,VLOOKUP($C$15,$I$100:$T$103,12,FALSE())+5),"") -> 33309.17 | G45: =IFERROR(INDEX($U$200:$AR$224,22,VLOOKUP($C$15,$I$100:$T$103,12,FALSE())+6),"") -> Big payoff — $1309/mo joins war chest.
B46: =IFERROR(INDEX($U$200:$AR$224,23,VLOOKUP($C$15,$I$100:$T$103,12,FALSE())+1),"") -> 23 | C46: =IFERROR(INDEX($U$200:$AR$224,23,VLOOKUP($C$15,$I$100:$T$103,12,FALSE())+2),"") -> Affirm — Tonal | D46: =IFERROR(INDEX($U$200:$AR$224,23,VLOOKUP($C$15,$I$100:$T$103,12,FALSE())+3),"") -> 46539 | E46: =IFERROR(INDEX($U$200:$AR$224,23,VLOOKUP($C$15,$I$100:$T$103,12,FALSE())+4),"") -> 4184.82 | F46: =IFERROR(INDEX($U$200:$AR$224,23,VLOOKUP($C$15,$I$100:$T$103,12,FALSE())+5),"") -> 4324.32 | G46: =IFERROR(INDEX($U$200:$AR$224,23,VLOOKUP($C$15,$I$100:$T$103,12,FALSE())+6),"") -> Same-month kill! +$140/mo.
B47: =IFERROR(INDEX($U$200:$AR$224,24,VLOOKUP($C$15,$I$100:$T$103,12,FALSE())+1),"") -> 24 | C47: =IFERROR(INDEX($U$200:$AR$224,24,VLOOKUP($C$15,$I$100:$T$103,12,FALSE())+2),"") -> Affirm — Peloton | D47: =IFERROR(INDEX($U$200:$AR$224,24,VLOOKUP($C$15,$I$100:$T$103,12,FALSE())+3),"") -> 46569 | E47: =IFERROR(INDEX($U$200:$AR$224,24,VLOOKUP($C$15,$I$100:$T$103,12,FALSE())+4),"") -> 3553.86 | F47: =IFERROR(INDEX($U$200:$AR$224,24,VLOOKUP($C$15,$I$100:$T$103,12,FALSE())+5),"") -> 3661.61 | G47: =IFERROR(INDEX($U$200:$AR$224,24,VLOOKUP($C$15,$I$100:$T$103,12,FALSE())+6),"") -> +$108/mo to next attack.
B48: =IFERROR(INDEX($U$200:$AR$224,25,VLOOKUP($C$15,$I$100:$T$103,12,FALSE())+1),"") -> 25 | C48: =IFERROR(INDEX($U$200:$AR$224,25,VLOOKUP($C$15,$I$100:$T$103,12,FALSE())+2),"") -> Affirm — Amazon | D48: =IFERROR(INDEX($U$200:$AR$224,25,VLOOKUP($C$15,$I$100:$T$103,12,FALSE())+3),"") -> 46569 | E48: =IFERROR(INDEX($U$200:$AR$224,25,VLOOKUP($C$15,$I$100:$T$103,12,FALSE())+4),"") -> 1069.37 | F48: =IFERROR(INDEX($U$200:$AR$224,25,VLOOKUP($C$15,$I$100:$T$103,12,FALSE())+5),"") -> 1136.3 | G48: =IFERROR(INDEX($U$200:$AR$224,25,VLOOKUP($C$15,$I$100:$T$103,12,FALSE())+6),"") -> 🎉 DEBT FREE!
I100: Just Minimums | J100: 37 | K100: 34132.168 | L100: Affirm — Shady Rays | M100: Affirm — Ridge | N100: Affirm — Target | O100: 7 | P100: 10 | Q100: 10 | R100: Pay $115 → Affirm — Shady Rays by Nov 2026 | S100: That kills it, frees up $19/mo for the next attack. | T100: 0
I101: Conservative | J101: 22 | K101: 18272.58 | L101: Mattress Firm / Synchrony Home | M101: Ashley Furniture / Synchrony | N101: Best Buy / Citi | O101: 2 | P101: 2 | Q101: 3 | R101: Pay $1,583 → Mattress Firm / Synchrony Home AND $934 → Ashley Furniture / Synchrony | S101: You have $1,500/mo extra. Kills BOTH this month — over $2,517 of debt gone. | T101: 6
I102: Current Plan | J102: 15 | K102: 11780.352 | L102: Mattress Firm / Synchrony Home | M102: Ashley Furniture / Synchrony | N102: Best Buy / Citi | O102: 1 | P102: 1 | Q102: 2 | R102: Pay $1,583 → Mattress Firm / Synchrony Home AND $934 → Ashley Furniture / Synchrony | S102: You have $3,472/mo extra. Kills BOTH this month — over $2,517 of debt gone. | T102: 12
I103: Aggressive | J103: 11 | K103: 6045.7503 | L103: Amex Platinum (Pay Over Time) | M103: Affirm — Best Buy (Dec) | N103: Capital One Quicksilver | O103: 1 | P103: 1 | Q103: 2 | R103: Pay $1,406 → Amex Platinum (Pay Over Time) AND $3,020 → Affirm — Best Buy (Dec) | S103: You have $3,472/mo extra. Kills BOTH this month — over $4,426 of debt gone. | T103: 18
U200: 1 | V200: Affirm — Shady Rays | W200: 46327 | X200: 114.71 | Y200: 133.82 | Z200: First win! Frees up $19/mo. | AA200: 1 | AB200: Mattress Firm / Synchrony Home | AC200: 46174 | AD200: 1583.49 | AE200: 1712.49 | AF200: First win! Frees up $129/mo. | AG200: 1 | AH200: Mattress Firm / Synchrony Home | AI200: 46143 | AJ200: 1583.49 | AK200: 1712.49 | AL200: First win! Frees up $129/mo. | AM200: 1 | AN200: Amex Platinum (Pay Over Time) | AO200: 46143 | AP200: 1406.09 | AQ200: 1446.09 | AR200: First win! Frees up $40/mo.
U201: 2 | V201: Affirm — Ridge | W201: 46419 | X201: 504.15 | Y201: 560.17 | Z201: +$56/mo to next attack. | AA201: 2 | AB201: Ashley Furniture / Synchrony | AC201: 46174 | AD201: 933.82 | AE201: 966.82 | AF201: Same-month kill! +$33/mo. | AG201: 2 | AH201: Ashley Furniture / Synchrony | AI201: 46143 | AJ201: 933.82 | AK201: 966.82 | AL201: Same-month kill! +$33/mo. | AM201: 2 | AN201: Affirm — Best Buy (Dec) | AO201: 46143 | AP201: 3020.12 | AQ201: 3171.13 | AR201: Same-month kill! +$151/mo.
U202: 3 | V202: Affirm — Target | W202: 46419 | X202: 183.47 | Y202: 203.85 | Z202: Same-month kill! +$20/mo. | AA202: 3 | AB202: Best Buy / Citi | AC202: 46204 | AD202: 1200 | AE202: 1229 | AF202: +$29/mo to next attack. | AG202: 3 | AH202: Best Buy / Citi | AI202: 46174 | AJ202: 1200 | AK202: 1229 | AL202: +$29/mo to next attack. | AM202: 3 | AN202: Capital One Quicksilver | AO202: 46174 | AP202: 1169.64 | AQ202: 1207.64 | AR202: +$38/mo to next attack.
U203: 4 | V203: Affirm — Shokz | W203: 46419 | X203: 182.14 | Y203: 200.36 | Z203: Same-month kill! +$18/mo. | AA203: 4 | AB203: Capital One Platinum | AC203: 46296 | AD203: 5930.94 | AE203: 6130.94 | AF203: Big payoff — $200/mo joins war chest. | AG203: 4 | AH203: Capital One Platinum | AI203: 46204 | AJ203: 5930.94 | AK203: 6130.94 | AL203: Big payoff — $200/mo joins war chest. | AM203: 4 | AN203: Affirm — Best Buy (Feb) | AO203: 46174 | AP203: 1160.62 | AQ203: 1233.16 | AR203: Same-month kill! +$73/mo.
U204: 5 | V204: Mattress Firm / Synchrony Home | W204: 46508 | X204: 1583.49 | Y204: 1712.49 | Z204: +$129/mo to next attack. | AA204: 5 | AB204: Affirm — Shady Rays | AC204: 46327 | AD204: 114.71 | AE204: 133.82 | AF204: +$19/mo to next attack. | AG204: 5 | AH204: Amex Delta SkyMiles Gold | AI204: 46266 | AJ204: 7294.06 | AK204: 7499.93 | AL204: Big payoff — $206/mo joins war chest. | AM204: 5 | AN204: Discover | AO204: 46204 | AP204: 2758 | AQ204: 2838 | AR204: +$80/mo to next attack.
U205: 6 | V205: Chase Amazon Prime Visa | W205: 46569 | X205: 654.42 | Y205: 708.41 | Z205: +$54/mo to next attack. | AA205: 6 | AB205: Amex Delta SkyMiles Gold | AC205: 46419 | AD205: 7294.06 | AE205: 7499.93 | AF205: Big payoff — $206/mo joins war chest. | AG205: 6 | AH205: Menards Big Card (Cap One) | AI205: 46296 | AJ205: 2758.32 | AK205: 2850.32 | AL205: +$92/mo to next attack. | AM205: 6 | AN205: Credit One Bank | AO205: 46204 | AP205: 300 | AQ205: 308.25 | AR205: Same-month kill! +$8/mo.
U206: 7 | V206: Ashley Furniture / Synchrony | W206: 46600 | X206: 933.82 | Y206: 966.82 | Z206: +$33/mo to next attack. | AA206: 7 | AB206: Affirm — Ridge | AC206: 46419 | AD206: 504.15 | AE206: 560.17 | AF206: Same-month kill! +$56/mo. | AG206: 7 | AH206: Amex Platinum (Pay Over Time) | AI206: 46296 | AJ206: 1406.09 | AK206: 1446.09 | AL206: Same-month kill! +$40/mo. | AM206: 7 | AN206: PayPal Credit (Hannah) / Synchrony | AO206: 46204 | AP206: 3116.13 | AQ206: 3215.13 | AR206: Same-month kill! +$99/mo.
U207: 8 | V207: Affirm — Amazon | W207: 46661 | X207: 1069.37 | Y207: 1136.3 | Z207: +$67/mo to next attack. | AA207: 8 | AB207: Affirm — Target | AC207: 46419 | AD207: 183.47 | AE207: 203.85 | AF207: Same-month kill! +$20/mo. | AG207: 8 | AH207: Affirm — Best Buy (Dec) | AI207: 46327 | AJ207: 3020.12 | AK207: 3171.13 | AL207: +$151/mo to next attack. | AM207: 8 | AN207: PayPal Credit (Brad) / Synchrony | AO207: 46235 | AP207: 1570.31 | AQ207: 1614.31 | AR207: +$44/mo to next attack.
U208: 9 | V208: Best Buy / Citi | W208: 46722 | X208: 1200 | Y208: 1229 | Z208: +$29/mo to next attack. | AA208: 9 | AB208: Affirm — Shokz | AC208: 46419 | AD208: 182.14 | AE208: 200.36 | AF208: Same-month kill! +$18/mo. | AG208: 9 | AH208: Capital One Quicksilver | AI208: 46327 | AJ208: 1169.64 | AK208: 1207.64 | AL208: Same-month kill! +$38/mo. | AM208: 9 | AN208: Affirm — Shady Rays | AO208: 46235 | AP208: 114.71 | AQ208: 133.82 | AR208: Same-month kill! +$19/mo.
U209: 10 | V209: Affirm — Best Buy (Feb) | W209: 46753 | X209: 1160.62 | Y209: 1233.16 | Z209: +$73/mo to next attack. | AA209: 10 | AB209: Menards Big Card (Cap One) | AC209: 46447 | AD209: 2758.32 | AE209: 2850.32 | AF209: +$92/mo to next attack. | AG209: 10 | AH209: Affirm — Best Buy (Feb) | AI209: 46327 | AJ209: 1160.62 | AK209: 1233.16 | AL209: Same-month kill! +$73/mo. | AM209: 10 | AN209: Amex Blue Cash Preferred | AO209: 46235 | AP209: 1015.61 | AQ209: 1055.61 | AR209: Same-month kill! +$40/mo.
U210: 11 | V210: Capital One Platinum | W210: 46935 | X210: 5930.94 | Y210: 6130.94 | Z210: Big payoff — $200/mo joins war chest. | AA210: 11 | AB210: Amex Platinum (Pay Over Time) | AC210: 46447 | AD210: 1406.09 | AE210: 1446.09 | AF210: Same-month kill! +$40/mo. | AG210: 11 | AH210: Affirm — Shady Rays | AI210: 46327 | AJ210: 114.71 | AK210: 133.82 | AL210: Same-month kill! +$19/mo. | AM210: 11 | AN210: Chase Amazon Prime Visa | AO210: 46235 | AP210: 654.42 | AQ210: 708.41 | AR210: Same-month kill! +$54/mo.
U211: 12 | V211: Affirm — Best Buy (Dec) | W211: 46966 | X211: 3020.12 | Y211: 3171.13 | Z211: +$151/mo to next attack. | AA211: 12 | AB211: Affirm — Best Buy (Dec) | AC211: 46478 | AD211: 3020.12 | AE211: 3171.13 | AF211: +$151/mo to next attack. | AG211: 12 | AH211: Discover | AI211: 46357 | AJ211: 2758 | AK211: 2838 | AL211: +$80/mo to next attack. | AM211: 12 | AN211: Apple Card (Goldman Sachs) | AO211: 46266 | AP211: 7477.57 | AQ211: 7743.07 | AR211: Big payoff — $266/mo joins war chest.
... U218: 19 | V218: Credit One Bank | W218: 47178 | X218: 300 | Y218: 308.25 | Z218: Same-month kill! +$8/mo. | AA218: 19 | AB218: Chase Amazon Prime Visa | AC218: 46569 | AD218: 654.42 | AE218: 708.41 | AF218: Same-month kill! +$54/mo. | AG218: 19 | AH218: Affirm — Ridge | AI218: 46419 | AJ218: 504.15 | AK218: 560.17 | AL218: Same-month kill! +$56/mo. | AM218: 19 | AN218: Affirm — Amazon | AO218: 46447 | AP218: 1069.37 | AQ218: 1136.3 | AR218: 🎉 DEBT FREE!
U219: 20 | V219: PayPal Credit (Hannah) / Synchrony | W219: 47178 | X219: 3116.13 | Y219: 3215.13 | Z219: Same-month kill! +$99/mo. | AA219: 20 | AB219: Amex Blue Cash Preferred | AC219: 46600 | AD219: 1015.61 | AE219: 1055.61 | AF219: +$40/mo to next attack. | AG219: 20 | AH219: Affirm — Target | AI219: 46419 | AJ219: 183.47 | AK219: 203.85 | AL219: Same-month kill! +$20/mo.
U220: 21 | V220: PayPal Credit (Brad) / Synchrony | W220: 47209 | X220: 1570.31 | Y220: 1614.31 | Z220: +$44/mo to next attack. | AA220: 21 | AB220: Apple Card (Goldman Sachs) | AC220: 46631 | AD220: 7477.57 | AE220: 7743.07 | AF220: Big payoff — $266/mo joins war chest. | AG220: 21 | AH220: Affirm — Shokz | AI220: 46419 | AJ220: 182.14 | AK220: 200.36 | AL220: Same-month kill! +$18/mo.
U221: 22 | V221: Amex Blue Cash Preferred | W221: 47209 | X221: 1015.61 | Y221: 1055.61 | Z221: Same-month kill! +$40/mo. | AA221: 22 | AB221: Affirm — Amazon | AC221: 46661 | AD221: 1069.37 | AE221: 1136.3 | AF221: +$67/mo to next attack. | AG221: 22 | AH221: Upstart Loan | AI221: 46539 | AJ221: 32000 | AK221: 33309.17 | AL221: Big payoff — $1309/mo joins war chest.
U222: 23 | V222: Apple Card (Goldman Sachs) | W222: 47209 | X222: 7477.57 | Y222: 7743.07 | Z222: Same-month kill! +$266/mo. | AA222: 23 | AB222: Upstart Loan | AC222: 46753 | AD222: 32000 | AE222: 33309.17 | AF222: Big payoff — $1309/mo joins war chest. | AG222: 23 | AH222: Affirm — Tonal | AI222: 46539 | AJ222: 4184.82 | AK222: 4324.32 | AL222: Same-month kill! +$140/mo.
U223: 24 | V223: Affirm — Tonal | W223: 47209 | X223: 4184.82 | Y223: 4324.32 | Z223: Same-month kill! +$140/mo. | AA223: 24 | AB223: Affirm — Tonal | AC223: 46784 | AD223: 4184.82 | AE223: 4324.32 | AF223: +$140/mo to next attack. | AG223: 24 | AH223: Affirm — Peloton | AI223: 46569 | AJ223: 3553.86 | AK223: 3661.61 | AL223: +$108/mo to next attack.
U224: 25 | V224: Affirm — Peloton | W224: 47239 | X224: 3553.86 | Y224: 3661.61 | Z224: 🎉 DEBT FREE! | AA224: 25 | AB224: Affirm — Peloton | AC224: 46784 | AD224: 3553.86 | AE224: 3661.61 | AF224: 🎉 DEBT FREE! | AG224: 25 | AH224: Affirm — Amazon | AI224: 46569 | AJ224: 1069.37 | AK224: 1136.3 | AL224: 🎉 DEBT FREE!

Sheet Payments
A1: PAYMENTS & TRANSACTIONS
A2: Starting Balance: | C2: 2954.7 | D2: Current Balance: | E2: =IFERROR(LOOKUP(2,1/(F6:F505<>""),G6:G505),C2) -> 3408.09 | F2: Statement Date: | G2: 46141
A3: Log every transaction. Bulk-paste from bank CSV. Pick Type (Income/Expense) and Creditor for each row.
A5: # | B5: Date | C5: Description (from bank) | D5: Type | E5: Creditor / Category | F5: Amount | G5: Running Balance | H5: Notes / Match Rule | I5: Month | J5: Year
A6: 1 | B6: 46113 | C6: APPLECARD GSBANK PAYMENT 2228596 WEB ID: 9999999999 | D6: Expense | E6: Apple Card (Goldman Sachs) | F6: 227.5 | G6: 2727.2 | H6: APPLECARD GSBANK → Apple Card (Goldman Sachs) | I6: =IF(B6="","",TEXT(B6,"mmm")) -> Apr | J6: =IF(B6="","",YEAR(B6)) -> 2026
A7: 2 | B7: 46113 | C7: PAYPAL INST XFER DOORDASH MOOYAH WEB ID: PAYPALSI77 | D7: Expense | E7: DoorDash & Delivery | F7: 42.53 | G7: 2684.67 | H7: DOORDASH → DoorDash & Delivery | I7: =IF(B7="","",TEXT(B7,"mmm")) -> Apr | J7: =IF(B7="","",YEAR(B7)) -> 2026
A8: 3 | B8: 46113 | C8: VENMO PAYMENT 1049294046835 WEB ID: 3264681992 | D8: Expense | E8: Venmo Transfer | F8: 16.25 | G8: 2668.42 | H8: VENMO → Venmo Transfer | I8: =IF(B8="","",TEXT(B8,"mmm")) -> Apr | J8: =IF(B8="","",YEAR(B8)) -> 2026
A9: 4 | B9: 46113 | C9: CAPITAL ONE CRCARDPMT CA0CBEAA436C428 WEB ID: 9541719318 | D9: Expense | E9: Capital One Platinum | F9: 500 | G9: 2168.42 | H9: CAP ONE @ $500 → Capital One Platinum | I9: =IF(B9="","",TEXT(B9,"mmm")) -> Apr | J9: =IF(B9="","",YEAR(B9)) -> 2026
A10: 5 | B10: 46114 | C10: UPSTART NETWORK CORNING / 1028845 WEB ID: 45466061FN | D10: Expense | E10: Upstart Loan | F10: 1309.17 | G10: 859.25 | H10: UPSTART NETWORK → Upstart Loan | I10: =IF(B10="","",TEXT(B10,"mmm")) -> Apr | J10: =IF(B10="","",YEAR(B10)) -> 2026
A11: 6 | B11: 46114 | C11: AMERICAN EXPRESS ACH PMT W3556 WEB ID: 2005032111 | D11: Expense | E11: Amex Delta SkyMiles Gold | F11: 600 | G11: 259.25 | H11: AMEX @ $600 → Amex Delta SkyMiles Gold | I11: =IF(B11="","",TEXT(B11,"mmm")) -> Apr | J11: =IF(B11="","",YEAR(B11)) -> 2026
A12: 7 | B12: 46115 | C12: KFI STAFFING, LL PAYROLL PPD ID: 874304726 | D12: Income | E12: Hannah's Paycheck (KFI) | F12: 3909.8 | G12: 4169.05 | H12: KFI STAFFING → Hannah's Paycheck (KFI) | I12: =IF(B12="","",TEXT(B12,"mmm")) -> Apr | J12: =IF(B12="","",YEAR(B12)) -> 2026
A13: 8 | B13: 46115 | C13: STATE FARM RO 27 SFPP PPD ID: 9000307001 | D13: Expense | F13: 128.59 | G13: 4040.46 | H13: STATE FARM → Auto Insurance (State Farm) | I13: =IF(B13="","",TEXT(B13,"mmm")) -> Apr | J13: =IF(B13="","",YEAR(B13)) -> 2026
A14: 9 | B14: 46115 | C14: PAYPAL PURCHASE PLAYSTATION WEB ID: PAYPALSI77 | D14: Expense | E14: PayPal Credit (Brad) / Synchrony | F14: 18.98 | G14: 4021.48 | H14: PLAYSTATION → Gaming subs | I14: =IF(B14="","",TEXT(B14,"mmm")) -> Apr | J14: =IF(B14="","",YEAR(B14)) -> 2026
A15: 10 | B15: 46115 | C15: CAPITAL ONE CRCARDPMT CA040925E95DF6A WEB ID: 9541719318 | D15: Expense | E15: Capital One Platinum | F15: 91 | G15: 3930.48 | H15: CAP ONE @ $91 → Capital One Platinum | I15: =IF(B15="","",TEXT(B15,"mmm")) -> Apr | J15: =IF(B15="","",YEAR(B15)) -> 2026
A16: 11 | B16: 46115 | C16: FIGURE LENDING L FIGUREPAYM PPD ID: 1191069000 | D16: Expense | E16: HELOC (Figure) | F16: 677.4 | G16: 3253.08 | H16: FIGURE LENDING → HELOC (Figure) | I16: =IF(B16="","",TEXT(B16,"mmm")) -> Apr | J16: =IF(B16="","",YEAR(B16)) -> 2026
A17: 12 | B17: 46115 | C17: PAYPAL PURCHASE STITCHFIXIN WEB ID: PAYPALSI77 | D17: Expense | E17: PayPal Credit (Brad) / Synchrony | F17: 42.77 | G17: 3210.31 | H17: STITCHFIXIN → Clothing (Threadbeast/Stitch/Lulu) | I17: =IF(B17="","",TEXT(B17,"mmm")) -> Apr | J17: =IF(B17="","",YEAR(B17)) -> 2026
A18: 13 | B18: 46118 | C18: PAYPAL TRANSFER PPD ID: PAYPALSD11 | D18: Income | E18: PayPal Credit (Brad) / Synchrony | F18: 87.48 | G18: 3297.79 | H18: PAYPAL → PayPal Credit (Brad) / Synchrony | I18: =IF(B18="","",TEXT(B18,"mmm")) -> Apr | J18: =IF(B18="","",YEAR(B18)) -> 2026
A19: 14 | B19: 46118 | C19: PAYPAL TRANSFER PPD ID: PAYPALSD11 | D19: Income | E19: PayPal Credit (Brad) / Synchrony | F19: 69.29 | G19: 3367.08 | H19: PAYPAL → PayPal Credit (Brad) / Synchrony | I19: =IF(B19="","",TEXT(B19,"mmm")) -> Apr | J19: =IF(B19="","",YEAR(B19)) -> 2026
A20: 15 | B20: 46118 | C20: PAYPAL TRANSFER PPD ID: PAYPALSD11 | D20: Income | E20: PayPal Credit (Brad) / Synchrony | F20: 9.02 | G20: 3376.1 | H20: PAYPAL → PayPal Credit (Brad) / Synchrony | I20: =IF(B20="","",TEXT(B20,"mmm")) -> Apr | J20: =IF(B20="","",YEAR(B20)) -> 2026
A21: 16 | B21: 46118 | C21: PAYPAL TRANSFER PPD ID: PAYPALSD11 | D21: Income | E21: PayPal Credit (Brad) / Synchrony | F21: 3.92 | G21: 3380.02 | H21: PAYPAL → PayPal Credit (Brad) / Synchrony | I21: =IF(B21="","",TEXT(B21,"mmm")) -> Apr | J21: =IF(B21="","",YEAR(B21)) -> 2026
A22: 17 | B22: 46118 | C22: PAYPAL TRANSFER PPD ID: PAYPALSD11 | D22: Income | E22: PayPal Credit (Brad) / Synchrony | F22: 3.65 | G22: 3383.67 | H22: PAYPAL → PayPal Credit (Brad) / Synchrony | I22: =IF(B22="","",TEXT(B22,"mmm")) -> Apr | J22: =IF(B22="","",YEAR(B22)) -> 2026
A23: 18 | B23: 46118 | C23: PAYPAL TRANSFER PPD ID: PAYPALSD11 | D23: Income | E23: PayPal Credit (Brad) / Synchrony | F23: 2.85 | G23: 3386.52 | H23: PAYPAL → PayPal Credit (Brad) / Synchrony | I23: =IF(B23="","",TEXT(B23,"mmm")) -> Apr | J23: =IF(B23="","",YEAR(B23)) -> 2026
A24: 19 | B24: 46118 | C24: PAYPAL TRANSFER PPD ID: PAYPALSD11 | D24: Income | E24: PayPal Credit (Brad) / Synchrony | F24: 0.54 | G24: 3387.06 | H24: PAYPAL → PayPal Credit (Brad) / Synchrony | I24: =IF(B24="","",TEXT(B24,"mmm")) -> Apr | J24: =IF(B24="","",YEAR(B24)) -> 2026
A25: 20 | B25: 46118 | C25: STATE FARM RO 27 CPC-CLIENT PPD ID: 9000313004 | D25: Expense | F25: 121.54 | G25: 3265.52 | H25: STATE FARM → Auto Insurance (State Farm) | I25: =IF(B25="","",TEXT(B25,"mmm")) -> Apr | J25: =IF(B25="","",YEAR(B25)) -> 2026
A26: 21 | B26: 46118 | C26: Online Transfer to GMR ...0324 transaction#: 28716405797 04/06 | D26: Transfer | E26: Savings Transfer (out) | F26: -80 | G26: 3185.52 | H26: ONLINE TRANSFER TO → Savings Transfer (out) | I26: =IF(B26="","",TEXT(B26,"mmm")) -> Apr | J26: =IF(B26="","",YEAR(B26)) -> 2026
A27: 22 | B27: 46118 | C27: Online Transfer to GMR ...0324 transaction#: 28716411133 04/06 | D27: Transfer | E27: Savings Transfer (out) | F27: -10 | G27: 3175.52 | H27: ONLINE TRANSFER TO → Savings Transfer (out) | I27: =IF(B27="","",TEXT(B27,"mmm")) -> Apr | J27: =IF(B27="","",YEAR(B27)) -> 2026
A28: 23 | B28: 46118 | C28: Online Transfer to SAV ...9037 transaction#: 28716437177 04/06 | D28: Transfer | E28: Savings Transfer (out) | F28: -20 | G28: 3155.52 | H28: ONLINE TRANSFER TO → Savings Transfer (out) | I28: =IF(B28="","",TEXT(B28,"mmm")) -> Apr | J28: =IF(B28="","",YEAR(B28)) -> 2026
A29: 24 | B29: 46118 | C29: UW Credit Union Loan Pay 000001836855588 WEB ID: 1222528268 | D29: Expense | E29: Hannah's Car Payment (UW Credit Union) | F29: 651.55 | G29: 2503.97 | H29: UW CREDIT UNION → UW Credit Union (Hannah's Car) | I29: =IF(B29="","",TEXT(B29,"mmm")) -> Apr | J29: =IF(B29="","",YEAR(B29)) -> 2026
A30: 25 | B30: 46118 | C30: CHASE CREDIT CRD AUTOPAY PPD ID: 4760039224 | D30: Expense | E30: Chase Amazon Prime Visa | F30: 434.31 | G30: 2069.66 | H30: CHASE CREDIT CRD → Chase Amazon Prime Visa | I30: =IF(B30="","",TEXT(B30,"mmm")) -> Apr | J30: =IF(B30="","",YEAR(B30)) -> 2026
A31: 26 | B31: 46118 | C31: BEST BUY AUTO PYMT 721951705420517 WEB ID: CITIAUTFDR | D31: Expense | F31: 29 | G31: 2040.66 | H31: CITI → Best Buy / Citi | I31: =IF(B31="","",TEXT(B31,"mmm")) -> Apr | J31: =IF(B31="","",YEAR(B31)) -> 2026
A32: 27 | B32: 46118 | C32: PAYPAL PURCHASE STARBUCKS WEB ID: PAYPALSI77 | D32: Expense | E32: PayPal Credit (Brad) / Synchrony | F32: 15 | G32: 2025.66 | H32: STARBUCKS → Coffee (Starbucks, Dunkin) | I32: =IF(B32="","",TEXT(B32,"mmm")) -> Apr | J32: =IF(B32="","",YEAR(B32)) -> 2026
A33: 28 | B33: 46118 | C33: PAYPAL PURCHASE NINTENDOAME WEB ID: PAYPALSI77 | D33: Expense | E33: PayPal Credit (Brad) / Synchrony | F33: 4.21 | G33: 2021.45 | H33: PAYPAL → PayPal Credit (Brad) / Synchrony | I33: =IF(B33="","",TEXT(B33,"mmm")) -> Apr | J33: =IF(B33="","",YEAR(B33)) -> 2026
A34: 29 | B34: 46118 | C34: AMERICAN EXPRESS ACH PMT M9698 WEB ID: 2005032111 | D34: Expense | E34: Amex Delta SkyMiles Gold | F34: 402.82 | G34: 1618.63 | H34: AMEX @ $402.82 → Amex Delta SkyMiles Gold | I34: =IF(B34="","",TEXT(B34,"mmm")) -> Apr | J34: =IF(B34="","",YEAR(B34)) -> 2026
A35: 30 | B35: 46118 | C35: AMERICAN EXPRESS ACH PMT M9212 WEB ID: 2005032111 | D35: Expense | E35: Amex Delta SkyMiles Gold | F35: 85.01 | G35: 1533.62 | H35: AMERICAN EXPRESS → Amex Delta SkyMiles Gold | I35: =IF(B35="","",TEXT(B35,"mmm")) -> Apr | J35: =IF(B35="","",YEAR(B35)) -> 2026
A36: 31 | B36: 46119 | C36: TOYOTA ACH LEASE WEB 3L0Y0OBJS80I9FC WEB ID: 3953775816 | D36: Expense | E36: Toyota Lease | F36: 672.8 | G36: 860.82 | H36: TOYOTA ACH → Toyota Lease | I36: =IF(B36="","",TEXT(B36,"mmm")) -> Apr | J36: =IF(B36="","",YEAR(B36)) -> 2026
A37: 32 | B37: 46119 | C37: PAYPAL INST XFER 1049422616723 WEB ID: PAYPALSI77 | D37: Expense | E37: PayPal Credit (Brad) / Synchrony | F37: 105 | G37: 755.82 | H37: PAYPAL → PayPal Credit (Brad) / Synchrony | I37: =IF(B37="","",TEXT(B37,"mmm")) -> Apr | J37: =IF(B37="","",YEAR(B37)) -> 2026
A38: 33 | B38: 46120 | C38: BRGHTWHL* Aldo.. PURCHASE B ST-U6B8C1H0S5E2 WEB ID: 1800948598 | D38: Expense | E38: Shopping (Misc) | F38: 200 | G38: 555.82 | H38: BRGHTWHL → Shopping (Misc) | I38: =IF(B38="","",TEXT(B38,"mmm")) -> Apr | J38: =IF(B38="","",YEAR(B38)) -> 2026
A39: 34 | B39: 46120 | C39: DISCOVER E-PAYMENT 2877 WEB ID: 2510020270 | D39: Expense | E39: Discover | F39: 184.7 | G39: 371.12 | H39: DISCOVER → Discover | I39: =IF(B39="","",TEXT(B39,"mmm")) -> Apr | J39: =IF(B39="","",YEAR(B39)) -> 2026
A40: 35 | B40: 46121 | C40: EXACT SCIENCES PAYROLL PPD ID: 9111111103 | D40: Income | E40: Brad's Paycheck (Exact) | F40: 2274.43 | G40: 2645.55 | H40: EXACT SCIENCES → Brad's Paycheck (Exact) | I40: =IF(B40="","",TEXT(B40,"mmm")) -> Apr | J40: =IF(B40="","",YEAR(B40)) -> 2026
A41: 36 | B41: 46121 | C41: KWIK TRIP INC PAYMENT 000093008198591 WEB ID: 9161597801 | D41: Expense | E41: Gasoline (Kwik Trip / Woodmans) | F41: 200 | G41: 2445.55 | H41: KWIK TRIP → Gasoline (Kwik Trip / Woodmans) | I41: =IF(B41="","",TEXT(B41,"mmm")) -> Apr | J41: =IF(B41="","",YEAR(B41)) -> 2026
A42: 37 | B42: 46121 | C42: FID BKG SVC LLC MONEYLINE PPD ID: 0368004600 | D42: Expense | E42: Fidelity Investment | F42: 50 | G42: 2395.55 | H42: FID BKG SVC → Fidelity Investment | I42: =IF(B42="","",TEXT(B42,"mmm")) -> Apr | J42: =IF(B42="","",YEAR(B42)) -> 2026
A43: 38 | B43: 46121 | C43: SYNCHRONY BANK PAYMENT 601918212201035 WEB ID: 1061537262 | D43: Expense | E43: Mattress Firm / Synchrony Home | F43: 200 | G43: 2195.55 | H43: SYNCHRONY @ $200 → Mattress Firm / Synchrony Home | I43: =IF(B43="","",TEXT(B43,"mmm")) -> Apr | J43: =IF(B43="","",YEAR(B43)) -> 2026
... A58: 53 | B58: 46126 | C58: PAYPAL PURCHASE PLAYSTATION WEB ID: PAYPALSI77 | D58: Expense | E58: PayPal Credit (Brad) / Synchrony | F58: 6.32 | G58: 1856.98 | H58: PLAYSTATION → Gaming subs | I58: =IF(B58="","",TEXT(B58,"mmm")) -> Apr | J58: =IF(B58="","",YEAR(B58)) -> 2026
A59: 54 | B59: 46126 | C59: TruStage LIFE INSUR PPD ID: 007CMMLIPY | D59: Expense | F59: 95 | G59: 1761.98 | H59: TRUSTAGE → Life Insurance (Trustage) | I59: =IF(B59="","",TEXT(B59,"mmm")) -> Apr | J59: =IF(B59="","",YEAR(B59)) -> 2026
A60: 55 | B60: 46127 | C60: ODP TRANSFER FROM SAVINGS ...9128 | D60: Transfer | E60: Savings Transfer (in) | F60: 335.58 | G60: 2097.56 | H60: ODP TRANSFER → Savings Transfer (in) | I60: =IF(B60="","",TEXT(B60,"mmm")) -> Apr | J60: =IF(B60="","",YEAR(B60)) -> 2026
A61: 56 | B61: 46127 | C61: LAKEVIEW LN SRV MTG PYMT 0061850673 WEB ID: 1541322890 | D61: Expense | E61: Mortgage (Lakeview) | F61: 1989.81 | G61: 107.75 | H61: LAKEVIEW LN → Mortgage (Lakeview) | I61: =IF(B61="","",TEXT(B61,"mmm")) -> Apr | J61: =IF(B61="","",YEAR(B61)) -> 2026
A62: 57 | B62: 46127 | C62: AFFIRM.COM PAYME AFFIRM.COM ST-Z6V3X0F4U6T7 WEB ID: 1800948598 | D62: Expense | E62: Affirm — Peloton | F62: 107.75 | G62: 0 | H62: AFFIRM @ $107.75 → Affirm — Peloton | I62: =IF(B62="","",TEXT(B62,"mmm")) -> Apr | J62: =IF(B62="","",YEAR(B62)) -> 2026
A63: 58 | B63: 46128 | C63: ODP TRANSFER FROM SAVINGS ...9128 | D63: Transfer | E63: Savings Transfer (in) | F63: 452.01 | G63: 452.01 | H63: ODP TRANSFER → Savings Transfer (in) | I63: =IF(B63="","",TEXT(B63,"mmm")) -> Apr | J63: =IF(B63="","",YEAR(B63)) -> 2026
A64: 59 | B64: 46128 | C64: PAYPAL PURCHASE ANCESTRYCOM WEB ID: PAYPALSI77 | D64: Expense | E64: PayPal Credit (Brad) / Synchrony | F64: 26.36 | G64: 425.65 | H64: ANCESTRY → Ancestry.com | I64: =IF(B64="","",TEXT(B64,"mmm")) -> Apr | J64: =IF(B64="","",YEAR(B64)) -> 2026
A65: 60 | B65: 46128 | C65: VERIZON WIRELESS PAYMENTS PPD ID: 7223344794 | D65: Expense | E65: Phone (Verizon) | F65: 425.65 | G65: 0 | H65: VERIZON WIRELESS → Phone (Verizon) | I65: =IF(B65="","",TEXT(B65,"mmm")) -> Apr | J65: =IF(B65="","",YEAR(B65)) -> 2026
A66: 61 | B66: 46129 | C66: KFI STAFFING, LL PAYROLL PPD ID: 874304726 | D66: Income | E66: Hannah's Paycheck (KFI) | F66: 3819.79 | G66: 3819.79 | H66: KFI STAFFING → Hannah's Paycheck (KFI) | I66: =IF(B66="","",TEXT(B66,"mmm")) -> Apr | J66: =IF(B66="","",YEAR(B66)) -> 2026
A67: 62 | B67: 46129 | C67: PAYPAL INST XFER PYPL PAYMTHLY WEB ID: PAYPALSI77 | D67: Expense | E67: PayPal Credit (Brad) / Synchrony | F67: 59.06 | G67: 3760.73 | H67: PAYPAL → PayPal Credit (Brad) / Synchrony | I67: =IF(B67="","",TEXT(B67,"mmm")) -> Apr | J67: =IF(B67="","",YEAR(B67)) -> 2026
A68: 63 | B68: 46132 | C68: VENMO CASHOUT PPD ID: 5264681992 | D68: Income | E68: Venmo Transfer | F68: 85 | G68: 3845.73 | H68: VENMO → Venmo Transfer | I68: =IF(B68="","",TEXT(B68,"mmm")) -> Apr | J68: =IF(B68="","",YEAR(B68)) -> 2026
A69: 64 | B69: 46132 | C69: ATM WITHDRAWAL 008272 04/182251 W BR | D69: Expense | F69: 60 | G69: 3785.73 | H69: ATM WITHDRAWAL → Misc / Buffer | I69: =IF(B69="","",TEXT(B69,"mmm")) -> Apr | J69: =IF(B69="","",YEAR(B69)) -> 2026
A70: 65 | B70: 46132 | C70: AFFIRM.COM PAYME AFFIRM.COM ST-S5P7M8K7A2N6 WEB ID: 4270465600 | D70: Expense | E70: Affirm — Best Buy (Dec) | F70: 151.01 | G70: 3634.72 | H70: AFFIRM @ $151.01 → Affirm — Best Buy (Dec) | I70: =IF(B70="","",TEXT(B70,"mmm")) -> Apr | J70: =IF(B70="","",YEAR(B70)) -> 2026
A71: 66 | B71: 46132 | C71: PAYPAL PURCHASE DOORDASH DUNKIN WEB ID: PAYPALSI77 | D71: Expense | E71: DoorDash & Delivery | F71: 30.04 | G71: 3604.68 | H71: DOORDASH → DoorDash & Delivery | I71: =IF(B71="","",TEXT(B71,"mmm")) -> Apr | J71: =IF(B71="","",YEAR(B71)) -> 2026
A72: 67 | B72: 46132 | C72: AFFIRM.COM PAYME AFFIRM.COM ST-P2Y2J7K9D2C3 WEB ID: 1800948598 | D72: Expense | E72: Affirm — Shokz | F72: 18.22 | G72: 3586.46 | H72: AFFIRM @ $18.22 → Affirm — Shokz | I72: =IF(B72="","",TEXT(B72,"mmm")) -> Apr | J72: =IF(B72="","",YEAR(B72)) -> 2026
A73: 68 | B73: 46132 | C73: CAPITAL ONE CRCARDPMT CA00822C50CA9D3 WEB ID: 9541719318 | D73: Expense | E73: Capital One Quicksilver | F73: 34 | G73: 3552.46 | H73: CAP ONE @ $34 → Capital One Quicksilver | I73: =IF(B73="","",TEXT(B73,"mmm")) -> Apr | J73: =IF(B73="","",YEAR(B73)) -> 2026
A74: 69 | B74: 46132 | C74: Online Transfer to GMR ...0324 transaction#: 28905703675 04/20 | D74: Transfer | E74: Savings Transfer (out) | F74: -10 | G74: 3542.46 | H74: ONLINE TRANSFER TO → Savings Transfer (out) | I74: =IF(B74="","",TEXT(B74,"mmm")) -> Apr | J74: =IF(B74="","",YEAR(B74)) -> 2026
A75: 70 | B75: 46132 | C75: Online Transfer to GMR ...0324 transaction#: 28905723669 04/20 | D75: Transfer | E75: Savings Transfer (out) | F75: -30 | G75: 3512.46 | H75: ONLINE TRANSFER TO → Savings Transfer (out) | I75: =IF(B75="","",TEXT(B75,"mmm")) -> Apr | J75: =IF(B75="","",YEAR(B75)) -> 2026
A76: 71 | B76: 46132 | C76: AMERICAN EXPRESS ACH PMT M1016 WEB ID: 2005032111 | D76: Expense | E76: Amex Delta SkyMiles Gold | F76: 410.32 | G76: 3102.14 | H76: AMEX @ $410.32 → Amex Delta SkyMiles Gold | I76: =IF(B76="","",TEXT(B76,"mmm")) -> Apr | J76: =IF(B76="","",YEAR(B76)) -> 2026
A77: 72 | B77: 46132 | C77: AMERICAN EXPRESS ACH PMT M1684 WEB ID: 2005032111 | D77: Expense | E77: Amex Delta SkyMiles Gold | F77: 162.41 | G77: 2939.73 | H77: AMEX @ $162.41 → Amex Delta SkyMiles Gold | I77: =IF(B77="","",TEXT(B77,"mmm")) -> Apr | J77: =IF(B77="","",YEAR(B77)) -> 2026
A78: 73 | B78: 46133 | C78: DISCOVER E-PAYMENT 2877 WEB ID: 2510020270 | D78: Expense | E78: Discover | F78: 185.3 | G78: 2754.43 | H78: DISCOVER → Discover | I78: =IF(B78="","",TEXT(B78,"mmm")) -> Apr | J78: =IF(B78="","",YEAR(B78)) -> 2026
A79: 74 | B79: 46133 | C79: PAYPAL PURCHASE STARBUCKS WEB ID: PAYPALSI77 | D79: Expense | E79: PayPal Credit (Brad) / Synchrony | F79: 10 | G79: 2744.43 | H79: STARBUCKS → Coffee (Starbucks, Dunkin) | I79: =IF(B79="","",TEXT(B79,"mmm")) -> Apr | J79: =IF(B79="","",YEAR(B79)) -> 2026
A80: 75 | B80: 46133 | C80: MADISON GAS EL BILLPAY PPD ID: 0000000160 | D80: Expense | E80: Electric & Gas (MGE) | F80: 241 | G80: 2503.43 | H80: MADISON GAS → Electric & Gas (MGE) | I80: =IF(B80="","",TEXT(B80,"mmm")) -> Apr | J80: =IF(B80="","",YEAR(B80)) -> 2026
A81: 76 | B81: 46134 | C81: SYNCHRONY BANK PAYMENT 601919305959779 WEB ID: 1061537262 | D81: Expense | E81: Ashley Furniture / Synchrony | F81: 34 | G81: 2469.43 | H81: SYNCHRONY → Ashley Furniture / Synchrony | I81: =IF(B81="","",TEXT(B81,"mmm")) -> Apr | J81: =IF(B81="","",YEAR(B81)) -> 2026
A82: 77 | B82: 46134 | C82: METRO MARKET #434 MADISON WI 04/22 | D82: Expense | F82: 58.84 | G82: 2410.59 | H82: METRO MARKET → Groceries ($425/wk × 4.33 wks) | I82: =IF(B82="","",TEXT(B82,"mmm")) -> Apr | J82: =IF(B82="","",YEAR(B82)) -> 2026
A83: 78 | B83: 46135 | C83: EXACT SCIENCES PAYROLL PPD ID: 9111111103 | D83: Income | E83: Brad's Paycheck (Exact) | F83: 2274.42 | G83: 4685.01 | H83: EXACT SCIENCES → Brad's Paycheck (Exact) | I83: =IF(B83="","",TEXT(B83,"mmm")) -> Apr | J83: =IF(B83="","",YEAR(B83)) -> 2026
A84: 79 | B84: 46135 | C84: INTUIT FINANCING QBC_PMTS PPD ID: 5463467445 | D84: Expense | F84: 176.06 | G84: 4508.95 | H84: INTUIT → Intuit / Tax | I84: =IF(B84="","",TEXT(B84,"mmm")) -> Apr | J84: =IF(B84="","",YEAR(B84)) -> 2026
A85: 80 | B85: 46135 | C85: FID BKG SVC LLC MONEYLINE PPD ID: 0368004600 | D85: Expense | E85: Fidelity Investment | F85: 50 | G85: 4458.95 | H85: FID BKG SVC → Fidelity Investment | I85: =IF(B85="","",TEXT(B85,"mmm")) -> Apr | J85: =IF(B85="","",YEAR(B85)) -> 2026
A86: 81 | B86: 46136 | C86: KWIK TRIP INC PAYMENT 000093008226050 WEB ID: 9161597801 | D86: Expense | E86: Gasoline (Kwik Trip / Woodmans) | F86: 200 | G86: 4258.95 | H86: KWIK TRIP → Gasoline (Kwik Trip / Woodmans) | I86: =IF(B86="","",TEXT(B86,"mmm")) -> Apr | J86: =IF(B86="","",YEAR(B86)) -> 2026
A87: 82 | B87: 46136 | C87: CITY OF MADISON MADISON WI 9306199 WEB ID: 0000070577 | D87: Expense | E87: Water/Sewer (City of Madison) | F87: 89.48 | G87: 4169.47 | H87: CITY OF MADISON → Water/Sewer (City of Madison) | I87: =IF(B87="","",TEXT(B87,"mmm")) -> Apr | J87: =IF(B87="","",YEAR(B87)) -> 2026
A88: 83 | B88: 46136 | C88: COSTCO WHSE #1121 SUN PRAIRIE WI 503269 04/24 | D88: Expense | E88: Costco (warehouse stock-up) | F88: 62.45 | G88: 4107.02 | H88: COSTCO → Costco (warehouse stock-up) | I88: =IF(B88="","",TEXT(B88,"mmm")) -> Apr | J88: =IF(B88="","",YEAR(B88)) -> 2026
A89: 84 | B89: 46139 | C89: DISCOVER E-PAYMENT 2877 WEB ID: 2510020270 | D89: Expense | E89: Discover | F89: 39 | G89: 4068.02 | H89: DISCOVER → Discover | I89: =IF(B89="","",TEXT(B89,"mmm")) -> Apr | J89: =IF(B89="","",YEAR(B89)) -> 2026
A90: 85 | B90: 46139 | C90: PAYPAL PURCHASE DOORDASH DUNKIN WEB ID: PAYPALSI77 | D90: Expense | E90: DoorDash & Delivery | F90: 29.54 | G90: 4038.48 | H90: DOORDASH → DoorDash & Delivery | I90: =IF(B90="","",TEXT(B90,"mmm")) -> Apr | J90: =IF(B90="","",YEAR(B90)) -> 2026
A91: 86 | B91: 46139 | C91: PAYPAL PURCHASE DOORDASH DUNKIN WEB ID: PAYPALSI77 | D91: Expense | E91: DoorDash & Delivery | F91: 30.43 | G91: 4008.05 | H91: DOORDASH → DoorDash & Delivery | I91: =IF(B91="","",TEXT(B91,"mmm")) -> Apr | J91: =IF(B91="","",YEAR(B91)) -> 2026
A92: 87 | B92: 46139 | C92: SHEN ZHEN SHI SH PURCHASE 1049879865343 WEB ID: 770510487C | D92: Expense | E92: Shopping (Misc) | F92: 58.9 | G92: 3949.15 | H92: SHEN ZHEN → Shopping (Misc) | I92: =IF(B92="","",TEXT(B92,"mmm")) -> Apr | J92: =IF(B92="","",YEAR(B92)) -> 2026
A93: 88 | B93: 46139 | C93: Online Transfer to GMR ...0324 transaction#: 28983515805 04/27 | D93: Transfer | E93: Savings Transfer (out) | F93: -50 | G93: 3899.15 | H93: ONLINE TRANSFER TO → Savings Transfer (out) | I93: =IF(B93="","",TEXT(B93,"mmm")) -> Apr | J93: =IF(B93="","",YEAR(B93)) -> 2026
A94: 89 | B94: 46139 | C94: KLARNA PURCHASE QTDH Walmart WEB ID: 7891460966 | D94: Expense | E94: Klarna | F94: 47.05 | G94: 3852.1 | H94: KLARNA → Klarna | I94: =IF(B94="","",TEXT(B94,"mmm")) -> Apr | J94: =IF(B94="","",YEAR(B94)) -> 2026
A95: 90 | B95: 46141 | C95: DEPT EDUCATION STUDENT LN PPD ID: 9102001001 | D95: Expense | E95: Student Loan (Nelnet / Dept of Ed) | F95: 237.58 | G95: 3614.52 | H95: DEPT EDUCATION → Student Loan (Nelnet / Dept of Ed) | I95: =IF(B95="","",TEXT(B95,"mmm")) -> Apr | J95: =IF(B95="","",YEAR(B95)) -> 2026
A96: 91 | B96: 46141 | C96: AFFIRM.COM PAYME AFFIRM.COM ST-L4R3X2J2U2C3 WEB ID: 1800948598 | D96: Expense | E96: Affirm — Tonal | F96: 139.5 | G96: 3475.02 | H96: AFFIRM @ $139.50 → Affirm — Tonal | I96: =IF(B96="","",TEXT(B96,"mmm")) -> Apr | J96: =IF(B96="","",YEAR(B96)) -> 2026
A97: 92 | B97: 46141 | C97: AFFIRM.COM PAYME AFFIRM.COM ST-J6L0K3Z3X2C4 WEB ID: 1800948598 | D97: Expense | E97: Affirm — Amazon | F97: 66.93 | G97: 3408.09 | H97: AFFIRM @ $66.93 → Affirm — Amazon | I97: =IF(B97="","",TEXT(B97,"mmm")) -> Apr | J97: =IF(B97="","",YEAR(B97)) -> 2026
A98: 93 | D98: =IF(C98="","",IF(OR(ISNUMBER(SEARCH("PAYROLL",UPPER(C98))),ISNUMBER(SEARCH("PAYCHECK",UPPER(C98))),ISNUMBER(SEARCH("DEPOSIT",UPPER(C98)))),"Income",IF(ISNUMBER(SEARCH("TRANSFER",UPPER(C98))),"Transfer","Expense"))) | E98: =IF(C98="","",IFERROR(INDEX(Mapping!$B$5:$B$200,SUMPRODUCT(MAX((ISNUMBER(SEARCH(Mapping!$A$5:$A$200,UPPER(C98&""))))*ROW(Mapping!$A$5:$A$200)))-4),"")) | G98: =IF(F98="",G97,G97+IF(D98="Income",F98,IF(D98="Expense",-F98,F98))) -> 3408.09 | H98: =IF(C98="","",IFERROR(INDEX(Mapping!$A$5:$A$200,SUMPRODUCT(MAX((ISNUMBER(SEARCH(Mapping!$A$5:$A$200,UPPER(C98&""))))*ROW(Mapping!$A$5:$A$200)))-4)&" → "&INDEX(Mapping!$B$5:$B$200,SUMPRODUCT(MAX((ISNUMBER(SEARCH(Mapping!$A$5:$A$200,UPPER(C98&""))))*ROW(Mapping!$A$5:$A$200)))-4),"❓ no rule (add to Mapping)")) | I98: =IF(B98="","",TEXT(B98,"mmm")) | J98: =IF(B98="","",YEAR(B98))
A99: 94 | D99: =IF(C99="","",IF(OR(ISNUMBER(SEARCH("PAYROLL",UPPER(C99))),ISNUMBER(SEARCH("PAYCHECK",UPPER(C99))),ISNUMBER(SEARCH("DEPOSIT",UPPER(C99)))),"Income",IF(ISNUMBER(SEARCH("TRANSFER",UPPER(C99))),"Transfer","Expense"))) | E99: =IF(C99="","",IFERROR(INDEX(Mapping!$B$5:$B$200,SUMPRODUCT(MAX((ISNUMBER(SEARCH(Mapping!$A$5:$A$200,UPPER(C99&""))))*ROW(Mapping!$A$5:$A$200)))-4),"")) | G99: =IF(F99="",G98,G98+IF(D99="Income",F99,IF(D99="Expense",-F99,F99))) -> 3408.09 | H99: =IF(C99="","",IFERROR(INDEX(Mapping!$A$5:$A$200,SUMPRODUCT(MAX((ISNUMBER(SEARCH(Mapping!$A$5:$A$200,UPPER(C99&""))))*ROW(Mapping!$A$5:$A$200)))-4)&" → "&INDEX(Mapping!$B$5:$B$200,SUMPRODUCT(MAX((ISNUMBER(SEARCH(Mapping!$A$5:$A$200,UPPER(C99&""))))*ROW(Mapping!$A$5:$A$200)))-4),"❓ no rule (add to Mapping)")) | I99: =IF(B99="","",TEXT(B99,"mmm")) | J99: =IF(B99="","",YEAR(B99))
A100: 95 | D100: =IF(C100="","",IF(OR(ISNUMBER(SEARCH("PAYROLL",UPPER(C100))),ISNUMBER(SEARCH("PAYCHECK",UPPER(C100))),ISNUMBER(SEARCH("DEPOSIT",UPPER(C100)))),"Income",IF(ISNUMBER(SEARCH("TRANSFER",UPPER(C100))),"Transfer","Expense"))) | E100: =IF(C100="","",IFERROR(INDEX(Mapping!$B$5:$B$200,SUMPRODUCT(MAX((ISNUMBER(SEARCH(Mapping!$A$5:$A$200,UPPER(C100&""))))*ROW(Mapping!$A$5:$A$200)))-4),"")) | G100: =IF(F100="",G99,G99+IF(D100="Income",F100,IF(D100="Expense",-F100,F100))) -> 3408.09 | H100: =IF(C100="","",IFERROR(INDEX(Mapping!$A$5:$A$200,SUMPRODUCT(MAX((ISNUMBER(SEARCH(Mapping!$A$5:$A$200,UPPER(C100&""))))*ROW(Mapping!$A$5:$A$200)))-4)&" → "&INDEX(Mapping!$B$5:$B$200,SUMPRODUCT(MAX((ISNUMBER(SEARCH(Mapping!$A$5:$A$200,UPPER(C100&""))))*ROW(Mapping!$A$5:$A$200)))-4),"❓ no rule (add to Mapping)")) | I100: =IF(B100="","",TEXT(B100,"mmm")) | J100: =IF(B100="","",YEAR(B100))
A101: 96 | D101: =IF(C101="","",IF(OR(ISNUMBER(SEARCH("PAYROLL",UPPER(C101))),ISNUMBER(SEARCH("PAYCHECK",UPPER(C101))),ISNUMBER(SEARCH("DEPOSIT",UPPER(C101)))),"Income",IF(ISNUMBER(SEARCH("TRANSFER",UPPER(C101))),"Transfer","Expense"))) | E101: =IF(C101="","",IFERROR(INDEX(Mapping!$B$5:$B$200,SUMPRODUCT(MAX((ISNUMBER(SEARCH(Mapping!$A$5:$A$200,UPPER(C101&""))))*ROW(Mapping!$A$5:$A$200)))-4),"")) | G101: =IF(F101="",G100,G100+IF(D101="Income",F101,IF(D101="Expense",-F101,F101))) -> 3408.09 | H101: =IF(C101="","",IFERROR(INDEX(Mapping!$A$5:$A$200,SUMPRODUCT(MAX((ISNUMBER(SEARCH(Mapping!$A$5:$A$200,UPPER(C101&""))))*ROW(Mapping!$A$5:$A$200)))-4)&" → "&INDEX(Mapping!$B$5:$B$200,SUMPRODUCT(MAX((ISNUMBER(SEARCH(Mapping!$A$5:$A$200,UPPER(C101&""))))*ROW(Mapping!$A$5:$A$200)))-4),"❓ no rule (add to Mapping)")) | I101: =IF(B101="","",TEXT(B101,"mmm")) | J101: =IF(B101="","",YEAR(B101))
A102: 97 | D102: =IF(C102="","",IF(OR(ISNUMBER(SEARCH("PAYROLL",UPPER(C102))),ISNUMBER(SEARCH("PAYCHECK",UPPER(C102))),ISNUMBER(SEARCH("DEPOSIT",UPPER(C102)))),"Income",IF(ISNUMBER(SEARCH("TRANSFER",UPPER(C102))),"Transfer","Expense"))) | E102: =IF(C102="","",IFERROR(INDEX(Mapping!$B$5:$B$200,SUMPRODUCT(MAX((ISNUMBER(SEARCH(Mapping!$A$5:$A$200,UPPER(C102&""))))*ROW(Mapping!$A$5:$A$200)))-4),"")) | G102: =IF(F102="",G101,G101+IF(D102="Income",F102,IF(D102="Expense",-F102,F102))) -> 3408.09 | H102: =IF(C102="","",IFERROR(INDEX(Mapping!$A$5:$A$200,SUMPRODUCT(MAX((ISNUMBER(SEARCH(Mapping!$A$5:$A$200,UPPER(C102&""))))*ROW(Mapping!$A$5:$A$200)))-4)&" → "&INDEX(Mapping!$B$5:$B$200,SUMPRODUCT(MAX((ISNUMBER(SEARCH(Mapping!$A$5:$A$200,UPPER(C102&""))))*ROW(Mapping!$A$5:$A$200)))-4),"❓ no rule (add to Mapping)")) | I102: =IF(B102="","",TEXT(B102,"mmm")) | J102: =IF(B102="","",YEAR(B102))
A103: 98 | D103: =IF(C103="","",IF(OR(ISNUMBER(SEARCH("PAYROLL",UPPER(C103))),ISNUMBER(SEARCH("PAYCHECK",UPPER(C103))),ISNUMBER(SEARCH("DEPOSIT",UPPER(C103)))),"Income",IF(ISNUMBER(SEARCH("TRANSFER",UPPER(C103))),"Transfer","Expense"))) | E103: =IF(C103="","",IFERROR(INDEX(Mapping!$B$5:$B$200,SUMPRODUCT(MAX((ISNUMBER(SEARCH(Mapping!$A$5:$A$200,UPPER(C103&""))))*ROW(Mapping!$A$5:$A$200)))-4),"")) | G103: =IF(F103="",G102,G102+IF(D103="Income",F103,IF(D103="Expense",-F103,F103))) -> 3408.09 | H103: =IF(C103="","",IFERROR(INDEX(Mapping!$A$5:$A$200,SUMPRODUCT(MAX((ISNUMBER(SEARCH(Mapping!$A$5:$A$200,UPPER(C103&""))))*ROW(Mapping!$A$5:$A$200)))-4)&" → "&INDEX(Mapping!$B$5:$B$200,SUMPRODUCT(MAX((ISNUMBER(SEARCH(Mapping!$A$5:$A$200,UPPER(C103&""))))*ROW(Mapping!$A$5:$A$200)))-4),"❓ no rule (add to Mapping)")) | I103: =IF(B103="","",TEXT(B103,"mmm")) | J103: =IF(B103="","",YEAR(B103))
A104: 99 | D104: =IF(C104="","",IF(OR(ISNUMBER(SEARCH("PAYROLL",UPPER(C104))),ISNUMBER(SEARCH("PAYCHECK",UPPER(C104))),ISNUMBER(SEARCH("DEPOSIT",UPPER(C104)))),"Income",IF(ISNUMBER(SEARCH("TRANSFER",UPPER(C104))),"Transfer","Expense"))) | E104: =IF(C104="","",IFERROR(INDEX(Mapping!$B$5:$B$200,SUMPRODUCT(MAX((ISNUMBER(SEARCH(Mapping!$A$5:$A$200,UPPER(C104&""))))*ROW(Mapping!$A$5:$A$200)))-4),"")) | G104: =IF(F104="",G103,G103+IF(D104="Income",F104,IF(D104="Expense",-F104,F104))) -> 3408.09 | H104: =IF(C104="","",IFERROR(INDEX(Mapping!$A$5:$A$200,SUMPRODUCT(MAX((ISNUMBER(SEARCH(Mapping!$A$5:$A$200,UPPER(C104&""))))*ROW(Mapping!$A$5:$A$200)))-4)&" → "&INDEX(Mapping!$B$5:$B$200,SUMPRODUCT(MAX((ISNUMBER(SEARCH(Mapping!$A$5:$A$200,UPPER(C104&""))))*ROW(Mapping!$A$5:$A$200)))-4),"❓ no rule (add to Mapping)")) | I104: =IF(B104="","",TEXT(B104,"mmm")) | J104: =IF(B104="","",YEAR(B104))
A105: 100 | D105: =IF(C105="","",IF(OR(ISNUMBER(SEARCH("PAYROLL",UPPER(C105))),ISNUMBER(SEARCH("PAYCHECK",UPPER(C105))),ISNUMBER(SEARCH("DEPOSIT",UPPER(C105)))),"Income",IF(ISNUMBER(SEARCH("TRANSFER",UPPER(C105))),"Transfer","Expense"))) | E105: =IF(C105="","",IFERROR(INDEX(Mapping!$B$5:$B$200,SUMPRODUCT(MAX((ISNUMBER(SEARCH(Mapping!$A$5:$A$200,UPPER(C105&""))))*ROW(Mapping!$A$5:$A$200)))-4),"")) | G105: =IF(F105="",G104,G104+IF(D105="Income",F105,IF(D105="Expense",-F105,F105))) -> 3408.09 | H105: =IF(C105="","",IFERROR(INDEX(Mapping!$A$5:$A$200,SUMPRODUCT(MAX((ISNUMBER(SEARCH(Mapping!$A$5:$A$200,UPPER(C105&""))))*ROW(Mapping!$A$5:$A$200)))-4)&" → "&INDEX(Mapping!$B$5:$B$200,SUMPRODUCT(MAX((ISNUMBER(SEARCH(Mapping!$A$5:$A$200,UPPER(C105&""))))*ROW(Mapping!$A$5:$A$200)))-4),"❓ no rule (add to Mapping)")) | I105: =IF(B105="","",TEXT(B105,"mmm")) | J105: =IF(B105="","",YEAR(B105))
A106: 101 | D106: =IF(C106="","",IF(OR(ISNUMBER(SEARCH("PAYROLL",UPPER(C106))),ISNUMBER(SEARCH("PAYCHECK",UPPER(C106))),ISNUMBER(SEARCH("DEPOSIT",UPPER(C106)))),"Income",IF(ISNUMBER(SEARCH("TRANSFER",UPPER(C106))),"Transfer","Expense"))) | E106: =IF(C106="","",IFERROR(INDEX(Mapping!$B$5:$B$200,SUMPRODUCT(MAX((ISNUMBER(SEARCH(Mapping!$A$5:$A$200,UPPER(C106&""))))*ROW(Mapping!$A$5:$A$200)))-4),"")) | G106: =IF(F106="",G105,G105+IF(D106="Income",F106,IF(D106="Expense",-F106,F106))) -> 3408.09 | H106: =IF(C106="","",IFERROR(INDEX(Mapping!$A$5:$A$200,SUMPRODUCT(MAX((ISNUMBER(SEARCH(Mapping!$A$5:$A$200,UPPER(C106&""))))*ROW(Mapping!$A$5:$A$200)))-4)&" → "&INDEX(Mapping!$B$5:$B$200,SUMPRODUCT(MAX((ISNUMBER(SEARCH(Mapping!$A$5:$A$200,UPPER(C106&""))))*ROW(Mapping!$A$5:$A$200)))-4),"❓ no rule (add to Mapping)")) | I106: =IF(B106="","",TEXT(B106,"mmm")) | J106: =IF(B106="","",YEAR(B106))
A107: 102 | D107: =IF(C107="","",IF(OR(ISNUMBER(SEARCH("PAYROLL",UPPER(C107))),ISNUMBER(SEARCH("PAYCHECK",UPPER(C107))),ISNUMBER(SEARCH("DEPOSIT",UPPER(C107)))),"Income",IF(ISNUMBER(SEARCH("TRANSFER",UPPER(C107))),"Transfer","Expense"))) | E107: =IF(C107="","",IFERROR(INDEX(Mapping!$B$5:$B$200,SUMPRODUCT(MAX((ISNUMBER(SEARCH(Mapping!$A$5:$A$200,UPPER(C107&""))))*ROW(Mapping!$A$5:$A$200)))-4),"")) | G107: =IF(F107="",G106,G106+IF(D107="Income",F107,IF(D107="Expense",-F107,F107))) -> 3408.09 | H107: =IF(C107="","",IFERROR(INDEX(Mapping!$A$5:$A$200,SUMPRODUCT(MAX((ISNUMBER(SEARCH(Mapping!$A$5:$A$200,UPPER(C107&""))))*ROW(Mapping!$A$5:$A$200)))-4)&" → "&INDEX(Mapping!$B$5:$B$200,SUMPRODUCT(MAX((ISNUMBER(SEARCH(Mapping!$A$5:$A$200,UPPER(C107&""))))*ROW(Mapping!$A$5:$A$200)))-4),"❓ no rule (add to Mapping)")) | I107: =IF(B107="","",TEXT(B107,"mmm")) | J107: =IF(B107="","",YEAR(B107))
A108: 103 | D108: =IF(C108="","",IF(OR(ISNUMBER(SEARCH("PAYROLL",UPPER(C108))),ISNUMBER(SEARCH("PAYCHECK",UPPER(C108))),ISNUMBER(SEARCH("DEPOSIT",UPPER(C108)))),"Income",IF(ISNUMBER(SEARCH("TRANSFER",UPPER(C108))),"Transfer","Expense"))) | E108: =IF(C108="","",IFERROR(INDEX(Mapping!$B$5:$B$200,SUMPRODUCT(MAX((ISNUMBER(SEARCH(Mapping!$A$5:$A$200,UPPER(C108&""))))*ROW(Mapping!$A$5:$A$200)))-4),"")) | G108: =IF(F108="",G107,G107+IF(D108="Income",F108,IF(D108="Expense",-F108,F108))) -> 3408.09 | H108: =IF(C108="","",IFERROR(INDEX(Mapping!$A$5:$A$200,SUMPRODUCT(MAX((ISNUMBER(SEARCH(Mapping!$A$5:$A$200,UPPER(C108&""))))*ROW(Mapping!$A$5:$A$200)))-4)&" → "&INDEX(Mapping!$B$5:$B$200,SUMPRODUCT(MAX((ISNUMBER(SEARCH(Mapping!$A$5:$A$200,UPPER(C108&""))))*ROW(Mapping!$A$5:$A$200)))-4),"❓ no rule (add to Mapping)")) | I108: =IF(B108="","",TEXT(B108,"mmm")) | J108: =IF(B108="","",YEAR(B108))
A109: 104 | D109: =IF(C109="","",IF(OR(ISNUMBER(SEARCH("PAYROLL",UPPER(C109))),ISNUMBER(SEARCH("PAYCHECK",UPPER(C109))),ISNUMBER(SEARCH("DEPOSIT",UPPER(C109)))),"Income",IF(ISNUMBER(SEARCH("TRANSFER",UPPER(C109))),"Transfer","Expense"))) | E109: =IF(C109="","",IFERROR(INDEX(Mapping!$B$5:$B$200,SUMPRODUCT(MAX((ISNUMBER(SEARCH(Mapping!$A$5:$A$200,UPPER(C109&""))))*ROW(Mapping!$A$5:$A$200)))-4),"")) | G109: =IF(F109="",G108,G108+IF(D109="Income",F109,IF(D109="Expense",-F109,F109))) -> 3408.09 | H109: =IF(C109="","",IFERROR(INDEX(Mapping!$A$5:$A$200,SUMPRODUCT(MAX((ISNUMBER(SEARCH(Mapping!$A$5:$A$200,UPPER(C109&""))))*ROW(Mapping!$A$5:$A$200)))-4)&" → "&INDEX(Mapping!$B$5:$B$200,SUMPRODUCT(MAX((ISNUMBER(SEARCH(Mapping!$A$5:$A$200,UPPER(C109&""))))*ROW(Mapping!$A$5:$A$200)))-4),"❓ no rule (add to Mapping)")) | I109: =IF(B109="","",TEXT(B109,"mmm")) | J109: =IF(B109="","",YEAR(B109))
... A505: 500 | D505: =IF(C505="","",IF(OR(ISNUMBER(SEARCH("PAYROLL",UPPER(C505))),ISNUMBER(SEARCH("PAYCHECK",UPPER(C505))),ISNUMBER(SEARCH("DEPOSIT",UPPER(C505)))),"Income",IF(ISNUMBER(SEARCH("TRANSFER",UPPER(C505))),"Transfer","Expense"))) | E505: =IF(C505="","",IFERROR(INDEX(Mapping!$B$5:$B$200,SUMPRODUCT(MAX((ISNUMBER(SEARCH(Mapping!$A$5:$A$200,UPPER(C505&""))))*ROW(Mapping!$A$5:$A$200)))-4),"")) | G505: =IF(F505="",G504,G504+IF(D505="Income",F505,IF(D505="Expense",-F505,F505))) -> 3408.09 | H505: =IF(C505="","",IFERROR(INDEX(Mapping!$A$5:$A$200,SUMPRODUCT(MAX((ISNUMBER(SEARCH(Mapping!$A$5:$A$200,UPPER(C505&""))))*ROW(Mapping!$A$5:$A$200)))-4)&" → "&INDEX(Mapping!$B$5:$B$200,SUMPRODUCT(MAX((ISNUMBER(SEARCH(Mapping!$A$5:$A$200,UPPER(C505&""))))*ROW(Mapping!$A$5:$A$200)))-4),"❓ no rule (add to Mapping)")) | I505: =IF(B505="","",TEXT(B505,"mmm")) | J505: =IF(B505="","",YEAR(B505))

Sheet Forecast
A1: 📊 CASH FLOW FORECAST
A3: Today's Balance: | B3: =Payments!E2 -> 3408.09 | C3: Forecast Start: | D3: 46143 | E3: View: | F3: 90 days | I3: =IF(F3="30 days",30,IF(F3="60 days",60,IF(F3="90 days",90,IF(F3="180 days",180,365)))) -> 90
A5: 💵 Lowest Bal: | B5: =MIN(OFFSET($AH$200,0,0,$I$3,1)) -> 2571.91 | C5: 📈 Income: | D5: =SUM(OFFSET($AD$200,0,0,$I$3,1)) -> 40385.05 | E5: 📉 Expenses: | F5: =SUM(OFFSET($AE$200,0,0,$I$3,1)) -> 26733.91 | G5: 💳 Debt Pmt: | H5: =SUM(OFFSET($AF$200,0,0,$I$3,1)) -> 9572.72 | I5: 🎯 End: | J5: =INDEX($AH$200:$AH$564,$I$3) -> 7486.51
A7: 📅 DAILY FORECAST (next 90 days)
A9: Day | B9: Date | C9: Income | D9: Expense | E9: Debt Pmt | F9: Net | G9: Balance | H9: Warning | I9: Notes
A10: 1 | B10: =AB200 -> 46143 | C10: =AD200 -> 3819.79 | D10: =AE200 -> 601.16 | E10: =AF200 -> 557.5 | F10: =AG200 -> 2661.13 | G10: =AH200 -> 6069.22 | H10: =IF(G10<0,"🚨",IF(G10<500,"⚠",""))
A11: 2 | B11: =AB201 -> 46144 | C11: =AD201 -> 0 | D11: =AE201 -> 0 | E11: =AF201 -> 1309.17 | F11: =AG201 -> -1309.17 | G11: =AH201 -> 4760.05 | H11: =IF(G11<0,"🚨",IF(G11<500,"⚠",""))
A12: 3 | B12: =AB202 -> 46145 | C12: =AD202 -> 0 | D12: =AE202 -> 927.53 | E12: =AF202 -> 0 | F12: =AG202 -> -927.53 | G12: =AH202 -> 3832.52 | H12: =IF(G12<0,"🚨",IF(G12<500,"⚠",""))
A13: 4 | B13: =AB203 -> 46146 | C13: =AD203 -> 0 | D13: =AE203 -> 0 | E13: =AF203 -> 0 | F13: =AG203 -> 0 | G13: =AH203 -> 3832.52 | H13: =IF(G13<0,"🚨",IF(G13<500,"⚠",""))
A14: 5 | B14: =AB204 -> 46147 | C14: =AD204 -> 0 | D14: =AE204 -> 51.01 | E14: =AF204 -> 0 | F14: =AG204 -> -51.01 | G14: =AH204 -> 3781.51 | H14: =IF(G14<0,"🚨",IF(G14<500,"⚠",""))
A15: 6 | B15: =AB205 -> 46148 | C15: =AD205 -> 0 | D15: =AE205 -> 651.55 | E15: =AF205 -> 259.86 | F15: =AG205 -> -911.41 | G15: =AH205 -> 2870.1 | H15: =IF(G15<0,"🚨",IF(G15<500,"⚠",""))
A16: 7 | B16: =AB206 -> 46149 | C16: =AD206 -> 2274.42 | D16: =AE206 -> 672.8 | E16: =AF206 -> 8.25 | F16: =AG206 -> 1593.37 | G16: =AH206 -> 4463.47 | H16: =IF(G16<0,"🚨",IF(G16<500,"⚠",""))
A17: 8 | B17: =AB207 -> 46150 | C17: =AD207 -> 0 | D17: =AE207 -> 513.85 | E17: =AF207 -> 0 | F17: =AG207 -> -513.85 | G17: =AH207 -> 3949.62 | H17: =IF(G17<0,"🚨",IF(G17<500,"⚠",""))
A18: 9 | B18: =AB208 -> 46151 | C18: =AD208 -> 0 | D18: =AE208 -> 0 | E18: =AF208 -> 162 | F18: =AG208 -> -162 | G18: =AH208 -> 3787.62 | H18: =IF(G18<0,"🚨",IF(G18<500,"⚠",""))
A19: 10 | B19: =AB209 -> 46152 | C19: =AD209 -> 0 | D19: =AE209 -> 340.22 | E19: =AF209 -> 72.54 | F19: =AG209 -> -412.76 | G19: =AH209 -> 3374.86 | H19: =IF(G19<0,"🚨",IF(G19<500,"⚠",""))
A20: 11 | B20: =AB210 -> 46153 | C20: =AD210 -> 0 | D20: =AE210 -> 0 | E20: =AF210 -> 0 | F20: =AG210 -> 0 | G20: =AH210 -> 3374.86 | H20: =IF(G20<0,"🚨",IF(G20<500,"⚠",""))
A21: 12 | B21: =AB211 -> 46154 | C21: =AD211 -> 0 | D21: =AE211 -> 167.68 | E21: =AF211 -> 0 | F21: =AG211 -> -167.68 | G21: =AH211 -> 3207.18 | H21: =IF(G21<0,"🚨",IF(G21<500,"⚠",""))
... A99: 90 | B99: =AB289 -> 46232 | C99: =AD289 -> 0 | D99: =AE289 -> 237.58 | E99: =AF289 -> 206.43 | F99: =AG289 -> -444.01 | G99: =AH289 -> 7486.51 | H99: =IF(G99<0,"🚨",IF(G99<500,"⚠",""))
A101: 📆 WEEKLY ROLLUP (days 91-180)
A103: Wk# | B103: Week of | C103: Income | D103: Expense | E103: Debt Pmt | F103: Net | G103: End Bal | H103: Warning | I103: Notes
A104: 14 | B104: =$D$3+91 -> 46234 | C104: =SUM(AD291:AD297) -> 0 | D104: =SUM(AE291:AE297) -> 2231.25 | E104: =SUM(AF291:AF297) -> 1926.53 | F104: =C104-D104-E104 -> -4157.78 | G104: =AH297 -> 5603.15 | H104: =IF(G104<0,"🚨",IF(G104<500,"⚠",""))
A105: 15 | B105: =$D$3+98 -> 46241 | C105: =SUM(AD298:AD304) -> 6094.21 | D105: =SUM(AE298:AE304) -> 1694.55 | E105: =SUM(AF298:AF304) -> 160.79 | F105: =C105-D105-E105 -> 4238.87 | G105: =AH304 -> 9842.02 | H105: =IF(G105<0,"🚨",IF(G105<500,"⚠",""))
A106: 16 | B106: =$D$3+105 -> 46248 | C106: =SUM(AD305:AD311) -> 0 | D106: =SUM(AE305:AE311) -> 3792.57 | E106: =SUM(AF305:AF311) -> 553.49 | F106: =C106-D106-E106 -> -4346.06 | G106: =AH311 -> 5495.96 | H106: =IF(G106<0,"🚨",IF(G106<500,"⚠",""))
A107: 17 | B107: =$D$3+112 -> 46255 | C107: =SUM(AD312:AD318) -> 6094.21 | D107: =SUM(AE312:AE318) -> 802.02 | E107: =SUM(AF312:AF318) -> 80 | F107: =C107-D107-E107 -> 5212.19 | G107: =AH318 -> 10708.15 | H107: =IF(G107<0,"🚨",IF(G107<500,"⚠",""))
A108: 18 | B108: =$D$3+119 -> 46262 | C108: =SUM(AD319:AD325) -> 0 | D108: =SUM(AE319:AE325) -> 1766.27 | E108: =SUM(AF319:AF325) -> 1873.1 | F108: =C108-D108-E108 -> -3639.37 | G108: =AH325 -> 7068.78 | H108: =IF(G108<0,"🚨",IF(G108<500,"⚠",""))
A109: 19 | B109: =$D$3+126 -> 46269 | C109: =SUM(AD326:AD332) -> 6094.21 | D109: =SUM(AE326:AE332) -> 2229.43 | E109: =SUM(AF326:AF332) -> 134.78 | F109: =C109-D109-E109 -> 3730 | G109: =AH332 -> 10798.78 | H109: =IF(G109<0,"🚨",IF(G109<500,"⚠",""))
A110: 20 | B110: =$D$3+133 -> 46276 | C110: =SUM(AD333:AD339) -> 0 | D110: =SUM(AE333:AE339) -> 3960.25 | E110: =SUM(AF333:AF339) -> 426.26 | F110: =C110-D110-E110 -> -4386.51 | G110: =AH339 -> 6412.27 | H110: =IF(G110<0,"🚨",IF(G110<500,"⚠",""))
A111: 21 | B111: =$D$3+140 -> 46283 | C111: =SUM(AD340:AD346) -> 6094.21 | D111: =SUM(AE340:AE346) -> 802.02 | E111: =SUM(AF340:AF346) -> 287.23 | F111: =C111-D111-E111 -> 5004.96 | G111: =AH346 -> 11417.23 | H111: =IF(G111<0,"🚨",IF(G111<500,"⚠",""))
A112: 22 | B112: =$D$3+147 -> 46290 | C112: =SUM(AD347:AD353) -> 0 | D112: =SUM(AE347:AE353) -> 838.74 | E112: =SUM(AF347:AF353) -> 471.93 | F112: =C112-D112-E112 -> -1310.67 | G112: =AH353 -> 10106.56 | H112: =IF(G112<0,"🚨",IF(G112<500,"⚠",""))
A113: 23 | B113: =$D$3+154 -> 46297 | C113: =SUM(AD354:AD360) -> 6094.21 | D113: =SUM(AE354:AE360) -> 2816.74 | E113: =SUM(AF354:AF360) -> 1317.42 | F113: =C113-D113-E113 -> 1960.05 | G113: =AH360 -> 12066.61 | H113: =IF(G113<0,"🚨",IF(G113<500,"⚠",""))
A114: 24 | B114: =$D$3+161 -> 46304 | C114: =SUM(AD361:AD367) -> 0 | D114: =SUM(AE361:AE367) -> 3958.47 | E114: =SUM(AF361:AF367) -> 315.8 | F114: =C114-D114-E114 -> -4274.27 | G114: =AH367 -> 7792.34 | H114: =IF(G114<0,"🚨",IF(G114<500,"⚠",""))
A115: 25 | B115: =$D$3+168 -> 46311 | C115: =SUM(AD368:AD374) -> 6094.21 | D115: =SUM(AE368:AE374) -> 1043 | E115: =SUM(AF368:AF374) -> 430.23 | F115: =C115-D115-E115 -> 4620.98 | G115: =AH374 -> 12413.32 | H115: =IF(G115<0,"🚨",IF(G115<500,"⚠",""))
A116: 26 | B116: =$D$3+175 -> 46318 | C116: =SUM(AD375:AD381) -> 0 | D116: =SUM(AE375:AE381) -> 798.6 | E116: =SUM(AF375:AF381) -> 206.43 | F116: =C116-D116-E116 -> -1005.03 | G116: =AH381 -> 11408.29 | H116: =IF(G116<0,"🚨",IF(G116<500,"⚠",""))
A118: 🗓️ MONTHLY ROLLUP (months 7-12)
A120: Mo# | B120: Month | C120: Income | D120: Expense | E120: Debt Pmt | F120: Net | G120: End Bal | H120: Warning | I120: Notes
A121: 7 | B121: =EDATE($D$3,6) -> 46327 | C121: =SUMIF($AC$200:$AC$564,7,$AD$200:$AD$564) -> 12188.42 | D121: =SUMIF($AC$200:$AC$564,7,$AE$200:$AE$564) -> 8757.97 | E121: =SUMIF($AC$200:$AC$564,7,$AF$200:$AF$564) -> 2273.83 | F121: =C121-D121-E121 -> 1156.62 | G121: =LOOKUP(2,1/($AC$200:$AC$564=7),$AH$200:$AH$564) -> 15924.7 | H121: =IF(G121<0,"🚨",IF(G121<500,"⚠",""))
A122: 8 | B122: =EDATE($D$3,7) -> 46357 | C122: =SUMIF($AC$200:$AC$564,8,$AD$200:$AD$564) -> 14462.84 | D122: =SUMIF($AC$200:$AC$564,8,$AE$200:$AE$564) -> 8757.97 | E122: =SUMIF($AC$200:$AC$564,8,$AF$200:$AF$564) -> 2122.47 | F122: =C122-D122-E122 -> 3582.4 | G122: =LOOKUP(2,1/($AC$200:$AC$564=8),$AH$200:$AH$564) -> 19507.1 | H122: =IF(G122<0,"🚨",IF(G122<500,"⚠",""))
A123: 9 | B123: =EDATE($D$3,8) -> 46388 | C123: =SUMIF($AC$200:$AC$564,9,$AD$200:$AD$564) -> 12188.42 | D123: =SUMIF($AC$200:$AC$564,9,$AE$200:$AE$564) -> 9217.97 | E123: =SUMIF($AC$200:$AC$564,9,$AF$200:$AF$564) -> 1983.47 | F123: =C123-D123-E123 -> 986.98 | G123: =LOOKUP(2,1/($AC$200:$AC$564=9),$AH$200:$AH$564) -> 20494.08 | H123: =IF(G123<0,"🚨",IF(G123<500,"⚠",""))
A124: 10 | B124: =EDATE($D$3,9) -> 46419 | C124: =SUMIF($AC$200:$AC$564,10,$AD$200:$AD$564) -> 12188.42 | D124: =SUMIF($AC$200:$AC$564,10,$AE$200:$AE$564) -> 8520.39 | E124: =SUMIF($AC$200:$AC$564,10,$AF$200:$AF$564) -> 1472.94 | F124: =C124-D124-E124 -> 2195.09 | G124: =LOOKUP(2,1/($AC$200:$AC$564=10),$AH$200:$AH$564) -> 22689.17 | H124: =IF(G124<0,"🚨",IF(G124<500,"⚠",""))
A125: 11 | B125: =EDATE($D$3,10) -> 46447 | C125: =SUMIF($AC$200:$AC$564,11,$AD$200:$AD$564) -> 12188.42 | D125: =SUMIF($AC$200:$AC$564,11,$AE$200:$AE$564) -> 8757.97 | E125: =SUMIF($AC$200:$AC$564,11,$AF$200:$AF$564) -> 1623.35 | F125: =C125-D125-E125 -> 1807.1 | G125: =LOOKUP(2,1/($AC$200:$AC$564=11),$AH$200:$AH$564) -> 24496.27 | H125: =IF(G125<0,"🚨",IF(G125<500,"⚠",""))
A126: 12 | B126: =EDATE($D$3,11) -> 46478 | C126: =SUMIF($AC$200:$AC$564,12,$AD$200:$AD$564) -> 16008.21 | D126: =SUMIF($AC$200:$AC$564,12,$AE$200:$AE$564) -> 9217.97 | E126: =SUMIF($AC$200:$AC$564,12,$AF$200:$AF$564) -> 1623.35 | F126: =C126-D126-E126 -> 5166.89 | G126: =LOOKUP(2,1/($AC$200:$AC$564=12),$AH$200:$AH$564) -> 29663.16 | H126: =IF(G126<0,"🚨",IF(G126<500,"⚠",""))
A128: 🎉 DEBTS PAID OFF — month-by-month timeline
A130: Mo | B130: Month | C130: Debts Paid Off This Month | G130: Freed Min/mo | H130: Cumulative Freed
A131: 1 | B131: =EDATE($D$3,0) -> 46143 | C131: Ashley Furniture / Synchrony, Mattress Firm / Synchrony Home, Best Buy / Citi | G131: 191 | H131: 191
A132: 2 | B132: =EDATE($D$3,1) -> 46174 | C132: — | H132: 191
A133: 3 | B133: =EDATE($D$3,2) -> 46204 | C133: Capital One Platinum | G133: 200 | H133: 391
A134: 4 | B134: =EDATE($D$3,3) -> 46235 | C134: Amex Delta SkyMiles Gold | G134: 205.87 | H134: 596.87
A135: 5 | B135: =EDATE($D$3,4) -> 46266 | C135: Menards Big Card (Cap One), Amex Platinum (Pay Over Time), Chase Amazon Prime Visa | G135: 185.99 | H135: 782.86
A136: 6 | B136: =EDATE($D$3,5) -> 46296 | C136: Affirm — Best Buy (Dec), Affirm — Best Buy (Feb), Capital One Quicksilver | G136: 261.55 | H136: 1044.41
A137: 7 | B137: =EDATE($D$3,6) -> 46327 | C137: Discover, Credit One Bank, PayPal Credit (Brad) / Synchrony, Affirm — Shady Rays | G137: 151.36 | H137: 1195.77
A138: 8 | B138: =EDATE($D$3,7) -> 46357 | C138: PayPal Credit (Hannah) / Synchrony, Amex Blue Cash Preferred | G138: 139 | H138: 1334.77
A139: 9 | B139: =EDATE($D$3,8) -> 46388 | C139: Apple Card (Goldman Sachs), Affirm — Shokz, Affirm — Target | G139: 304.1 | H139: 1638.87
A140: 10 | B140: =EDATE($D$3,9) -> 46419 | C140: Affirm — Ridge | G140: 56.02 | H140: 1694.89
A141: 11 | B141: =EDATE($D$3,10) -> 46447 | C141: — | H141: 1694.89
A142: 12 | B142: =EDATE($D$3,11) -> 46478 | C142: — | H142: 1694.89
AA199: day_idx | AB199: date | AC199: month_offset | AD199: income | AE199: expense | AF199: debt_pmt | AG199: net | AH199: balance
AA200: 0 | AB200: =$D$3+0 -> 46143 | AC200: =MIN(12,1+DATEDIF($D$3,AB200,"M")) -> 1 | AD200: =SUMPRODUCT(('Recurring Items'!$C$6:$C$56="Income")*('Recurring Items'!$H$6:$H$56<>"Skip")*IFERROR(N('Recurring Items'!$D$6:$D$56),0)*(('Recurring Items'!$E$6:$E$56="Monthly")*(DAY(AB200)='Recurring Items'!$F$6:$F$56)+('Recurring Items'!$E$6:$E$56="Bi-weekly")*(WEEKDAY(AB200)=IFERROR(WEEKDAY('Recurring Items'!$G$6:$G$56),0))*(MOD(AB200-IFERROR('Recurring Items'!$G$6:$G$56,0),14)=0)*(AB200>=IFERROR('Recurring Items'!$G$6:$G$56,9000000000))+('Recurring Items'!$E$6:$E$56="Weekly")*(WEEKDAY(AB200)=IFERROR(WEEKDAY('Recurring Items'!$G$6:$G$56),0))*(AB200>=IFERROR('Recurring Items'!$G$6:$G$56,9000000000))+('Recurring Items'!$E$6:$E$56="One-time")*(AB200='Recurring Items'!$G$6:$G$56))) -> 3819.79 | AE200: =SUMPRODUCT(('Recurring Items'!$C$6:$C$56="Expense")*('Recurring Items'!$H$6:$H$56<>"Skip")*IFERROR(N('Recurring Items'!$D$6:$D$56),0)*(('Recurring Items'!$E$6:$E$56="Monthly")*(DAY(AB200)='Recurring Items'!$F$6:$F$56)+('Recurring Items'!$E$6:$E$56="Bi-weekly")*(WEEKDAY(AB200)=IFERROR(WEEKDAY('Recurring Items'!$G$6:$G$56),0))*(MOD(AB200-IFERROR('Recurring Items'!$G$6:$G$56,0),14)=0)*(AB200>=IFERROR('Recurring Items'!$G$6:$G$56,9000000000))+('Recurring Items'!$E$6:$E$56="Weekly")*(WEEKDAY(AB200)=IFERROR(WEEKDAY('Recurring Items'!$G$6:$G$56),0))*(AB200>=IFERROR('Recurring Items'!$G$6:$G$56,9000000000))+('Recurring Items'!$E$6:$E$56="One-time")*(AB200='Recurring Items'!$G$6:$G$56))) -> 601.16 | AF200: =(IF(AC200=1,'Debt Tracker'!$P$5>0.01,INDEX('Debt Tracker'!$T$5:$AE$29,1,AC200-1)>0.01))*('Recurring Items'!$H$8<>"Skip")*(DAY(AB200)='Recurring Items'!$F$8)*IFERROR(N('Recurring Items'!$D$8),0)+(IF(AC200=1,'Debt Tracker'!$P$6>0.01,INDEX('Debt Tracker'!$T$5:$AE$29,2,AC200-1)>0.01))*('Recurring Items'!$H$9<>"Skip")*(DAY(AB200)='Recurring Items'!$F$9)*IFERROR(N('Recurring Items'!$D$9),0)+(IF(AC200=1,'Debt Tracker'!$P$7>0.01,INDEX('Debt Tracker'!$T$5:$AE$29,3,AC200-1)>0.01))*('Recurring Items'!$H$10<>"Skip")*(DAY(AB200)='Recurring Items'!$F$10)*IFERROR(N('Recurring Items'!$D$10),0)+(IF(AC200=1,'Debt Tracker'!$P$8>0.01,INDEX('Debt Tracker'!$T$5:$AE$29,4,AC200-1)>0.01))*('Recurring Items'!$H$11<>"Skip")*(DAY(AB200)='Recurring Items'!$F$11)*IFERROR(N('Recurring Items'!$D$11),0)+(IF(AC200=1,'Debt Tracker'!$P$9>0.01,INDEX('Debt Tracker'!$T$5:$AE$29,5,AC200-1)>0.01))*('Recurring Items'!$H$12<>"Skip")*(DAY(AB200)='Recurring Items'!$F$12)*IFERROR(N('Recurring Items'!$D$12),0)+(IF(AC200=1,'Debt Tracker'!$P$10>0.01,INDEX('Debt Tracker'!$T$5:$AE$29,6,AC200-1)>0.01))*('Recurring Items'!$H$13<>"Skip")*(DAY(AB200)='Recurring Items'!$F$13)*IFERROR(N('Recurring Items'!$D$13),0)+(IF(AC200=1,'Debt Tracker'!$P$11>0.01,INDEX('Debt Tracker'!$T$5:$AE$29,7,AC200-1)>0.01))*('Recurring Items'!$H$14<>"Skip")*(DAY(AB200)='Recurring Items'!$F$14)*IFERROR(N('Recurring Items'!$D$14),0)+(IF(AC200=1,'Debt Tracker'!$P$12>0.01,INDEX('Debt Tracker'!$T$5:$AE$29,8,AC200-1)>0.01))*('Recurring Items'!$H$15<>"Skip")*(DAY(AB200)='Recurring Items'!$F$15)*IFERROR(N('Recurring Items'!$D$15),0)+(IF(AC200=1,'Debt Tracker'!$P$13>0.01,INDEX('Debt Tracker'!$T$5:$AE$29,9,AC200-1)>0.01))*('Recurring Items'!$H$16<>"Skip")*(DAY(AB200)='Recurring Items'!$F$16)*IFERROR(N('Recurring Items'!$D$16),0)+(IF(AC200=1,'Debt Tracker'!$P$14>0.01,INDEX('Debt Tracker'!$T$5:$AE$29,10,AC200-1)>0.01))*('Recurring Items'!$H$17<>"Skip")*(DAY(AB200)='Recurring Items'!$F$17)*IFERROR(N('Recurring Items'!$D$17),0)+(IF(AC200=1,'Debt Tracker'!$P$15>0.01,INDEX('Debt Tracker'!$T$5:$AE$29,11,AC200-1)>0.01))*('Recurring Items'!$H$18<>"Skip")*(DAY(AB200)='Recurring Items'!$F$18)*IFERROR(N('Recurring Items'!$D$18),0)+(IF(AC200=1,'Debt Tracker'!$P$16>0.01,INDEX('Debt Tracker'!$T$5:$AE$29,12,AC200-1)>0.01))*('Recurring Items'!$H$19<>"Skip")*(DAY(AB200)='Recurring Items'!$F$19)*IFERROR(N('Recurring Items'!$D$19),0)+(IF(AC200=1,'Debt Tracker'!$P$17>0.01,INDEX('Debt Tracker'!$T$5:$AE$29,13,AC200-1)>0.01))*('Recurring Items'!$H$20<>"Skip")*(DAY(AB200)='Recurring Items'!$F$20)*IFERROR(N('Recurring Items'!$D$20),0)+(IF(AC200=1,'Debt Tracker'!$P$18>0.01,INDEX('Debt Tracker'!$T$5:$AE$29,14,AC200-1)>0.01))*('Recurring Items'!$H$21<>"Skip")*(DAY(AB200)='Recurring Items'!$F$21)*IFERROR(N('Recurring Items'!$D$21),0)+(IF(AC200=1,'Debt Tracker'!$P$19>0.01,INDEX('Debt Tracker'!$T$5:$AE$29,15,AC200-1)>0.01))*('Recurring Items'!$H$22<>"Skip")*(DAY(AB200)='Recurring Items'!$F$22)*IFERROR(N('Recurring Items'!$D$22),0)+(IF(AC200=1,'Debt Tracker'!$P$20>0.01,INDEX('Debt Tracker'!$T$5:$AE$29,16,AC200-1)>0.01))*('Recurring Items'!$H$23<>"Skip")*(DAY(AB200)='Recurring Items'!$F$23)*IFERROR(N('Recurring Items'!$D$23),0)+(IF(AC200=1,'Debt Tracker'!$P$21>0.01,INDEX('Debt Tracker'!$T$5:$AE$29,17,AC200-1)>0.01))*('Recurring Items'!$H$24<>"Skip")*(DAY(AB200)='Recurring Items'!$F$24)*IFERROR(N('Recurring Items'!$D$24),0)+(IF(AC200=1,'Debt Tracker'!$P$22>0.01,INDEX('Debt Tracker'!$T$5:$AE$29,18,AC200-1)>0.01))*('Recurring Items'!$H$25<>"Skip")*(DAY(AB200)='Recurring Items'!$F$25)*IFERROR(N('Recurring Items'!$D$25),0)+(IF(AC200=1,'Debt Tracker'!$P$23>0.01,INDEX('Debt Tracker'!$T$5:$AE$29,19,AC200-1)>0.01))*('Recurring Items'!$H$26<>"Skip")*(DAY(AB200)='Recurring Items'!$F$26)*IFERROR(N('Recurring Items'!$D$26),0)+(IF(AC200=1,'Debt Tracker'!$P$24>0.01,INDEX('Debt Tracker'!$T$5:$AE$29,20,AC200-1)>0.01))*('Recurring Items'!$H$27<>"Skip")*(DAY(AB200)='Recurring Items'!$F$27)*IFERROR(N('Recurring Items'!$D$27),0)+(IF(AC200=1,'Debt Tracker'!$P$25>0.01,INDEX('Debt Tracker'!$T$5:$AE$29,21,AC200-1)>0.01))*('Recurring Items'!$H$28<>"Skip")*(DAY(AB200)='Recurring Items'!$F$28)*IFERROR(N('Recurring Items'!$D$28),0)+(IF(AC200=1,'Debt Tracker'!$P$26>0.01,INDEX('Debt Tracker'!$T$5:$AE$29,22,AC200-1)>0.01))*('Recurring Items'!$H$29<>"Skip")*(DAY(AB200)='Recurring Items'!$F$29)*IFERROR(N('Recurring Items'!$D$29),0)+(IF(AC200=1,'Debt Tracker'!$P$27>0.01,INDEX('Debt Tracker'!$T$5:$AE$29,23,AC200-1)>0.01))*('Recurring Items'!$H$30<>"Skip")*(DAY(AB200)='Recurring Items'!$F$30)*IFERROR(N('Recurring Items'!$D$30),0)+(IF(AC200=1,'Debt Tracker'!$P$28>0.01,INDEX('Debt Tracker'!$T$5:$AE$29,24,AC200-1)>0.01))*('Recurring Items'!$H$31<>"Skip")*(DAY(AB200)='Recurring Items'!$F$31)*IFERROR(N('Recurring Items'!$D$31),0)+(IF(AC200=1,'Debt Tracker'!$P$29>0.01,INDEX('Debt Tracker'!$T$5:$AE$29,25,AC200-1)>0.01))*('Recurring Items'!$H$32<>"Skip")*(DAY(AB200)='Recurring Items'!$F$32)*IFERROR(N('Recurring Items'!$D$32),0) -> 557.5 | AG200: =AD200-AE200-AF200 -> 2661.13 | AH200: =$B$3+AG200 -> 6069.22
AA201: 1 | AB201: =$D$3+1 -> 46144 | AC201: =MIN(12,1+DATEDIF($D$3,AB201,"M")) -> 1 | AD201: =SUMPRODUCT(('Recurring Items'!$C$6:$C$56="Income")*('Recurring Items'!$H$6:$H$56<>"Skip")*IFERROR(N('Recurring Items'!$D$6:$D$56),0)*(('Recurring Items'!$E$6:$E$56="Monthly")*(DAY(AB201)='Recurring Items'!$F$6:$F$56)+('Recurring Items'!$E$6:$E$56="Bi-weekly")*(WEEKDAY(AB201)=IFERROR(WEEKDAY('Recurring Items'!$G$6:$G$56),0))*(MOD(AB201-IFERROR('Recurring Items'!$G$6:$G$56,0),14)=0)*(AB201>=IFERROR('Recurring Items'!$G$6:$G$56,9000000000))+('Recurring Items'!$E$6:$E$56="Weekly")*(WEEKDAY(AB201)=IFERROR(WEEKDAY('Recurring Items'!$G$6:$G$56),0))*(AB201>=IFERROR('Recurring Items'!$G$6:$G$56,9000000000))+('Recurring Items'!$E$6:$E$56="One-time")*(AB201='Recurring Items'!$G$6:$G$56))) -> 0 | AE201: =SUMPRODUCT(('Recurring Items'!$C$6:$C$56="Expense")*('Recurring Items'!$H$6:$H$56<>"Skip")*IFERROR(N('Recurring Items'!$D$6:$D$56),0)*(('Recurring Items'!$E$6:$E$56="Monthly")*(DAY(AB201)='Recurring Items'!$F$6:$F$56)+('Recurring Items'!$E$6:$E$56="Bi-weekly")*(WEEKDAY(AB201)=IFERROR(WEEKDAY('Recurring Items'!$G$6:$G$56),0))*(MOD(AB201-IFERROR('Recurring Items'!$G$6:$G$56,0),14)=0)*(AB201>=IFERROR('Recurring Items'!$G$6:$G$56,9000000000))+('Recurring Items'!$E$6:$E$56="Weekly")*(WEEKDAY(AB201)=IFERROR(WEEKDAY('Recurring Items'!$G$6:$G$56),0))*(AB201>=IFERROR('Recurring Items'!$G$6:$G$56,9000000000))+('Recurring Items'!$E$6:$E$56="One-time")*(AB201='Recurring Items'!$G$6:$G$56))) -> 0 | AF201: =(IF(AC201=1,'Debt Tracker'!$P$5>0.01,INDEX('Debt Tracker'!$T$5:$AE$29,1,AC201-1)>0.01))*('Recurring Items'!$H$8<>"Skip")*(DAY(AB201)='Recurring Items'!$F$8)*IFERROR(N('Recurring Items'!$D$8),0)+(IF(AC201=1,'Debt Tracker'!$P$6>0.01,INDEX('Debt Tracker'!$T$5:$AE$29,2,AC201-1)>0.01))*('Recurring Items'!$H$9<>"Skip")*(DAY(AB201)='Recurring Items'!$F$9)*IFERROR(N('Recurring Items'!$D$9),0)+(IF(AC201=1,'Debt Tracker'!$P$7>0.01,INDEX('Debt Tracker'!$T$5:$AE$29,3,AC201-1)>0.01))*('Recurring Items'!$H$10<>"Skip")*(DAY(AB201)='Recurring Items'!$F$10)*IFERROR(N('Recurring Items'!$D$10),0)+(IF(AC201=1,'Debt Tracker'!$P$8>0.01,INDEX('Debt Tracker'!$T$5:$AE$29,4,AC201-1)>0.01))*('Recurring Items'!$H$11<>"Skip")*(DAY(AB201)='Recurring Items'!$F$11)*IFERROR(N('Recurring Items'!$D$11),0)+(IF(AC201=1,'Debt Tracker'!$P$9>0.01,INDEX('Debt Tracker'!$T$5:$AE$29,5,AC201-1)>0.01))*('Recurring Items'!$H$12<>"Skip")*(DAY(AB201)='Recurring Items'!$F$12)*IFERROR(N('Recurring Items'!$D$12),0)+(IF(AC201=1,'Debt Tracker'!$P$10>0.01,INDEX('Debt Tracker'!$T$5:$AE$29,6,AC201-1)>0.01))*('Recurring Items'!$H$13<>"Skip")*(DAY(AB201)='Recurring Items'!$F$13)*IFERROR(N('Recurring Items'!$D$13),0)+(IF(AC201=1,'Debt Tracker'!$P$11>0.01,INDEX('Debt Tracker'!$T$5:$AE$29,7,AC201-1)>0.01))*('Recurring Items'!$H$14<>"Skip")*(DAY(AB201)='Recurring Items'!$F$14)*IFERROR(N('Recurring Items'!$D$14),0)+(IF(AC201=1,'Debt Tracker'!$P$12>0.01,INDEX('Debt Tracker'!$T$5:$AE$29,8,AC201-1)>0.01))*('Recurring Items'!$H$15<>"Skip")*(DAY(AB201)='Recurring Items'!$F$15)*IFERROR(N('Recurring Items'!$D$15),0)+(IF(AC201=1,'Debt Tracker'!$P$13>0.01,INDEX('Debt Tracker'!$T$5:$AE$29,9,AC201-1)>0.01))*('Recurring Items'!$H$16<>"Skip")*(DAY(AB201)='Recurring Items'!$F$16)*IFERROR(N('Recurring Items'!$D$16),0)+(IF(AC201=1,'Debt Tracker'!$P$14>0.01,INDEX('Debt Tracker'!$T$5:$AE$29,10,AC201-1)>0.01))*('Recurring Items'!$H$17<>"Skip")*(DAY(AB201)='Recurring Items'!$F$17)*IFERROR(N('Recurring Items'!$D$17),0)+(IF(AC201=1,'Debt Tracker'!$P$15>0.01,INDEX('Debt Tracker'!$T$5:$AE$29,11,AC201-1)>0.01))*('Recurring Items'!$H$18<>"Skip")*(DAY(AB201)='Recurring Items'!$F$18)*IFERROR(N('Recurring Items'!$D$18),0)+(IF(AC201=1,'Debt Tracker'!$P$16>0.01,INDEX('Debt Tracker'!$T$5:$AE$29,12,AC201-1)>0.01))*('Recurring Items'!$H$19<>"Skip")*(DAY(AB201)='Recurring Items'!$F$19)*IFERROR(N('Recurring Items'!$D$19),0)+(IF(AC201=1,'Debt Tracker'!$P$17>0.01,INDEX('Debt Tracker'!$T$5:$AE$29,13,AC201-1)>0.01))*('Recurring Items'!$H$20<>"Skip")*(DAY(AB201)='Recurring Items'!$F$20)*IFERROR(N('Recurring Items'!$D$20),0)+(IF(AC201=1,'Debt Tracker'!$P$18>0.01,INDEX('Debt Tracker'!$T$5:$AE$29,14,AC201-1)>0.01))*('Recurring Items'!$H$21<>"Skip")*(DAY(AB201)='Recurring Items'!$F$21)*IFERROR(N('Recurring Items'!$D$21),0)+(IF(AC201=1,'Debt Tracker'!$P$19>0.01,INDEX('Debt Tracker'!$T$5:$AE$29,15,AC201-1)>0.01))*('Recurring Items'!$H$22<>"Skip")*(DAY(AB201)='Recurring Items'!$F$22)*IFERROR(N('Recurring Items'!$D$22),0)+(IF(AC201=1,'Debt Tracker'!$P$20>0.01,INDEX('Debt Tracker'!$T$5:$AE$29,16,AC201-1)>0.01))*('Recurring Items'!$H$23<>"Skip")*(DAY(AB201)='Recurring Items'!$F$23)*IFERROR(N('Recurring Items'!$D$23),0)+(IF(AC201=1,'Debt Tracker'!$P$21>0.01,INDEX('Debt Tracker'!$T$5:$AE$29,17,AC201-1)>0.01))*('Recurring Items'!$H$24<>"Skip")*(DAY(AB201)='Recurring Items'!$F$24)*IFERROR(N('Recurring Items'!$D$24),0)+(IF(AC201=1,'Debt Tracker'!$P$22>0.01,INDEX('Debt Tracker'!$T$5:$AE$29,18,AC201-1)>0.01))*('Recurring Items'!$H$25<>"Skip")*(DAY(AB201)='Recurring Items'!$F$25)*IFERROR(N('Recurring Items'!$D$25),0)+(IF(AC201=1,'Debt Tracker'!$P$23>0.01,INDEX('Debt Tracker'!$T$5:$AE$29,19,AC201-1)>0.01))*('Recurring Items'!$H$26<>"Skip")*(DAY(AB201)='Recurring Items'!$F$26)*IFERROR(N('Recurring Items'!$D$26),0)+(IF(AC201=1,'Debt Tracker'!$P$24>0.01,INDEX('Debt Tracker'!$T$5:$AE$29,20,AC201-1)>0.01))*('Recurring Items'!$H$27<>"Skip")*(DAY(AB201)='Recurring Items'!$F$27)*IFERROR(N('Recurring Items'!$D$27),0)+(IF(AC201=1,'Debt Tracker'!$P$25>0.01,INDEX('Debt Tracker'!$T$5:$AE$29,21,AC201-1)>0.01))*('Recurring Items'!$H$28<>"Skip")*(DAY(AB201)='Recurring Items'!$F$28)*IFERROR(N('Recurring Items'!$D$28),0)+(IF(AC201=1,'Debt Tracker'!$P$26>0.01,INDEX('Debt Tracker'!$T$5:$AE$29,22,AC201-1)>0.01))*('Recurring Items'!$H$29<>"Skip")*(DAY(AB201)='Recurring Items'!$F$29)*IFERROR(N('Recurring Items'!$D$29),0)+(IF(AC201=1,'Debt Tracker'!$P$27>0.01,INDEX('Debt Tracker'!$T$5:$AE$29,23,AC201-1)>0.01))*('Recurring Items'!$H$30<>"Skip")*(DAY(AB201)='Recurring Items'!$F$30)*IFERROR(N('Recurring Items'!$D$30),0)+(IF(AC201=1,'Debt Tracker'!$P$28>0.01,INDEX('Debt Tracker'!$T$5:$AE$29,24,AC201-1)>0.01))*('Recurring Items'!$H$31<>"Skip")*(DAY(AB201)='Recurring Items'!$F$31)*IFERROR(N('Recurring Items'!$D$31),0)+(IF(AC201=1,'Debt Tracker'!$P$29>0.01,INDEX('Debt Tracker'!$T$5:$AE$29,25,AC201-1)>0.01))*('Recurring Items'!$H$32<>"Skip")*(DAY(AB201)='Recurring Items'!$F$32)*IFERROR(N('Recurring Items'!$D$32),0) -> 1309.17 | AG201: =AD201-AE201-AF201 -> -1309.17 | AH201: =AH200+AG201 -> 4760.05
AA202: 2 | AB202: =$D$3+2 -> 46145 | AC202: =MIN(12,1+DATEDIF($D$3,AB202,"M")) -> 1 | AD202: =SUMPRODUCT(('Recurring Items'!$C$6:$C$56="Income")*('Recurring Items'!$H$6:$H$56<>"Skip")*IFERROR(N('Recurring Items'!$D$6:$D$56),0)*(('Recurring Items'!$E$6:$E$56="Monthly")*(DAY(AB202)='Recurring Items'!$F$6:$F$56)+('Recurring Items'!$E$6:$E$56="Bi-weekly")*(WEEKDAY(AB202)=IFERROR(WEEKDAY('Recurring Items'!$G$6:$G$56),0))*(MOD(AB202-IFERROR('Recurring Items'!$G$6:$G$56,0),14)=0)*(AB202>=IFERROR('Recurring Items'!$G$6:$G$56,9000000000))+('Recurring Items'!$E$6:$E$56="Weekly")*(WEEKDAY(AB202)=IFERROR(WEEKDAY('Recurring Items'!$G$6:$G$56),0))*(AB202>=IFERROR('Recurring Items'!$G$6:$G$56,9000000000))+('Recurring Items'!$E$6:$E$56="One-time")*(AB202='Recurring Items'!$G$6:$G$56))) -> 0 | AE202: =SUMPRODUCT(('Recurring Items'!$C$6:$C$56="Expense")*('Recurring Items'!$H$6:$H$56<>"Skip")*IFERROR(N('Recurring Items'!$D$6:$D$56),0)*(('Recurring Items'!$E$6:$E$56="Monthly")*(DAY(AB202)='Recurring Items'!$F$6:$F$56)+('Recurring Items'!$E$6:$E$56="Bi-weekly")*(WEEKDAY(AB202)=IFERROR(WEEKDAY('Recurring Items'!$G$6:$G$56),0))*(MOD(AB202-IFERROR('Recurring Items'!$G$6:$G$56,0),14)=0)*(AB202>=IFERROR('Recurring Items'!$G$6:$G$56,9000000000))+('Recurring Items'!$E$6:$E$56="Weekly")*(WEEKDAY(AB202)=IFERROR(WEEKDAY('Recurring Items'!$G$6:$G$56),0))*(AB202>=IFERROR('Recurring Items'!$G$6:$G$56,9000000000))+('Recurring Items'!$E$6:$E$56="One-time")*(AB202='Recurring Items'!$G$6:$G$56))) -> 927.53 | AF202: =(IF(AC202=1,'Debt Tracker'!$P$5>0.01,INDEX('Debt Tracker'!$T$5:$AE$29,1,AC202-1)>0.01))*('Recurring Items'!$H$8<>"Skip")*(DAY(AB202)='Recurring Items'!$F$8)*IFERROR(N('Recurring Items'!$D$8),0)+(IF(AC202=1,'Debt Tracker'!$P$6>0.01,INDEX('Debt Tracker'!$T$5:$AE$29,2,AC202-1)>0.01))*('Recurring Items'!$H$9<>"Skip")*(DAY(AB202)='Recurring Items'!$F$9)*IFERROR(N('Recurring Items'!$D$9),0)+(IF(AC202=1,'Debt Tracker'!$P$7>0.01,INDEX('Debt Tracker'!$T$5:$AE$29,3,AC202-1)>0.01))*('Recurring Items'!$H$10<>"Skip")*(DAY(AB202)='Recurring Items'!$F$10)*IFERROR(N('Recurring Items'!$D$10),0)+(IF(AC202=1,'Debt Tracker'!$P$8>0.01,INDEX('Debt Tracker'!$T$5:$AE$29,4,AC202-1)>0.01))*('Recurring Items'!$H$11<>"Skip")*(DAY(AB202)='Recurring Items'!$F$11)*IFERROR(N('Recurring Items'!$D$11),0)+(IF(AC202=1,'Debt Tracker'!$P$9>0.01,INDEX('Debt Tracker'!$T$5:$AE$29,5,AC202-1)>0.01))*('Recurring Items'!$H$12<>"Skip")*(DAY(AB202)='Recurring Items'!$F$12)*IFERROR(N('Recurring Items'!$D$12),0)+(IF(AC202=1,'Debt Tracker'!$P$10>0.01,INDEX('Debt Tracker'!$T$5:$AE$29,6,AC202-1)>0.01))*('Recurring Items'!$H$13<>"Skip")*(DAY(AB202)='Recurring Items'!$F$13)*IFERROR(N('Recurring Items'!$D$13),0)+(IF(AC202=1,'Debt Tracker'!$P$11>0.01,INDEX('Debt Tracker'!$T$5:$AE$29,7,AC202-1)>0.01))*('Recurring Items'!$H$14<>"Skip")*(DAY(AB202)='Recurring Items'!$F$14)*IFERROR(N('Recurring Items'!$D$14),0)+(IF(AC202=1,'Debt Tracker'!$P$12>0.01,INDEX('Debt Tracker'!$T$5:$AE$29,8,AC202-1)>0.01))*('Recurring Items'!$H$15<>"Skip")*(DAY(AB202)='Recurring Items'!$F$15)*IFERROR(N('Recurring Items'!$D$15),0)+(IF(AC202=1,'Debt Tracker'!$P$13>0.01,INDEX('Debt Tracker'!$T$5:$AE$29,9,AC202-1)>0.01))*('Recurring Items'!$H$16<>"Skip")*(DAY(AB202)='Recurring Items'!$F$16)*IFERROR(N('Recurring Items'!$D$16),0)+(IF(AC202=1,'Debt Tracker'!$P$14>0.01,INDEX('Debt Tracker'!$T$5:$AE$29,10,AC202-1)>0.01))*('Recurring Items'!$H$17<>"Skip")*(DAY(AB202)='Recurring Items'!$F$17)*IFERROR(N('Recurring Items'!$D$17),0)+(IF(AC202=1,'Debt Tracker'!$P$15>0.01,INDEX('Debt Tracker'!$T$5:$AE$29,11,AC202-1)>0.01))*('Recurring Items'!$H$18<>"Skip")*(DAY(AB202)='Recurring Items'!$F$18)*IFERROR(N('Recurring Items'!$D$18),0)+(IF(AC202=1,'Debt Tracker'!$P$16>0.01,INDEX('Debt Tracker'!$T$5:$AE$29,12,AC202-1)>0.01))*('Recurring Items'!$H$19<>"Skip")*(DAY(AB202)='Recurring Items'!$F$19)*IFERROR(N('Recurring Items'!$D$19),0)+(IF(AC202=1,'Debt Tracker'!$P$17>0.01,INDEX('Debt Tracker'!$T$5:$AE$29,13,AC202-1)>0.01))*('Recurring Items'!$H$20<>"Skip")*(DAY(AB202)='Recurring Items'!$F$20)*IFERROR(N('Recurring Items'!$D$20),0)+(IF(AC202=1,'Debt Tracker'!$P$18>0.01,INDEX('Debt Tracker'!$T$5:$AE$29,14,AC202-1)>0.01))*('Recurring Items'!$H$21<>"Skip")*(DAY(AB202)='Recurring Items'!$F$21)*IFERROR(N('Recurring Items'!$D$21),0)+(IF(AC202=1,'Debt Tracker'!$P$19>0.01,INDEX('Debt Tracker'!$T$5:$AE$29,15,AC202-1)>0.01))*('Recurring Items'!$H$22<>"Skip")*(DAY(AB202)='Recurring Items'!$F$22)*IFERROR(N('Recurring Items'!$D$22),0)+(IF(AC202=1,'Debt Tracker'!$P$20>0.01,INDEX('Debt Tracker'!$T$5:$AE$29,16,AC202-1)>0.01))*('Recurring Items'!$H$23<>"Skip")*(DAY(AB202)='Recurring Items'!$F$23)*IFERROR(N('Recurring Items'!$D$23),0)+(IF(AC202=1,'Debt Tracker'!$P$21>0.01,INDEX('Debt Tracker'!$T$5:$AE$29,17,AC202-1)>0.01))*('Recurring Items'!$H$24<>"Skip")*(DAY(AB202)='Recurring Items'!$F$24)*IFERROR(N('Recurring Items'!$D$24),0)+(IF(AC202=1,'Debt Tracker'!$P$22>0.01,INDEX('Debt Tracker'!$T$5:$AE$29,18,AC202-1)>0.01))*('Recurring Items'!$H$25<>"Skip")*(DAY(AB202)='Recurring Items'!$F$25)*IFERROR(N('Recurring Items'!$D$25),0)+(IF(AC202=1,'Debt Tracker'!$P$23>0.01,INDEX('Debt Tracker'!$T$5:$AE$29,19,AC202-1)>0.01))*('Recurring Items'!$H$26<>"Skip")*(DAY(AB202)='Recurring Items'!$F$26)*IFERROR(N('Recurring Items'!$D$26),0)+(IF(AC202=1,'Debt Tracker'!$P$24>0.01,INDEX('Debt Tracker'!$T$5:$AE$29,20,AC202-1)>0.01))*('Recurring Items'!$H$27<>"Skip")*(DAY(AB202)='Recurring Items'!$F$27)*IFERROR(N('Recurring Items'!$D$27),0)+(IF(AC202=1,'Debt Tracker'!$P$25>0.01,INDEX('Debt Tracker'!$T$5:$AE$29,21,AC202-1)>0.01))*('Recurring Items'!$H$28<>"Skip")*(DAY(AB202)='Recurring Items'!$F$28)*IFERROR(N('Recurring Items'!$D$28),0)+(IF(AC202=1,'Debt Tracker'!$P$26>0.01,INDEX('Debt Tracker'!$T$5:$AE$29,22,AC202-1)>0.01))*('Recurring Items'!$H$29<>"Skip")*(DAY(AB202)='Recurring Items'!$F$29)*IFERROR(N('Recurring Items'!$D$29),0)+(IF(AC202=1,'Debt Tracker'!$P$27>0.01,INDEX('Debt Tracker'!$T$5:$AE$29,23,AC202-1)>0.01))*('Recurring Items'!$H$30<>"Skip")*(DAY(AB202)='Recurring Items'!$F$30)*IFERROR(N('Recurring Items'!$D$30),0)+(IF(AC202=1,'Debt Tracker'!$P$28>0.01,INDEX('Debt Tracker'!$T$5:$AE$29,24,AC202-1)>0.01))*('Recurring Items'!$H$31<>"Skip")*(DAY(AB202)='Recurring Items'!$F$31)*IFERROR(N('Recurring Items'!$D$31),0)+(IF(AC202=1,'Debt Tracker'!$P$29>0.01,INDEX('Debt Tracker'!$T$5:$AE$29,25,AC202-1)>0.01))*('Recurring Items'!$H$32<>"Skip")*(DAY(AB202)='Recurring Items'!$F$32)*IFERROR(N('Recurring Items'!$D$32),0) -> 0 | AG202: =AD202-AE202-AF202 -> -927.53 | AH202: =AH201+AG202 -> 3832.52
AA203: 3 | AB203: =$D$3+3 -> 46146 | AC203: =MIN(12,1+DATEDIF($D$3,AB203,"M")) -> 1 | AD203: =SUMPRODUCT(('Recurring Items'!$C$6:$C$56="Income")*('Recurring Items'!$H$6:$H$56<>"Skip")*IFERROR(N('Recurring Items'!$D$6:$D$56),0)*(('Recurring Items'!$E$6:$E$56="Monthly")*(DAY(AB203)='Recurring Items'!$F$6:$F$56)+('Recurring Items'!$E$6:$E$56="Bi-weekly")*(WEEKDAY(AB203)=IFERROR(WEEKDAY('Recurring Items'!$G$6:$G$56),0))*(MOD(AB203-IFERROR('Recurring Items'!$G$6:$G$56,0),14)=0)*(AB203>=IFERROR('Recurring Items'!$G$6:$G$56,9000000000))+('Recurring Items'!$E$6:$E$56="Weekly")*(WEEKDAY(AB203)=IFERROR(WEEKDAY('Recurring Items'!$G$6:$G$56),0))*(AB203>=IFERROR('Recurring Items'!$G$6:$G$56,9000000000))+('Recurring Items'!$E$6:$E$56="One-time")*(AB203='Recurring Items'!$G$6:$G$56))) -> 0 | AE203: =SUMPRODUCT(('Recurring Items'!$C$6:$C$56="Expense")*('Recurring Items'!$H$6:$H$56<>"Skip")*IFERROR(N('Recurring Items'!$D$6:$D$56),0)*(('Recurring Items'!$E$6:$E$56="Monthly")*(DAY(AB203)='Recurring Items'!$F$6:$F$56)+('Recurring Items'!$E$6:$E$56="Bi-weekly")*(WEEKDAY(AB203)=IFERROR(WEEKDAY('Recurring Items'!$G$6:$G$56),0))*(MOD(AB203-IFERROR('Recurring Items'!$G$6:$G$56,0),14)=0)*(AB203>=IFERROR('Recurring Items'!$G$6:$G$56,9000000000))+('Recurring Items'!$E$6:$E$56="Weekly")*(WEEKDAY(AB203)=IFERROR(WEEKDAY('Recurring Items'!$G$6:$G$56),0))*(AB203>=IFERROR('Recurring Items'!$G$6:$G$56,9000000000))+('Recurring Items'!$E$6:$E$56="One-time")*(AB203='Recurring Items'!$G$6:$G$56))) -> 0 | AF203: =(IF(AC203=1,'Debt Tracker'!$P$5>0.01,INDEX('Debt Tracker'!$T$5:$AE$29,1,AC203-1)>0.01))*('Recurring Items'!$H$8<>"Skip")*(DAY(AB203)='Recurring Items'!$F$8)*IFERROR(N('Recurring Items'!$D$8),0)+(IF(AC203=1,'Debt Tracker'!$P$6>0.01,INDEX('Debt Tracker'!$T$5:$AE$29,2,AC203-1)>0.01))*('Recurring Items'!$H$9<>"Skip")*(DAY(AB203)='Recurring Items'!$F$9)*IFERROR(N('Recurring Items'!$D$9),0)+(IF(AC203=1,'Debt Tracker'!$P$7>0.01,INDEX('Debt Tracker'!$T$5:$AE$29,3,AC203-1)>0.01))*('Recurring Items'!$H$10<>"Skip")*(DAY(AB203)='Recurring Items'!$F$10)*IFERROR(N('Recurring Items'!$D$10),0)+(IF(AC203=1,'Debt Tracker'!$P$8>0.01,INDEX('Debt Tracker'!$T$5:$AE$29,4,AC203-1)>0.01))*('Recurring Items'!$H$11<>"Skip")*(DAY(AB203)='Recurring Items'!$F$11)*IFERROR(N('Recurring Items'!$D$11),0)+(IF(AC203=1,'Debt Tracker'!$P$9>0.01,INDEX('Debt Tracker'!$T$5:$AE$29,5,AC203-1)>0.01))*('Recurring Items'!$H$12<>"Skip")*(DAY(AB203)='Recurring Items'!$F$12)*IFERROR(N('Recurring Items'!$D$12),0)+(IF(AC203=1,'Debt Tracker'!$P$10>0.01,INDEX('Debt Tracker'!$T$5:$AE$29,6,AC203-1)>0.01))*('Recurring Items'!$H$13<>"Skip")*(DAY(AB203)='Recurring Items'!$F$13)*IFERROR(N('Recurring Items'!$D$13),0)+(IF(AC203=1,'Debt Tracker'!$P$11>0.01,INDEX('Debt Tracker'!$T$5:$AE$29,7,AC203-1)>0.01))*('Recurring Items'!$H$14<>"Skip")*(DAY(AB203)='Recurring Items'!$F$14)*IFERROR(N('Recurring Items'!$D$14),0)+(IF(AC203=1,'Debt Tracker'!$P$12>0.01,INDEX('Debt Tracker'!$T$5:$AE$29,8,AC203-1)>0.01))*('Recurring Items'!$H$15<>"Skip")*(DAY(AB203)='Recurring Items'!$F$15)*IFERROR(N('Recurring Items'!$D$15),0)+(IF(AC203=1,'Debt Tracker'!$P$13>0.01,INDEX('Debt Tracker'!$T$5:$AE$29,9,AC203-1)>0.01))*('Recurring Items'!$H$16<>"Skip")*(DAY(AB203)='Recurring Items'!$F$16)*IFERROR(N('Recurring Items'!$D$16),0)+(IF(AC203=1,'Debt Tracker'!$P$14>0.01,INDEX('Debt Tracker'!$T$5:$AE$29,10,AC203-1)>0.01))*('Recurring Items'!$H$17<>"Skip")*(DAY(AB203)='Recurring Items'!$F$17)*IFERROR(N('Recurring Items'!$D$17),0)+(IF(AC203=1,'Debt Tracker'!$P$15>0.01,INDEX('Debt Tracker'!$T$5:$AE$29,11,AC203-1)>0.01))*('Recurring Items'!$H$18<>"Skip")*(DAY(AB203)='Recurring Items'!$F$18)*IFERROR(N('Recurring Items'!$D$18),0)+(IF(AC203=1,'Debt Tracker'!$P$16>0.01,INDEX('Debt Tracker'!$T$5:$AE$29,12,AC203-1)>0.01))*('Recurring Items'!$H$19<>"Skip")*(DAY(AB203)='Recurring Items'!$F$19)*IFERROR(N('Recurring Items'!$D$19),0)+(IF(AC203=1,'Debt Tracker'!$P$17>0.01,INDEX('Debt Tracker'!$T$5:$AE$29,13,AC203-1)>0.01))*('Recurring Items'!$H$20<>"Skip")*(DAY(AB203)='Recurring Items'!$F$20)*IFERROR(N('Recurring Items'!$D$20),0)+(IF(AC203=1,'Debt Tracker'!$P$18>0.01,INDEX('Debt Tracker'!$T$5:$AE$29,14,AC203-1)>0.01))*('Recurring Items'!$H$21<>"Skip")*(DAY(AB203)='Recurring Items'!$F$21)*IFERROR(N('Recurring Items'!$D$21),0)+(IF(AC203=1,'Debt Tracker'!$P$19>0.01,INDEX('Debt Tracker'!$T$5:$AE$29,15,AC203-1)>0.01))*('Recurring Items'!$H$22<>"Skip")*(DAY(AB203)='Recurring Items'!$F$22)*IFERROR(N('Recurring Items'!$D$22),0)+(IF(AC203=1,'Debt Tracker'!$P$20>0.01,INDEX('Debt Tracker'!$T$5:$AE$29,16,AC203-1)>0.01))*('Recurring Items'!$H$23<>"Skip")*(DAY(AB203)='Recurring Items'!$F$23)*IFERROR(N('Recurring Items'!$D$23),0)+(IF(AC203=1,'Debt Tracker'!$P$21>0.01,INDEX('Debt Tracker'!$T$5:$AE$29,17,AC203-1)>0.01))*('Recurring Items'!$H$24<>"Skip")*(DAY(AB203)='Recurring Items'!$F$24)*IFERROR(N('Recurring Items'!$D$24),0)+(IF(AC203=1,'Debt Tracker'!$P$22>0.01,INDEX('Debt Tracker'!$T$5:$AE$29,18,AC203-1)>0.01))*('Recurring Items'!$H$25<>"Skip")*(DAY(AB203)='Recurring Items'!$F$25)*IFERROR(N('Recurring Items'!$D$25),0)+(IF(AC203=1,'Debt Tracker'!$P$23>0.01,INDEX('Debt Tracker'!$T$5:$AE$29,19,AC203-1)>0.01))*('Recurring Items'!$H$26<>"Skip")*(DAY(AB203)='Recurring Items'!$F$26)*IFERROR(N('Recurring Items'!$D$26),0)+(IF(AC203=1,'Debt Tracker'!$P$24>0.01,INDEX('Debt Tracker'!$T$5:$AE$29,20,AC203-1)>0.01))*('Recurring Items'!$H$27<>"Skip")*(DAY(AB203)='Recurring Items'!$F$27)*IFERROR(N('Recurring Items'!$D$27),0)+(IF(AC203=1,'Debt Tracker'!$P$25>0.01,INDEX('Debt Tracker'!$T$5:$AE$29,21,AC203-1)>0.01))*('Recurring Items'!$H$28<>"Skip")*(DAY(AB203)='Recurring Items'!$F$28)*IFERROR(N('Recurring Items'!$D$28),0)+(IF(AC203=1,'Debt Tracker'!$P$26>0.01,INDEX('Debt Tracker'!$T$5:$AE$29,22,AC203-1)>0.01))*('Recurring Items'!$H$29<>"Skip")*(DAY(AB203)='Recurring Items'!$F$29)*IFERROR(N('Recurring Items'!$D$29),0)+(IF(AC203=1,'Debt Tracker'!$P$27>0.01,INDEX('Debt Tracker'!$T$5:$AE$29,23,AC203-1)>0.01))*('Recurring Items'!$H$30<>"Skip")*(DAY(AB203)='Recurring Items'!$F$30)*IFERROR(N('Recurring Items'!$D$30),0)+(IF(AC203=1,'Debt Tracker'!$P$28>0.01,INDEX('Debt Tracker'!$T$5:$AE$29,24,AC203-1)>0.01))*('Recurring Items'!$H$31<>"Skip")*(DAY(AB203)='Recurring Items'!$F$31)*IFERROR(N('Recurring Items'!$D$31),0)+(IF(AC203=1,'Debt Tracker'!$P$29>0.01,INDEX('Debt Tracker'!$T$5:$AE$29,25,AC203-1)>0.01))*('Recurring Items'!$H$32<>"Skip")*(DAY(AB203)='Recurring Items'!$F$32)*IFERROR(N('Recurring Items'!$D$32),0) -> 0 | AG203: =AD203-AE203-AF203 -> 0 | AH203: =AH202+AG203 -> 3832.52
AA204: 4 | AB204: =$D$3+4 -> 46147 | AC204: =MIN(12,1+DATEDIF($D$3,AB204,"M")) -> 1 | AD204: =SUMPRODUCT(('Recurring Items'!$C$6:$C$56="Income")*('Recurring Items'!$H$6:$H$56<>"Skip")*IFERROR(N('Recurring Items'!$D$6:$D$56),0)*(('Recurring Items'!$E$6:$E$56="Monthly")*(DAY(AB204)='Recurring Items'!$F$6:$F$56)+('Recurring Items'!$E$6:$E$56="Bi-weekly")*(WEEKDAY(AB204)=IFERROR(WEEKDAY('Recurring Items'!$G$6:$G$56),0))*(MOD(AB204-IFERROR('Recurring Items'!$G$6:$G$56,0),14)=0)*(AB204>=IFERROR('Recurring Items'!$G$6:$G$56,9000000000))+('Recurring Items'!$E$6:$E$56="Weekly")*(WEEKDAY(AB204)=IFERROR(WEEKDAY('Recurring Items'!$G$6:$G$56),0))*(AB204>=IFERROR('Recurring Items'!$G$6:$G$56,9000000000))+('Recurring Items'!$E$6:$E$56="One-time")*(AB204='Recurring Items'!$G$6:$G$56))) -> 0 | AE204: =SUMPRODUCT(('Recurring Items'!$C$6:$C$56="Expense")*('Recurring Items'!$H$6:$H$56<>"Skip")*IFERROR(N('Recurring Items'!$D$6:$D$56),0)*(('Recurring Items'!$E$6:$E$56="Monthly")*(DAY(AB204)='Recurring Items'!$F$6:$F$56)+('Recurring Items'!$E$6:$E$56="Bi-weekly")*(WEEKDAY(AB204)=IFERROR(WEEKDAY('Recurring Items'!$G$6:$G$56),0))*(MOD(AB204-IFERROR('Recurring Items'!$G$6:$G$56,0),14)=0)*(AB204>=IFERROR('Recurring Items'!$G$6:$G$56,9000000000))+('Recurring Items'!$E$6:$E$56="Weekly")*(WEEKDAY(AB204)=IFERROR(WEEKDAY('Recurring Items'!$G$6:$G$56),0))*(AB204>=IFERROR('Recurring Items'!$G$6:$G$56,9000000000))+('Recurring Items'!$E$6:$E$56="One-time")*(AB204='Recurring Items'!$G$6:$G$56))) -> 51.01 | AF204: =(IF(AC204=1,'Debt Tracker'!$P$5>0.01,INDEX('Debt Tracker'!$T$5:$AE$29,1,AC204-1)>0.01))*('Recurring Items'!$H$8<>"Skip")*(DAY(AB204)='Recurring Items'!$F$8)*IFERROR(N('Recurring Items'!$D$8),0)+(IF(AC204=1,'Debt Tracker'!$P$6>0.01,INDEX('Debt Tracker'!$T$5:$AE$29,2,AC204-1)>0.01))*('Recurring Items'!$H$9<>"Skip")*(DAY(AB204)='Recurring Items'!$F$9)*IFERROR(N('Recurring Items'!$D$9),0)+(IF(AC204=1,'Debt Tracker'!$P$7>0.01,INDEX('Debt Tracker'!$T$5:$AE$29,3,AC204-1)>0.01))*('Recurring Items'!$H$10<>"Skip")*(DAY(AB204)='Recurring Items'!$F$10)*IFERROR(N('Recurring Items'!$D$10),0)+(IF(AC204=1,'Debt Tracker'!$P$8>0.01,INDEX('Debt Tracker'!$T$5:$AE$29,4,AC204-1)>0.01))*('Recurring Items'!$H$11<>"Skip")*(DAY(AB204)='Recurring Items'!$F$11)*IFERROR(N('Recurring Items'!$D$11),0)+(IF(AC204=1,'Debt Tracker'!$P$9>0.01,INDEX('Debt Tracker'!$T$5:$AE$29,5,AC204-1)>0.01))*('Recurring Items'!$H$12<>"Skip")*(DAY(AB204)='Recurring Items'!$F$12)*IFERROR(N('Recurring Items'!$D$12),0)+(IF(AC204=1,'Debt Tracker'!$P$10>0.01,INDEX('Debt Tracker'!$T$5:$AE$29,6,AC204-1)>0.01))*('Recurring Items'!$H$13<>"Skip")*(DAY(AB204)='Recurring Items'!$F$13)*IFERROR(N('Recurring Items'!$D$13),0)+(IF(AC204=1,'Debt Tracker'!$P$11>0.01,INDEX('Debt Tracker'!$T$5:$AE$29,7,AC204-1)>0.01))*('Recurring Items'!$H$14<>"Skip")*(DAY(AB204)='Recurring Items'!$F$14)*IFERROR(N('Recurring Items'!$D$14),0)+(IF(AC204=1,'Debt Tracker'!$P$12>0.01,INDEX('Debt Tracker'!$T$5:$AE$29,8,AC204-1)>0.01))*('Recurring Items'!$H$15<>"Skip")*(DAY(AB204)='Recurring Items'!$F$15)*IFERROR(N('Recurring Items'!$D$15),0)+(IF(AC204=1,'Debt Tracker'!$P$13>0.01,INDEX('Debt Tracker'!$T$5:$AE$29,9,AC204-1)>0.01))*('Recurring Items'!$H$16<>"Skip")*(DAY(AB204)='Recurring Items'!$F$16)*IFERROR(N('Recurring Items'!$D$16),0)+(IF(AC204=1,'Debt Tracker'!$P$14>0.01,INDEX('Debt Tracker'!$T$5:$AE$29,10,AC204-1)>0.01))*('Recurring Items'!$H$17<>"Skip")*(DAY(AB204)='Recurring Items'!$F$17)*IFERROR(N('Recurring Items'!$D$17),0)+(IF(AC204=1,'Debt Tracker'!$P$15>0.01,INDEX('Debt Tracker'!$T$5:$AE$29,11,AC204-1)>0.01))*('Recurring Items'!$H$18<>"Skip")*(DAY(AB204)='Recurring Items'!$F$18)*IFERROR(N('Recurring Items'!$D$18),0)+(IF(AC204=1,'Debt Tracker'!$P$16>0.01,INDEX('Debt Tracker'!$T$5:$AE$29,12,AC204-1)>0.01))*('Recurring Items'!$H$19<>"Skip")*(DAY(AB204)='Recurring Items'!$F$19)*IFERROR(N('Recurring Items'!$D$19),0)+(IF(AC204=1,'Debt Tracker'!$P$17>0.01,INDEX('Debt Tracker'!$T$5:$AE$29,13,AC204-1)>0.01))*('Recurring Items'!$H$20<>"Skip")*(DAY(AB204)='Recurring Items'!$F$20)*IFERROR(N('Recurring Items'!$D$20),0)+(IF(AC204=1,'Debt Tracker'!$P$18>0.01,INDEX('Debt Tracker'!$T$5:$AE$29,14,AC204-1)>0.01))*('Recurring Items'!$H$21<>"Skip")*(DAY(AB204)='Recurring Items'!$F$21)*IFERROR(N('Recurring Items'!$D$21),0)+(IF(AC204=1,'Debt Tracker'!$P$19>0.01,INDEX('Debt Tracker'!$T$5:$AE$29,15,AC204-1)>0.01))*('Recurring Items'!$H$22<>"Skip")*(DAY(AB204)='Recurring Items'!$F$22)*IFERROR(N('Recurring Items'!$D$22),0)+(IF(AC204=1,'Debt Tracker'!$P$20>0.01,INDEX('Debt Tracker'!$T$5:$AE$29,16,AC204-1)>0.01))*('Recurring Items'!$H$23<>"Skip")*(DAY(AB204)='Recurring Items'!$F$23)*IFERROR(N('Recurring Items'!$D$23),0)+(IF(AC204=1,'Debt Tracker'!$P$21>0.01,INDEX('Debt Tracker'!$T$5:$AE$29,17,AC204-1)>0.01))*('Recurring Items'!$H$24<>"Skip")*(DAY(AB204)='Recurring Items'!$F$24)*IFERROR(N('Recurring Items'!$D$24),0)+(IF(AC204=1,'Debt Tracker'!$P$22>0.01,INDEX('Debt Tracker'!$T$5:$AE$29,18,AC204-1)>0.01))*('Recurring Items'!$H$25<>"Skip")*(DAY(AB204)='Recurring Items'!$F$25)*IFERROR(N('Recurring Items'!$D$25),0)+(IF(AC204=1,'Debt Tracker'!$P$23>0.01,INDEX('Debt Tracker'!$T$5:$AE$29,19,AC204-1)>0.01))*('Recurring Items'!$H$26<>"Skip")*(DAY(AB204)='Recurring Items'!$F$26)*IFERROR(N('Recurring Items'!$D$26),0)+(IF(AC204=1,'Debt Tracker'!$P$24>0.01,INDEX('Debt Tracker'!$T$5:$AE$29,20,AC204-1)>0.01))*('Recurring Items'!$H$27<>"Skip")*(DAY(AB204)='Recurring Items'!$F$27)*IFERROR(N('Recurring Items'!$D$27),0)+(IF(AC204=1,'Debt Tracker'!$P$25>0.01,INDEX('Debt Tracker'!$T$5:$AE$29,21,AC204-1)>0.01))*('Recurring Items'!$H$28<>"Skip")*(DAY(AB204)='Recurring Items'!$F$28)*IFERROR(N('Recurring Items'!$D$28),0)+(IF(AC204=1,'Debt Tracker'!$P$26>0.01,INDEX('Debt Tracker'!$T$5:$AE$29,22,AC204-1)>0.01))*('Recurring Items'!$H$29<>"Skip")*(DAY(AB204)='Recurring Items'!$F$29)*IFERROR(N('Recurring Items'!$D$29),0)+(IF(AC204=1,'Debt Tracker'!$P$27>0.01,INDEX('Debt Tracker'!$T$5:$AE$29,23,AC204-1)>0.01))*('Recurring Items'!$H$30<>"Skip")*(DAY(AB204)='Recurring Items'!$F$30)*IFERROR(N('Recurring Items'!$D$30),0)+(IF(AC204=1,'Debt Tracker'!$P$28>0.01,INDEX('Debt Tracker'!$T$5:$AE$29,24,AC204-1)>0.01))*('Recurring Items'!$H$31<>"Skip")*(DAY(AB204)='Recurring Items'!$F$31)*IFERROR(N('Recurring Items'!$D$31),0)+(IF(AC204=1,'Debt Tracker'!$P$29>0.01,INDEX('Debt Tracker'!$T$5:$AE$29,25,AC204-1)>0.01))*('Recurring Items'!$H$32<>"Skip")*(DAY(AB204)='Recurring Items'!$F$32)*IFERROR(N('Recurring Items'!$D$32),0) -> 0 | AG204: =AD204-AE204-AF204 -> -51.01 | AH204: =AH203+AG204 -> 3781.51
AA205: 5 | AB205: =$D$3+5 -> 46148 | AC205: =MIN(12,1+DATEDIF($D$3,AB205,"M")) -> 1 | AD205: =SUMPRODUCT(('Recurring Items'!$C$6:$C$56="Income")*('Recurring Items'!$H$6:$H$56<>"Skip")*IFERROR(N('Recurring Items'!$D$6:$D$56),0)*(('Recurring Items'!$E$6:$E$56="Monthly")*(DAY(AB205)='Recurring Items'!$F$6:$F$56)+('Recurring Items'!$E$6:$E$56="Bi-weekly")*(WEEKDAY(AB205)=IFERROR(WEEKDAY('Recurring Items'!$G$6:$G$56),0))*(MOD(AB205-IFERROR('Recurring Items'!$G$6:$G$56,0),14)=0)*(AB205>=IFERROR('Recurring Items'!$G$6:$G$56,9000000000))+('Recurring Items'!$E$6:$E$56="Weekly")*(WEEKDAY(AB205)=IFERROR(WEEKDAY('Recurring Items'!$G$6:$G$56),0))*(AB205>=IFERROR('Recurring Items'!$G$6:$G$56,9000000000))+('Recurring Items'!$E$6:$E$56="One-time")*(AB205='Recurring Items'!$G$6:$G$56))) -> 0 | AE205: =SUMPRODUCT(('Recurring Items'!$C$6:$C$56="Expense")*('Recurring Items'!$H$6:$H$56<>"Skip")*IFERROR(N('Recurring Items'!$D$6:$D$56),0)*(('Recurring Items'!$E$6:$E$56="Monthly")*(DAY(AB205)='Recurring Items'!$F$6:$F$56)+('Recurring Items'!$E$6:$E$56="Bi-weekly")*(WEEKDAY(AB205)=IFERROR(WEEKDAY('Recurring Items'!$G$6:$G$56),0))*(MOD(AB205-IFERROR('Recurring Items'!$G$6:$G$56,0),14)=0)*(AB205>=IFERROR('Recurring Items'!$G$6:$G$56,9000000000))+('Recurring Items'!$E$6:$E$56="Weekly")*(WEEKDAY(AB205)=IFERROR(WEEKDAY('Recurring Items'!$G$6:$G$56),0))*(AB205>=IFERROR('Recurring Items'!$G$6:$G$56,9000000000))+('Recurring Items'!$E$6:$E$56="One-time")*(AB205='Recurring Items'!$G$6:$G$56))) -> 651.55 | AF205: =(IF(AC205=1,'Debt Tracker'!$P$5>0.01,INDEX('Debt Tracker'!$T$5:$AE$29,1,AC205-1)>0.01))*('Recurring Items'!$H$8<>"Skip")*(DAY(AB205)='Recurring Items'!$F$8)*IFERROR(N('Recurring Items'!$D$8),0)+(IF(AC205=1,'Debt Tracker'!$P$6>0.01,INDEX('Debt Tracker'!$T$5:$AE$29,2,AC205-1)>0.01))*('Recurring Items'!$H$9<>"Skip")*(DAY(AB205)='Recurring Items'!$F$9)*IFERROR(N('Recurring Items'!$D$9),0)+(IF(AC205=1,'Debt Tracker'!$P$7>0.01,INDEX('Debt Tracker'!$T$5:$AE$29,3,AC205-1)>0.01))*('Recurring Items'!$H$10<>"Skip")*(DAY(AB205)='Recurring Items'!$F$10)*IFERROR(N('Recurring Items'!$D$10),0)+(IF(AC205=1,'Debt Tracker'!$P$8>0.01,INDEX('Debt Tracker'!$T$5:$AE$29,4,AC205-1)>0.01))*('Recurring Items'!$H$11<>"Skip")*(DAY(AB205)='Recurring Items'!$F$11)*IFERROR(N('Recurring Items'!$D$11),0)+(IF(AC205=1,'Debt Tracker'!$P$9>0.01,INDEX('Debt Tracker'!$T$5:$AE$29,5,AC205-1)>0.01))*('Recurring Items'!$H$12<>"Skip")*(DAY(AB205)='Recurring Items'!$F$12)*IFERROR(N('Recurring Items'!$D$12),0)+(IF(AC205=1,'Debt Tracker'!$P$10>0.01,INDEX('Debt Tracker'!$T$5:$AE$29,6,AC205-1)>0.01))*('Recurring Items'!$H$13<>"Skip")*(DAY(AB205)='Recurring Items'!$F$13)*IFERROR(N('Recurring Items'!$D$13),0)+(IF(AC205=1,'Debt Tracker'!$P$11>0.01,INDEX('Debt Tracker'!$T$5:$AE$29,7,AC205-1)>0.01))*('Recurring Items'!$H$14<>"Skip")*(DAY(AB205)='Recurring Items'!$F$14)*IFERROR(N('Recurring Items'!$D$14),0)+(IF(AC205=1,'Debt Tracker'!$P$12>0.01,INDEX('Debt Tracker'!$T$5:$AE$29,8,AC205-1)>0.01))*('Recurring Items'!$H$15<>"Skip")*(DAY(AB205)='Recurring Items'!$F$15)*IFERROR(N('Recurring Items'!$D$15),0)+(IF(AC205=1,'Debt Tracker'!$P$13>0.01,INDEX('Debt Tracker'!$T$5:$AE$29,9,AC205-1)>0.01))*('Recurring Items'!$H$16<>"Skip")*(DAY(AB205)='Recurring Items'!$F$16)*IFERROR(N('Recurring Items'!$D$16),0)+(IF(AC205=1,'Debt Tracker'!$P$14>0.01,INDEX('Debt Tracker'!$T$5:$AE$29,10,AC205-1)>0.01))*('Recurring Items'!$H$17<>"Skip")*(DAY(AB205)='Recurring Items'!$F$17)*IFERROR(N('Recurring Items'!$D$17),0)+(IF(AC205=1,'Debt Tracker'!$P$15>0.01,INDEX('Debt Tracker'!$T$5:$AE$29,11,AC205-1)>0.01))*('Recurring Items'!$H$18<>"Skip")*(DAY(AB205)='Recurring Items'!$F$18)*IFERROR(N('Recurring Items'!$D$18),0)+(IF(AC205=1,'Debt Tracker'!$P$16>0.01,INDEX('Debt Tracker'!$T$5:$AE$29,12,AC205-1)>0.01))*('Recurring Items'!$H$19<>"Skip")*(DAY(AB205)='Recurring Items'!$F$19)*IFERROR(N('Recurring Items'!$D$19),0)+(IF(AC205=1,'Debt Tracker'!$P$17>0.01,INDEX('Debt Tracker'!$T$5:$AE$29,13,AC205-1)>0.01))*('Recurring Items'!$H$20<>"Skip")*(DAY(AB205)='Recurring Items'!$F$20)*IFERROR(N('Recurring Items'!$D$20),0)+(IF(AC205=1,'Debt Tracker'!$P$18>0.01,INDEX('Debt Tracker'!$T$5:$AE$29,14,AC205-1)>0.01))*('Recurring Items'!$H$21<>"Skip")*(DAY(AB205)='Recurring Items'!$F$21)*IFERROR(N('Recurring Items'!$D$21),0)+(IF(AC205=1,'Debt Tracker'!$P$19>0.01,INDEX('Debt Tracker'!$T$5:$AE$29,15,AC205-1)>0.01))*('Recurring Items'!$H$22<>"Skip")*(DAY(AB205)='Recurring Items'!$F$22)*IFERROR(N('Recurring Items'!$D$22),0)+(IF(AC205=1,'Debt Tracker'!$P$20>0.01,INDEX('Debt Tracker'!$T$5:$AE$29,16,AC205-1)>0.01))*('Recurring Items'!$H$23<>"Skip")*(DAY(AB205)='Recurring Items'!$F$23)*IFERROR(N('Recurring Items'!$D$23),0)+(IF(AC205=1,'Debt Tracker'!$P$21>0.01,INDEX('Debt Tracker'!$T$5:$AE$29,17,AC205-1)>0.01))*('Recurring Items'!$H$24<>"Skip")*(DAY(AB205)='Recurring Items'!$F$24)*IFERROR(N('Recurring Items'!$D$24),0)+(IF(AC205=1,'Debt Tracker'!$P$22>0.01,INDEX('Debt Tracker'!$T$5:$AE$29,18,AC205-1)>0.01))*('Recurring Items'!$H$25<>"Skip")*(DAY(AB205)='Recurring Items'!$F$25)*IFERROR(N('Recurring Items'!$D$25),0)+(IF(AC205=1,'Debt Tracker'!$P$23>0.01,INDEX('Debt Tracker'!$T$5:$AE$29,19,AC205-1)>0.01))*('Recurring Items'!$H$26<>"Skip")*(DAY(AB205)='Recurring Items'!$F$26)*IFERROR(N('Recurring Items'!$D$26),0)+(IF(AC205=1,'Debt Tracker'!$P$24>0.01,INDEX('Debt Tracker'!$T$5:$AE$29,20,AC205-1)>0.01))*('Recurring Items'!$H$27<>"Skip")*(DAY(AB205)='Recurring Items'!$F$27)*IFERROR(N('Recurring Items'!$D$27),0)+(IF(AC205=1,'Debt Tracker'!$P$25>0.01,INDEX('Debt Tracker'!$T$5:$AE$29,21,AC205-1)>0.01))*('Recurring Items'!$H$28<>"Skip")*(DAY(AB205)='Recurring Items'!$F$28)*IFERROR(N('Recurring Items'!$D$28),0)+(IF(AC205=1,'Debt Tracker'!$P$26>0.01,INDEX('Debt Tracker'!$T$5:$AE$29,22,AC205-1)>0.01))*('Recurring Items'!$H$29<>"Skip")*(DAY(AB205)='Recurring Items'!$F$29)*IFERROR(N('Recurring Items'!$D$29),0)+(IF(AC205=1,'Debt Tracker'!$P$27>0.01,INDEX('Debt Tracker'!$T$5:$AE$29,23,AC205-1)>0.01))*('Recurring Items'!$H$30<>"Skip")*(DAY(AB205)='Recurring Items'!$F$30)*IFERROR(N('Recurring Items'!$D$30),0)+(IF(AC205=1,'Debt Tracker'!$P$28>0.01,INDEX('Debt Tracker'!$T$5:$AE$29,24,AC205-1)>0.01))*('Recurring Items'!$H$31<>"Skip")*(DAY(AB205)='Recurring Items'!$F$31)*IFERROR(N('Recurring Items'!$D$31),0)+(IF(AC205=1,'Debt Tracker'!$P$29>0.01,INDEX('Debt Tracker'!$T$5:$AE$29,25,AC205-1)>0.01))*('Recurring Items'!$H$32<>"Skip")*(DAY(AB205)='Recurring Items'!$F$32)*IFERROR(N('Recurring Items'!$D$32),0) -> 259.86 | AG205: =AD205-AE205-AF205 -> -911.41 | AH205: =AH204+AG205 -> 2870.1
AA206: 6 | AB206: =$D$3+6 -> 46149 | AC206: =MIN(12,1+DATEDIF($D$3,AB206,"M")) -> 1 | AD206: =SUMPRODUCT(('Recurring Items'!$C$6:$C$56="Income")*('Recurring Items'!$H$6:$H$56<>"Skip")*IFERROR(N('Recurring Items'!$D$6:$D$56),0)*(('Recurring Items'!$E$6:$E$56="Monthly")*(DAY(AB206)='Recurring Items'!$F$6:$F$56)+('Recurring Items'!$E$6:$E$56="Bi-weekly")*(WEEKDAY(AB206)=IFERROR(WEEKDAY('Recurring Items'!$G$6:$G$56),0))*(MOD(AB206-IFERROR('Recurring Items'!$G$6:$G$56,0),14)=0)*(AB206>=IFERROR('Recurring Items'!$G$6:$G$56,9000000000))+('Recurring Items'!$E$6:$E$56="Weekly")*(WEEKDAY(AB206)=IFERROR(WEEKDAY('Recurring Items'!$G$6:$G$56),0))*(AB206>=IFERROR('Recurring Items'!$G$6:$G$56,9000000000))+('Recurring Items'!$E$6:$E$56="One-time")*(AB206='Recurring Items'!$G$6:$G$56))) -> 2274.42 | AE206: =SUMPRODUCT(('Recurring Items'!$C$6:$C$56="Expense")*('Recurring Items'!$H$6:$H$56<>"Skip")*IFERROR(N('Recurring Items'!$D$6:$D$56),0)*(('Recurring Items'!$E$6:$E$56="Monthly")*(DAY(AB206)='Recurring Items'!$F$6:$F$56)+('Recurring Items'!$E$6:$E$56="Bi-weekly")*(WEEKDAY(AB206)=IFERROR(WEEKDAY('Recurring Items'!$G$6:$G$56),0))*(MOD(AB206-IFERROR('Recurring Items'!$G$6:$G$56,0),14)=0)*(AB206>=IFERROR('Recurring Items'!$G$6:$G$56,9000000000))+('Recurring Items'!$E$6:$E$56="Weekly")*(WEEKDAY(AB206)=IFERROR(WEEKDAY('Recurring Items'!$G$6:$G$56),0))*(AB206>=IFERROR('Recurring Items'!$G$6:$G$56,9000000000))+('Recurring Items'!$E$6:$E$56="One-time")*(AB206='Recurring Items'!$G$6:$G$56))) -> 672.8 | AF206: =(IF(AC206=1,'Debt Tracker'!$P$5>0.01,INDEX('Debt Tracker'!$T$5:$AE$29,1,AC206-1)>0.01))*('Recurring Items'!$H$8<>"Skip")*(DAY(AB206)='Recurring Items'!$F$8)*IFERROR(N('Recurring Items'!$D$8),0)+(IF(AC206=1,'Debt Tracker'!$P$6>0.01,INDEX('Debt Tracker'!$T$5:$AE$29,2,AC206-1)>0.01))*('Recurring Items'!$H$9<>"Skip")*(DAY(AB206)='Recurring Items'!$F$9)*IFERROR(N('Recurring Items'!$D$9),0)+(IF(AC206=1,'Debt Tracker'!$P$7>0.01,INDEX('Debt Tracker'!$T$5:$AE$29,3,AC206-1)>0.01))*('Recurring Items'!$H$10<>"Skip")*(DAY(AB206)='Recurring Items'!$F$10)*IFERROR(N('Recurring Items'!$D$10),0)+(IF(AC206=1,'Debt Tracker'!$P$8>0.01,INDEX('Debt Tracker'!$T$5:$AE$29,4,AC206-1)>0.01))*('Recurring Items'!$H$11<>"Skip")*(DAY(AB206)='Recurring Items'!$F$11)*IFERROR(N('Recurring Items'!$D$11),0)+(IF(AC206=1,'Debt Tracker'!$P$9>0.01,INDEX('Debt Tracker'!$T$5:$AE$29,5,AC206-1)>0.01))*('Recurring Items'!$H$12<>"Skip")*(DAY(AB206)='Recurring Items'!$F$12)*IFERROR(N('Recurring Items'!$D$12),0)+(IF(AC206=1,'Debt Tracker'!$P$10>0.01,INDEX('Debt Tracker'!$T$5:$AE$29,6,AC206-1)>0.01))*('Recurring Items'!$H$13<>"Skip")*(DAY(AB206)='Recurring Items'!$F$13)*IFERROR(N('Recurring Items'!$D$13),0)+(IF(AC206=1,'Debt Tracker'!$P$11>0.01,INDEX('Debt Tracker'!$T$5:$AE$29,7,AC206-1)>0.01))*('Recurring Items'!$H$14<>"Skip")*(DAY(AB206)='Recurring Items'!$F$14)*IFERROR(N('Recurring Items'!$D$14),0)+(IF(AC206=1,'Debt Tracker'!$P$12>0.01,INDEX('Debt Tracker'!$T$5:$AE$29,8,AC206-1)>0.01))*('Recurring Items'!$H$15<>"Skip")*(DAY(AB206)='Recurring Items'!$F$15)*IFERROR(N('Recurring Items'!$D$15),0)+(IF(AC206=1,'Debt Tracker'!$P$13>0.01,INDEX('Debt Tracker'!$T$5:$AE$29,9,AC206-1)>0.01))*('Recurring Items'!$H$16<>"Skip")*(DAY(AB206)='Recurring Items'!$F$16)*IFERROR(N('Recurring Items'!$D$16),0)+(IF(AC206=1,'Debt Tracker'!$P$14>0.01,INDEX('Debt Tracker'!$T$5:$AE$29,10,AC206-1)>0.01))*('Recurring Items'!$H$17<>"Skip")*(DAY(AB206)='Recurring Items'!$F$17)*IFERROR(N('Recurring Items'!$D$17),0)+(IF(AC206=1,'Debt Tracker'!$P$15>0.01,INDEX('Debt Tracker'!$T$5:$AE$29,11,AC206-1)>0.01))*('Recurring Items'!$H$18<>"Skip")*(DAY(AB206)='Recurring Items'!$F$18)*IFERROR(N('Recurring Items'!$D$18),0)+(IF(AC206=1,'Debt Tracker'!$P$16>0.01,INDEX('Debt Tracker'!$T$5:$AE$29,12,AC206-1)>0.01))*('Recurring Items'!$H$19<>"Skip")*(DAY(AB206)='Recurring Items'!$F$19)*IFERROR(N('Recurring Items'!$D$19),0)+(IF(AC206=1,'Debt Tracker'!$P$17>0.01,INDEX('Debt Tracker'!$T$5:$AE$29,13,AC206-1)>0.01))*('Recurring Items'!$H$20<>"Skip")*(DAY(AB206)='Recurring Items'!$F$20)*IFERROR(N('Recurring Items'!$D$20),0)+(IF(AC206=1,'Debt Tracker'!$P$18>0.01,INDEX('Debt Tracker'!$T$5:$AE$29,14,AC206-1)>0.01))*('Recurring Items'!$H$21<>"Skip")*(DAY(AB206)='Recurring Items'!$F$21)*IFERROR(N('Recurring Items'!$D$21),0)+(IF(AC206=1,'Debt Tracker'!$P$19>0.01,INDEX('Debt Tracker'!$T$5:$AE$29,15,AC206-1)>0.01))*('Recurring Items'!$H$22<>"Skip")*(DAY(AB206)='Recurring Items'!$F$22)*IFERROR(N('Recurring Items'!$D$22),0)+(IF(AC206=1,'Debt Tracker'!$P$20>0.01,INDEX('Debt Tracker'!$T$5:$AE$29,16,AC206-1)>0.01))*('Recurring Items'!$H$23<>"Skip")*(DAY(AB206)='Recurring Items'!$F$23)*IFERROR(N('Recurring Items'!$D$23),0)+(IF(AC206=1,'Debt Tracker'!$P$21>0.01,INDEX('Debt Tracker'!$T$5:$AE$29,17,AC206-1)>0.01))*('Recurring Items'!$H$24<>"Skip")*(DAY(AB206)='Recurring Items'!$F$24)*IFERROR(N('Recurring Items'!$D$24),0)+(IF(AC206=1,'Debt Tracker'!$P$22>0.01,INDEX('Debt Tracker'!$T$5:$AE$29,18,AC206-1)>0.01))*('Recurring Items'!$H$25<>"Skip")*(DAY(AB206)='Recurring Items'!$F$25)*IFERROR(N('Recurring Items'!$D$25),0)+(IF(AC206=1,'Debt Tracker'!$P$23>0.01,INDEX('Debt Tracker'!$T$5:$AE$29,19,AC206-1)>0.01))*('Recurring Items'!$H$26<>"Skip")*(DAY(AB206)='Recurring Items'!$F$26)*IFERROR(N('Recurring Items'!$D$26),0)+(IF(AC206=1,'Debt Tracker'!$P$24>0.01,INDEX('Debt Tracker'!$T$5:$AE$29,20,AC206-1)>0.01))*('Recurring Items'!$H$27<>"Skip")*(DAY(AB206)='Recurring Items'!$F$27)*IFERROR(N('Recurring Items'!$D$27),0)+(IF(AC206=1,'Debt Tracker'!$P$25>0.01,INDEX('Debt Tracker'!$T$5:$AE$29,21,AC206-1)>0.01))*('Recurring Items'!$H$28<>"Skip")*(DAY(AB206)='Recurring Items'!$F$28)*IFERROR(N('Recurring Items'!$D$28),0)+(IF(AC206=1,'Debt Tracker'!$P$26>0.01,INDEX('Debt Tracker'!$T$5:$AE$29,22,AC206-1)>0.01))*('Recurring Items'!$H$29<>"Skip")*(DAY(AB206)='Recurring Items'!$F$29)*IFERROR(N('Recurring Items'!$D$29),0)+(IF(AC206=1,'Debt Tracker'!$P$27>0.01,INDEX('Debt Tracker'!$T$5:$AE$29,23,AC206-1)>0.01))*('Recurring Items'!$H$30<>"Skip")*(DAY(AB206)='Recurring Items'!$F$30)*IFERROR(N('Recurring Items'!$D$30),0)+(IF(AC206=1,'Debt Tracker'!$P$28>0.01,INDEX('Debt Tracker'!$T$5:$AE$29,24,AC206-1)>0.01))*('Recurring Items'!$H$31<>"Skip")*(DAY(AB206)='Recurring Items'!$F$31)*IFERROR(N('Recurring Items'!$D$31),0)+(IF(AC206=1,'Debt Tracker'!$P$29>0.01,INDEX('Debt Tracker'!$T$5:$AE$29,25,AC206-1)>0.01))*('Recurring Items'!$H$32<>"Skip")*(DAY(AB206)='Recurring Items'!$F$32)*IFERROR(N('Recurring Items'!$D$32),0) -> 8.25 | AG206: =AD206-AE206-AF206 -> 1593.37 | AH206: =AH205+AG206 -> 4463.47
AA207: 7 | AB207: =$D$3+7 -> 46150 | AC207: =MIN(12,1+DATEDIF($D$3,AB207,"M")) -> 1 | AD207: =SUMPRODUCT(('Recurring Items'!$C$6:$C$56="Income")*('Recurring Items'!$H$6:$H$56<>"Skip")*IFERROR(N('Recurring Items'!$D$6:$D$56),0)*(('Recurring Items'!$E$6:$E$56="Monthly")*(DAY(AB207)='Recurring Items'!$F$6:$F$56)+('Recurring Items'!$E$6:$E$56="Bi-weekly")*(WEEKDAY(AB207)=IFERROR(WEEKDAY('Recurring Items'!$G$6:$G$56),0))*(MOD(AB207-IFERROR('Recurring Items'!$G$6:$G$56,0),14)=0)*(AB207>=IFERROR('Recurring Items'!$G$6:$G$56,9000000000))+('Recurring Items'!$E$6:$E$56="Weekly")*(WEEKDAY(AB207)=IFERROR(WEEKDAY('Recurring Items'!$G$6:$G$56),0))*(AB207>=IFERROR('Recurring Items'!$G$6:$G$56,9000000000))+('Recurring Items'!$E$6:$E$56="One-time")*(AB207='Recurring Items'!$G$6:$G$56))) -> 0 | AE207: =SUMPRODUCT(('Recurring Items'!$C$6:$C$56="Expense")*('Recurring Items'!$H$6:$H$56<>"Skip")*IFERROR(N('Recurring Items'!$D$6:$D$56),0)*(('Recurring Items'!$E$6:$E$56="Monthly")*(DAY(AB207)='Recurring Items'!$F$6:$F$56)+('Recurring Items'!$E$6:$E$56="Bi-weekly")*(WEEKDAY(AB207)=IFERROR(WEEKDAY('Recurring Items'!$G$6:$G$56),0))*(MOD(AB207-IFERROR('Recurring Items'!$G$6:$G$56,0),14)=0)*(AB207>=IFERROR('Recurring Items'!$G$6:$G$56,9000000000))+('Recurring Items'!$E$6:$E$56="Weekly")*(WEEKDAY(AB207)=IFERROR(WEEKDAY('Recurring Items'!$G$6:$G$56),0))*(AB207>=IFERROR('Recurring Items'!$G$6:$G$56,9000000000))+('Recurring Items'!$E$6:$E$56="One-time")*(AB207='Recurring Items'!$G$6:$G$56))) -> 513.85 | AF207: =(IF(AC207=1,'Debt Tracker'!$P$5>0.01,INDEX('Debt Tracker'!$T$5:$AE$29,1,AC207-1)>0.01))*('Recurring Items'!$H$8<>"Skip")*(DAY(AB207)='Recurring Items'!$F$8)*IFERROR(N('Recurring Items'!$D$8),0)+(IF(AC207=1,'Debt Tracker'!$P$6>0.01,INDEX('Debt Tracker'!$T$5:$AE$29,2,AC207-1)>0.01))*('Recurring Items'!$H$9<>"Skip")*(DAY(AB207)='Recurring Items'!$F$9)*IFERROR(N('Recurring Items'!$D$9),0)+(IF(AC207=1,'Debt Tracker'!$P$7>0.01,INDEX('Debt Tracker'!$T$5:$AE$29,3,AC207-1)>0.01))*('Recurring Items'!$H$10<>"Skip")*(DAY(AB207)='Recurring Items'!$F$10)*IFERROR(N('Recurring Items'!$D$10),0)+(IF(AC207=1,'Debt Tracker'!$P$8>0.01,INDEX('Debt Tracker'!$T$5:$AE$29,4,AC207-1)>0.01))*('Recurring Items'!$H$11<>"Skip")*(DAY(AB207)='Recurring Items'!$F$11)*IFERROR(N('Recurring Items'!$D$11),0)+(IF(AC207=1,'Debt Tracker'!$P$9>0.01,INDEX('Debt Tracker'!$T$5:$AE$29,5,AC207-1)>0.01))*('Recurring Items'!$H$12<>"Skip")*(DAY(AB207)='Recurring Items'!$F$12)*IFERROR(N('Recurring Items'!$D$12),0)+(IF(AC207=1,'Debt Tracker'!$P$10>0.01,INDEX('Debt Tracker'!$T$5:$AE$29,6,AC207-1)>0.01))*('Recurring Items'!$H$13<>"Skip")*(DAY(AB207)='Recurring Items'!$F$13)*IFERROR(N('Recurring Items'!$D$13),0)+(IF(AC207=1,'Debt Tracker'!$P$11>0.01,INDEX('Debt Tracker'!$T$5:$AE$29,7,AC207-1)>0.01))*('Recurring Items'!$H$14<>"Skip")*(DAY(AB207)='Recurring Items'!$F$14)*IFERROR(N('Recurring Items'!$D$14),0)+(IF(AC207=1,'Debt Tracker'!$P$12>0.01,INDEX('Debt Tracker'!$T$5:$AE$29,8,AC207-1)>0.01))*('Recurring Items'!$H$15<>"Skip")*(DAY(AB207)='Recurring Items'!$F$15)*IFERROR(N('Recurring Items'!$D$15),0)+(IF(AC207=1,'Debt Tracker'!$P$13>0.01,INDEX('Debt Tracker'!$T$5:$AE$29,9,AC207-1)>0.01))*('Recurring Items'!$H$16<>"Skip")*(DAY(AB207)='Recurring Items'!$F$16)*IFERROR(N('Recurring Items'!$D$16),0)+(IF(AC207=1,'Debt Tracker'!$P$14>0.01,INDEX('Debt Tracker'!$T$5:$AE$29,10,AC207-1)>0.01))*('Recurring Items'!$H$17<>"Skip")*(DAY(AB207)='Recurring Items'!$F$17)*IFERROR(N('Recurring Items'!$D$17),0)+(IF(AC207=1,'Debt Tracker'!$P$15>0.01,INDEX('Debt Tracker'!$T$5:$AE$29,11,AC207-1)>0.01))*('Recurring Items'!$H$18<>"Skip")*(DAY(AB207)='Recurring Items'!$F$18)*IFERROR(N('Recurring Items'!$D$18),0)+(IF(AC207=1,'Debt Tracker'!$P$16>0.01,INDEX('Debt Tracker'!$T$5:$AE$29,12,AC207-1)>0.01))*('Recurring Items'!$H$19<>"Skip")*(DAY(AB207)='Recurring Items'!$F$19)*IFERROR(N('Recurring Items'!$D$19),0)+(IF(AC207=1,'Debt Tracker'!$P$17>0.01,INDEX('Debt Tracker'!$T$5:$AE$29,13,AC207-1)>0.01))*('Recurring Items'!$H$20<>"Skip")*(DAY(AB207)='Recurring Items'!$F$20)*IFERROR(N('Recurring Items'!$D$20),0)+(IF(AC207=1,'Debt Tracker'!$P$18>0.01,INDEX('Debt Tracker'!$T$5:$AE$29,14,AC207-1)>0.01))*('Recurring Items'!$H$21<>"Skip")*(DAY(AB207)='Recurring Items'!$F$21)*IFERROR(N('Recurring Items'!$D$21),0)+(IF(AC207=1,'Debt Tracker'!$P$19>0.01,INDEX('Debt Tracker'!$T$5:$AE$29,15,AC207-1)>0.01))*('Recurring Items'!$H$22<>"Skip")*(DAY(AB207)='Recurring Items'!$F$22)*IFERROR(N('Recurring Items'!$D$22),0)+(IF(AC207=1,'Debt Tracker'!$P$20>0.01,INDEX('Debt Tracker'!$T$5:$AE$29,16,AC207-1)>0.01))*('Recurring Items'!$H$23<>"Skip")*(DAY(AB207)='Recurring Items'!$F$23)*IFERROR(N('Recurring Items'!$D$23),0)+(IF(AC207=1,'Debt Tracker'!$P$21>0.01,INDEX('Debt Tracker'!$T$5:$AE$29,17,AC207-1)>0.01))*('Recurring Items'!$H$24<>"Skip")*(DAY(AB207)='Recurring Items'!$F$24)*IFERROR(N('Recurring Items'!$D$24),0)+(IF(AC207=1,'Debt Tracker'!$P$22>0.01,INDEX('Debt Tracker'!$T$5:$AE$29,18,AC207-1)>0.01))*('Recurring Items'!$H$25<>"Skip")*(DAY(AB207)='Recurring Items'!$F$25)*IFERROR(N('Recurring Items'!$D$25),0)+(IF(AC207=1,'Debt Tracker'!$P$23>0.01,INDEX('Debt Tracker'!$T$5:$AE$29,19,AC207-1)>0.01))*('Recurring Items'!$H$26<>"Skip")*(DAY(AB207)='Recurring Items'!$F$26)*IFERROR(N('Recurring Items'!$D$26),0)+(IF(AC207=1,'Debt Tracker'!$P$24>0.01,INDEX('Debt Tracker'!$T$5:$AE$29,20,AC207-1)>0.01))*('Recurring Items'!$H$27<>"Skip")*(DAY(AB207)='Recurring Items'!$F$27)*IFERROR(N('Recurring Items'!$D$27),0)+(IF(AC207=1,'Debt Tracker'!$P$25>0.01,INDEX('Debt Tracker'!$T$5:$AE$29,21,AC207-1)>0.01))*('Recurring Items'!$H$28<>"Skip")*(DAY(AB207)='Recurring Items'!$F$28)*IFERROR(N('Recurring Items'!$D$28),0)+(IF(AC207=1,'Debt Tracker'!$P$26>0.01,INDEX('Debt Tracker'!$T$5:$AE$29,22,AC207-1)>0.01))*('Recurring Items'!$H$29<>"Skip")*(DAY(AB207)='Recurring Items'!$F$29)*IFERROR(N('Recurring Items'!$D$29),0)+(IF(AC207=1,'Debt Tracker'!$P$27>0.01,INDEX('Debt Tracker'!$T$5:$AE$29,23,AC207-1)>0.01))*('Recurring Items'!$H$30<>"Skip")*(DAY(AB207)='Recurring Items'!$F$30)*IFERROR(N('Recurring Items'!$D$30),0)+(IF(AC207=1,'Debt Tracker'!$P$28>0.01,INDEX('Debt Tracker'!$T$5:$AE$29,24,AC207-1)>0.01))*('Recurring Items'!$H$31<>"Skip")*(DAY(AB207)='Recurring Items'!$F$31)*IFERROR(N('Recurring Items'!$D$31),0)+(IF(AC207=1,'Debt Tracker'!$P$29>0.01,INDEX('Debt Tracker'!$T$5:$AE$29,25,AC207-1)>0.01))*('Recurring Items'!$H$32<>"Skip")*(DAY(AB207)='Recurring Items'!$F$32)*IFERROR(N('Recurring Items'!$D$32),0) -> 0 | AG207: =AD207-AE207-AF207 -> -513.85 | AH207: =AH206+AG207 -> 3949.62
AA208: 8 | AB208: =$D$3+8 -> 46151 | AC208: =MIN(12,1+DATEDIF($D$3,AB208,"M")) -> 1 | AD208: =SUMPRODUCT(('Recurring Items'!$C$6:$C$56="Income")*('Recurring Items'!$H$6:$H$56<>"Skip")*IFERROR(N('Recurring Items'!$D$6:$D$56),0)*(('Recurring Items'!$E$6:$E$56="Monthly")*(DAY(AB208)='Recurring Items'!$F$6:$F$56)+('Recurring Items'!$E$6:$E$56="Bi-weekly")*(WEEKDAY(AB208)=IFERROR(WEEKDAY('Recurring Items'!$G$6:$G$56),0))*(MOD(AB208-IFERROR('Recurring Items'!$G$6:$G$56,0),14)=0)*(AB208>=IFERROR('Recurring Items'!$G$6:$G$56,9000000000))+('Recurring Items'!$E$6:$E$56="Weekly")*(WEEKDAY(AB208)=IFERROR(WEEKDAY('Recurring Items'!$G$6:$G$56),0))*(AB208>=IFERROR('Recurring Items'!$G$6:$G$56,9000000000))+('Recurring Items'!$E$6:$E$56="One-time")*(AB208='Recurring Items'!$G$6:$G$56))) -> 0 | AE208: =SUMPRODUCT(('Recurring Items'!$C$6:$C$56="Expense")*('Recurring Items'!$H$6:$H$56<>"Skip")*IFERROR(N('Recurring Items'!$D$6:$D$56),0)*(('Recurring Items'!$E$6:$E$56="Monthly")*(DAY(AB208)='Recurring Items'!$F$6:$F$56)+('Recurring Items'!$E$6:$E$56="Bi-weekly")*(WEEKDAY(AB208)=IFERROR(WEEKDAY('Recurring Items'!$G$6:$G$56),0))*(MOD(AB208-IFERROR('Recurring Items'!$G$6:$G$56,0),14)=0)*(AB208>=IFERROR('Recurring Items'!$G$6:$G$56,9000000000))+('Recurring Items'!$E$6:$E$56="Weekly")*(WEEKDAY(AB208)=IFERROR(WEEKDAY('Recurring Items'!$G$6:$G$56),0))*(AB208>=IFERROR('Recurring Items'!$G$6:$G$56,9000000000))+('Recurring Items'!$E$6:$E$56="One-time")*(AB208='Recurring Items'!$G$6:$G$56))) -> 0 | AF208: =(IF(AC208=1,'Debt Tracker'!$P$5>0.01,INDEX('Debt Tracker'!$T$5:$AE$29,1,AC208-1)>0.01))*('Recurring Items'!$H$8<>"Skip")*(DAY(AB208)='Recurring Items'!$F$8)*IFERROR(N('Recurring Items'!$D$8),0)+(IF(AC208=1,'Debt Tracker'!$P$6>0.01,INDEX('Debt Tracker'!$T$5:$AE$29,2,AC208-1)>0.01))*('Recurring Items'!$H$9<>"Skip")*(DAY(AB208)='Recurring Items'!$F$9)*IFERROR(N('Recurring Items'!$D$9),0)+(IF(AC208=1,'Debt Tracker'!$P$7>0.01,INDEX('Debt Tracker'!$T$5:$AE$29,3,AC208-1)>0.01))*('Recurring Items'!$H$10<>"Skip")*(DAY(AB208)='Recurring Items'!$F$10)*IFERROR(N('Recurring Items'!$D$10),0)+(IF(AC208=1,'Debt Tracker'!$P$8>0.01,INDEX('Debt Tracker'!$T$5:$AE$29,4,AC208-1)>0.01))*('Recurring Items'!$H$11<>"Skip")*(DAY(AB208)='Recurring Items'!$F$11)*IFERROR(N('Recurring Items'!$D$11),0)+(IF(AC208=1,'Debt Tracker'!$P$9>0.01,INDEX('Debt Tracker'!$T$5:$AE$29,5,AC208-1)>0.01))*('Recurring Items'!$H$12<>"Skip")*(DAY(AB208)='Recurring Items'!$F$12)*IFERROR(N('Recurring Items'!$D$12),0)+(IF(AC208=1,'Debt Tracker'!$P$10>0.01,INDEX('Debt Tracker'!$T$5:$AE$29,6,AC208-1)>0.01))*('Recurring Items'!$H$13<>"Skip")*(DAY(AB208)='Recurring Items'!$F$13)*IFERROR(N('Recurring Items'!$D$13),0)+(IF(AC208=1,'Debt Tracker'!$P$11>0.01,INDEX('Debt Tracker'!$T$5:$AE$29,7,AC208-1)>0.01))*('Recurring Items'!$H$14<>"Skip")*(DAY(AB208)='Recurring Items'!$F$14)*IFERROR(N('Recurring Items'!$D$14),0)+(IF(AC208=1,'Debt Tracker'!$P$12>0.01,INDEX('Debt Tracker'!$T$5:$AE$29,8,AC208-1)>0.01))*('Recurring Items'!$H$15<>"Skip")*(DAY(AB208)='Recurring Items'!$F$15)*IFERROR(N('Recurring Items'!$D$15),0)+(IF(AC208=1,'Debt Tracker'!$P$13>0.01,INDEX('Debt Tracker'!$T$5:$AE$29,9,AC208-1)>0.01))*('Recurring Items'!$H$16<>"Skip")*(DAY(AB208)='Recurring Items'!$F$16)*IFERROR(N('Recurring Items'!$D$16),0)+(IF(AC208=1,'Debt Tracker'!$P$14>0.01,INDEX('Debt Tracker'!$T$5:$AE$29,10,AC208-1)>0.01))*('Recurring Items'!$H$17<>"Skip")*(DAY(AB208)='Recurring Items'!$F$17)*IFERROR(N('Recurring Items'!$D$17),0)+(IF(AC208=1,'Debt Tracker'!$P$15>0.01,INDEX('Debt Tracker'!$T$5:$AE$29,11,AC208-1)>0.01))*('Recurring Items'!$H$18<>"Skip")*(DAY(AB208)='Recurring Items'!$F$18)*IFERROR(N('Recurring Items'!$D$18),0)+(IF(AC208=1,'Debt Tracker'!$P$16>0.01,INDEX('Debt Tracker'!$T$5:$AE$29,12,AC208-1)>0.01))*('Recurring Items'!$H$19<>"Skip")*(DAY(AB208)='Recurring Items'!$F$19)*IFERROR(N('Recurring Items'!$D$19),0)+(IF(AC208=1,'Debt Tracker'!$P$17>0.01,INDEX('Debt Tracker'!$T$5:$AE$29,13,AC208-1)>0.01))*('Recurring Items'!$H$20<>"Skip")*(DAY(AB208)='Recurring Items'!$F$20)*IFERROR(N('Recurring Items'!$D$20),0)+(IF(AC208=1,'Debt Tracker'!$P$18>0.01,INDEX('Debt Tracker'!$T$5:$AE$29,14,AC208-1)>0.01))*('Recurring Items'!$H$21<>"Skip")*(DAY(AB208)='Recurring Items'!$F$21)*IFERROR(N('Recurring Items'!$D$21),0)+(IF(AC208=1,'Debt Tracker'!$P$19>0.01,INDEX('Debt Tracker'!$T$5:$AE$29,15,AC208-1)>0.01))*('Recurring Items'!$H$22<>"Skip")*(DAY(AB208)='Recurring Items'!$F$22)*IFERROR(N('Recurring Items'!$D$22),0)+(IF(AC208=1,'Debt Tracker'!$P$20>0.01,INDEX('Debt Tracker'!$T$5:$AE$29,16,AC208-1)>0.01))*('Recurring Items'!$H$23<>"Skip")*(DAY(AB208)='Recurring Items'!$F$23)*IFERROR(N('Recurring Items'!$D$23),0)+(IF(AC208=1,'Debt Tracker'!$P$21>0.01,INDEX('Debt Tracker'!$T$5:$AE$29,17,AC208-1)>0.01))*('Recurring Items'!$H$24<>"Skip")*(DAY(AB208)='Recurring Items'!$F$24)*IFERROR(N('Recurring Items'!$D$24),0)+(IF(AC208=1,'Debt Tracker'!$P$22>0.01,INDEX('Debt Tracker'!$T$5:$AE$29,18,AC208-1)>0.01))*('Recurring Items'!$H$25<>"Skip")*(DAY(AB208)='Recurring Items'!$F$25)*IFERROR(N('Recurring Items'!$D$25),0)+(IF(AC208=1,'Debt Tracker'!$P$23>0.01,INDEX('Debt Tracker'!$T$5:$AE$29,19,AC208-1)>0.01))*('Recurring Items'!$H$26<>"Skip")*(DAY(AB208)='Recurring Items'!$F$26)*IFERROR(N('Recurring Items'!$D$26),0)+(IF(AC208=1,'Debt Tracker'!$P$24>0.01,INDEX('Debt Tracker'!$T$5:$AE$29,20,AC208-1)>0.01))*('Recurring Items'!$H$27<>"Skip")*(DAY(AB208)='Recurring Items'!$F$27)*IFERROR(N('Recurring Items'!$D$27),0)+(IF(AC208=1,'Debt Tracker'!$P$25>0.01,INDEX('Debt Tracker'!$T$5:$AE$29,21,AC208-1)>0.01))*('Recurring Items'!$H$28<>"Skip")*(DAY(AB208)='Recurring Items'!$F$28)*IFERROR(N('Recurring Items'!$D$28),0)+(IF(AC208=1,'Debt Tracker'!$P$26>0.01,INDEX('Debt Tracker'!$T$5:$AE$29,22,AC208-1)>0.01))*('Recurring Items'!$H$29<>"Skip")*(DAY(AB208)='Recurring Items'!$F$29)*IFERROR(N('Recurring Items'!$D$29),0)+(IF(AC208=1,'Debt Tracker'!$P$27>0.01,INDEX('Debt Tracker'!$T$5:$AE$29,23,AC208-1)>0.01))*('Recurring Items'!$H$30<>"Skip")*(DAY(AB208)='Recurring Items'!$F$30)*IFERROR(N('Recurring Items'!$D$30),0)+(IF(AC208=1,'Debt Tracker'!$P$28>0.01,INDEX('Debt Tracker'!$T$5:$AE$29,24,AC208-1)>0.01))*('Recurring Items'!$H$31<>"Skip")*(DAY(AB208)='Recurring Items'!$F$31)*IFERROR(N('Recurring Items'!$D$31),0)+(IF(AC208=1,'Debt Tracker'!$P$29>0.01,INDEX('Debt Tracker'!$T$5:$AE$29,25,AC208-1)>0.01))*('Recurring Items'!$H$32<>"Skip")*(DAY(AB208)='Recurring Items'!$F$32)*IFERROR(N('Recurring Items'!$D$32),0) -> 162 | AG208: =AD208-AE208-AF208 -> -162 | AH208: =AH207+AG208 -> 3787.62
AA209: 9 | AB209: =$D$3+9 -> 46152 | AC209: =MIN(12,1+DATEDIF($D$3,AB209,"M")) -> 1 | AD209: =SUMPRODUCT(('Recurring Items'!$C$6:$C$56="Income")*('Recurring Items'!$H$6:$H$56<>"Skip")*IFERROR(N('Recurring Items'!$D$6:$D$56),0)*(('Recurring Items'!$E$6:$E$56="Monthly")*(DAY(AB209)='Recurring Items'!$F$6:$F$56)+('Recurring Items'!$E$6:$E$56="Bi-weekly")*(WEEKDAY(AB209)=IFERROR(WEEKDAY('Recurring Items'!$G$6:$G$56),0))*(MOD(AB209-IFERROR('Recurring Items'!$G$6:$G$56,0),14)=0)*(AB209>=IFERROR('Recurring Items'!$G$6:$G$56,9000000000))+('Recurring Items'!$E$6:$E$56="Weekly")*(WEEKDAY(AB209)=IFERROR(WEEKDAY('Recurring Items'!$G$6:$G$56),0))*(AB209>=IFERROR('Recurring Items'!$G$6:$G$56,9000000000))+('Recurring Items'!$E$6:$E$56="One-time")*(AB209='Recurring Items'!$G$6:$G$56))) -> 0 | AE209: =SUMPRODUCT(('Recurring Items'!$C$6:$C$56="Expense")*('Recurring Items'!$H$6:$H$56<>"Skip")*IFERROR(N('Recurring Items'!$D$6:$D$56),0)*(('Recurring Items'!$E$6:$E$56="Monthly")*(DAY(AB209)='Recurring Items'!$F$6:$F$56)+('Recurring Items'!$E$6:$E$56="Bi-weekly")*(WEEKDAY(AB209)=IFERROR(WEEKDAY('Recurring Items'!$G$6:$G$56),0))*(MOD(AB209-IFERROR('Recurring Items'!$G$6:$G$56,0),14)=0)*(AB209>=IFERROR('Recurring Items'!$G$6:$G$56,9000000000))+('Recurring Items'!$E$6:$E$56="Weekly")*(WEEKDAY(AB209)=IFERROR(WEEKDAY('Recurring Items'!$G$6:$G$56),0))*(AB209>=IFERROR('Recurring Items'!$G$6:$G$56,9000000000))+('Recurring Items'!$E$6:$E$56="One-time")*(AB209='Recurring Items'!$G$6:$G$56))) -> 340.22 | AF209: =(IF(AC209=1,'Debt Tracker'!$P$5>0.01,INDEX('Debt Tracker'!$T$5:$AE$29,1,AC209-1)>0.01))*('Recurring Items'!$H$8<>"Skip")*(DAY(AB209)='Recurring Items'!$F$8)*IFERROR(N('Recurring Items'!$D$8),0)+(IF(AC209=1,'Debt Tracker'!$P$6>0.01,INDEX('Debt Tracker'!$T$5:$AE$29,2,AC209-1)>0.01))*('Recurring Items'!$H$9<>"Skip")*(DAY(AB209)='Recurring Items'!$F$9)*IFERROR(N('Recurring Items'!$D$9),0)+(IF(AC209=1,'Debt Tracker'!$P$7>0.01,INDEX('Debt Tracker'!$T$5:$AE$29,3,AC209-1)>0.01))*('Recurring Items'!$H$10<>"Skip")*(DAY(AB209)='Recurring Items'!$F$10)*IFERROR(N('Recurring Items'!$D$10),0)+(IF(AC209=1,'Debt Tracker'!$P$8>0.01,INDEX('Debt Tracker'!$T$5:$AE$29,4,AC209-1)>0.01))*('Recurring Items'!$H$11<>"Skip")*(DAY(AB209)='Recurring Items'!$F$11)*IFERROR(N('Recurring Items'!$D$11),0)+(IF(AC209=1,'Debt Tracker'!$P$9>0.01,INDEX('Debt Tracker'!$T$5:$AE$29,5,AC209-1)>0.01))*('Recurring Items'!$H$12<>"Skip")*(DAY(AB209)='Recurring Items'!$F$12)*IFERROR(N('Recurring Items'!$D$12),0)+(IF(AC209=1,'Debt Tracker'!$P$10>0.01,INDEX('Debt Tracker'!$T$5:$AE$29,6,AC209-1)>0.01))*('Recurring Items'!$H$13<>"Skip")*(DAY(AB209)='Recurring Items'!$F$13)*IFERROR(N('Recurring Items'!$D$13),0)+(IF(AC209=1,'Debt Tracker'!$P$11>0.01,INDEX('Debt Tracker'!$T$5:$AE$29,7,AC209-1)>0.01))*('Recurring Items'!$H$14<>"Skip")*(DAY(AB209)='Recurring Items'!$F$14)*IFERROR(N('Recurring Items'!$D$14),0)+(IF(AC209=1,'Debt Tracker'!$P$12>0.01,INDEX('Debt Tracker'!$T$5:$AE$29,8,AC209-1)>0.01))*('Recurring Items'!$H$15<>"Skip")*(DAY(AB209)='Recurring Items'!$F$15)*IFERROR(N('Recurring Items'!$D$15),0)+(IF(AC209=1,'Debt Tracker'!$P$13>0.01,INDEX('Debt Tracker'!$T$5:$AE$29,9,AC209-1)>0.01))*('Recurring Items'!$H$16<>"Skip")*(DAY(AB209)='Recurring Items'!$F$16)*IFERROR(N('Recurring Items'!$D$16),0)+(IF(AC209=1,'Debt Tracker'!$P$14>0.01,INDEX('Debt Tracker'!$T$5:$AE$29,10,AC209-1)>0.01))*('Recurring Items'!$H$17<>"Skip")*(DAY(AB209)='Recurring Items'!$F$17)*IFERROR(N('Recurring Items'!$D$17),0)+(IF(AC209=1,'Debt Tracker'!$P$15>0.01,INDEX('Debt Tracker'!$T$5:$AE$29,11,AC209-1)>0.01))*('Recurring Items'!$H$18<>"Skip")*(DAY(AB209)='Recurring Items'!$F$18)*IFERROR(N('Recurring Items'!$D$18),0)+(IF(AC209=1,'Debt Tracker'!$P$16>0.01,INDEX('Debt Tracker'!$T$5:$AE$29,12,AC209-1)>0.01))*('Recurring Items'!$H$19<>"Skip")*(DAY(AB209)='Recurring Items'!$F$19)*IFERROR(N('Recurring Items'!$D$19),0)+(IF(AC209=1,'Debt Tracker'!$P$17>0.01,INDEX('Debt Tracker'!$T$5:$AE$29,13,AC209-1)>0.01))*('Recurring Items'!$H$20<>"Skip")*(DAY(AB209)='Recurring Items'!$F$20)*IFERROR(N('Recurring Items'!$D$20),0)+(IF(AC209=1,'Debt Tracker'!$P$18>0.01,INDEX('Debt Tracker'!$T$5:$AE$29,14,AC209-1)>0.01))*('Recurring Items'!$H$21<>"Skip")*(DAY(AB209)='Recurring Items'!$F$21)*IFERROR(N('Recurring Items'!$D$21),0)+(IF(AC209=1,'Debt Tracker'!$P$19>0.01,INDEX('Debt Tracker'!$T$5:$AE$29,15,AC209-1)>0.01))*('Recurring Items'!$H$22<>"Skip")*(DAY(AB209)='Recurring Items'!$F$22)*IFERROR(N('Recurring Items'!$D$22),0)+(IF(AC209=1,'Debt Tracker'!$P$20>0.01,INDEX('Debt Tracker'!$T$5:$AE$29,16,AC209-1)>0.01))*('Recurring Items'!$H$23<>"Skip")*(DAY(AB209)='Recurring Items'!$F$23)*IFERROR(N('Recurring Items'!$D$23),0)+(IF(AC209=1,'Debt Tracker'!$P$21>0.01,INDEX('Debt Tracker'!$T$5:$AE$29,17,AC209-1)>0.01))*('Recurring Items'!$H$24<>"Skip")*(DAY(AB209)='Recurring Items'!$F$24)*IFERROR(N('Recurring Items'!$D$24),0)+(IF(AC209=1,'Debt Tracker'!$P$22>0.01,INDEX('Debt Tracker'!$T$5:$AE$29,18,AC209-1)>0.01))*('Recurring Items'!$H$25<>"Skip")*(DAY(AB209)='Recurring Items'!$F$25)*IFERROR(N('Recurring Items'!$D$25),0)+(IF(AC209=1,'Debt Tracker'!$P$23>0.01,INDEX('Debt Tracker'!$T$5:$AE$29,19,AC209-1)>0.01))*('Recurring Items'!$H$26<>"Skip")*(DAY(AB209)='Recurring Items'!$F$26)*IFERROR(N('Recurring Items'!$D$26),0)+(IF(AC209=1,'Debt Tracker'!$P$24>0.01,INDEX('Debt Tracker'!$T$5:$AE$29,20,AC209-1)>0.01))*('Recurring Items'!$H$27<>"Skip")*(DAY(AB209)='Recurring Items'!$F$27)*IFERROR(N('Recurring Items'!$D$27),0)+(IF(AC209=1,'Debt Tracker'!$P$25>0.01,INDEX('Debt Tracker'!$T$5:$AE$29,21,AC209-1)>0.01))*('Recurring Items'!$H$28<>"Skip")*(DAY(AB209)='Recurring Items'!$F$28)*IFERROR(N('Recurring Items'!$D$28),0)+(IF(AC209=1,'Debt Tracker'!$P$26>0.01,INDEX('Debt Tracker'!$T$5:$AE$29,22,AC209-1)>0.01))*('Recurring Items'!$H$29<>"Skip")*(DAY(AB209)='Recurring Items'!$F$29)*IFERROR(N('Recurring Items'!$D$29),0)+(IF(AC209=1,'Debt Tracker'!$P$27>0.01,INDEX('Debt Tracker'!$T$5:$AE$29,23,AC209-1)>0.01))*('Recurring Items'!$H$30<>"Skip")*(DAY(AB209)='Recurring Items'!$F$30)*IFERROR(N('Recurring Items'!$D$30),0)+(IF(AC209=1,'Debt Tracker'!$P$28>0.01,INDEX('Debt Tracker'!$T$5:$AE$29,24,AC209-1)>0.01))*('Recurring Items'!$H$31<>"Skip")*(DAY(AB209)='Recurring Items'!$F$31)*IFERROR(N('Recurring Items'!$D$31),0)+(IF(AC209=1,'Debt Tracker'!$P$29>0.01,INDEX('Debt Tracker'!$T$5:$AE$29,25,AC209-1)>0.01))*('Recurring Items'!$H$32<>"Skip")*(DAY(AB209)='Recurring Items'!$F$32)*IFERROR(N('Recurring Items'!$D$32),0) -> 72.54 | AG209: =AD209-AE209-AF209 -> -412.76 | AH209: =AH208+AG209 -> 3374.86
AA210: 10 | AB210: =$D$3+10 -> 46153 | AC210: =MIN(12,1+DATEDIF($D$3,AB210,"M")) -> 1 | AD210: =SUMPRODUCT(('Recurring Items'!$C$6:$C$56="Income")*('Recurring Items'!$H$6:$H$56<>"Skip")*IFERROR(N('Recurring Items'!$D$6:$D$56),0)*(('Recurring Items'!$E$6:$E$56="Monthly")*(DAY(AB210)='Recurring Items'!$F$6:$F$56)+('Recurring Items'!$E$6:$E$56="Bi-weekly")*(WEEKDAY(AB210)=IFERROR(WEEKDAY('Recurring Items'!$G$6:$G$56),0))*(MOD(AB210-IFERROR('Recurring Items'!$G$6:$G$56,0),14)=0)*(AB210>=IFERROR('Recurring Items'!$G$6:$G$56,9000000000))+('Recurring Items'!$E$6:$E$56="Weekly")*(WEEKDAY(AB210)=IFERROR(WEEKDAY('Recurring Items'!$G$6:$G$56),0))*(AB210>=IFERROR('Recurring Items'!$G$6:$G$56,9000000000))+('Recurring Items'!$E$6:$E$56="One-time")*(AB210='Recurring Items'!$G$6:$G$56))) -> 0 | AE210: =SUMPRODUCT(('Recurring Items'!$C$6:$C$56="Expense")*('Recurring Items'!$H$6:$H$56<>"Skip")*IFERROR(N('Recurring Items'!$D$6:$D$56),0)*(('Recurring Items'!$E$6:$E$56="Monthly")*(DAY(AB210)='Recurring Items'!$F$6:$F$56)+('Recurring Items'!$E$6:$E$56="Bi-weekly")*(WEEKDAY(AB210)=IFERROR(WEEKDAY('Recurring Items'!$G$6:$G$56),0))*(MOD(AB210-IFERROR('Recurring Items'!$G$6:$G$56,0),14)=0)*(AB210>=IFERROR('Recurring Items'!$G$6:$G$56,9000000000))+('Recurring Items'!$E$6:$E$56="Weekly")*(WEEKDAY(AB210)=IFERROR(WEEKDAY('Recurring Items'!$G$6:$G$56),0))*(AB210>=IFERROR('Recurring Items'!$G$6:$G$56,9000000000))+('Recurring Items'!$E$6:$E$56="One-time")*(AB210='Recurring Items'!$G$6:$G$56))) -> 0 | AF210: =(IF(AC210=1,'Debt Tracker'!$P$5>0.01,INDEX('Debt Tracker'!$T$5:$AE$29,1,AC210-1)>0.01))*('Recurring Items'!$H$8<>"Skip")*(DAY(AB210)='Recurring Items'!$F$8)*IFERROR(N('Recurring Items'!$D$8),0)+(IF(AC210=1,'Debt Tracker'!$P$6>0.01,INDEX('Debt Tracker'!$T$5:$AE$29,2,AC210-1)>0.01))*('Recurring Items'!$H$9<>"Skip")*(DAY(AB210)='Recurring Items'!$F$9)*IFERROR(N('Recurring Items'!$D$9),0)+(IF(AC210=1,'Debt Tracker'!$P$7>0.01,INDEX('Debt Tracker'!$T$5:$AE$29,3,AC210-1)>0.01))*('Recurring Items'!$H$10<>"Skip")*(DAY(AB210)='Recurring Items'!$F$10)*IFERROR(N('Recurring Items'!$D$10),0)+(IF(AC210=1,'Debt Tracker'!$P$8>0.01,INDEX('Debt Tracker'!$T$5:$AE$29,4,AC210-1)>0.01))*('Recurring Items'!$H$11<>"Skip")*(DAY(AB210)='Recurring Items'!$F$11)*IFERROR(N('Recurring Items'!$D$11),0)+(IF(AC210=1,'Debt Tracker'!$P$9>0.01,INDEX('Debt Tracker'!$T$5:$AE$29,5,AC210-1)>0.01))*('Recurring Items'!$H$12<>"Skip")*(DAY(AB210)='Recurring Items'!$F$12)*IFERROR(N('Recurring Items'!$D$12),0)+(IF(AC210=1,'Debt Tracker'!$P$10>0.01,INDEX('Debt Tracker'!$T$5:$AE$29,6,AC210-1)>0.01))*('Recurring Items'!$H$13<>"Skip")*(DAY(AB210)='Recurring Items'!$F$13)*IFERROR(N('Recurring Items'!$D$13),0)+(IF(AC210=1,'Debt Tracker'!$P$11>0.01,INDEX('Debt Tracker'!$T$5:$AE$29,7,AC210-1)>0.01))*('Recurring Items'!$H$14<>"Skip")*(DAY(AB210)='Recurring Items'!$F$14)*IFERROR(N('Recurring Items'!$D$14),0)+(IF(AC210=1,'Debt Tracker'!$P$12>0.01,INDEX('Debt Tracker'!$T$5:$AE$29,8,AC210-1)>0.01))*('Recurring Items'!$H$15<>"Skip")*(DAY(AB210)='Recurring Items'!$F$15)*IFERROR(N('Recurring Items'!$D$15),0)+(IF(AC210=1,'Debt Tracker'!$P$13>0.01,INDEX('Debt Tracker'!$T$5:$AE$29,9,AC210-1)>0.01))*('Recurring Items'!$H$16<>"Skip")*(DAY(AB210)='Recurring Items'!$F$16)*IFERROR(N('Recurring Items'!$D$16),0)+(IF(AC210=1,'Debt Tracker'!$P$14>0.01,INDEX('Debt Tracker'!$T$5:$AE$29,10,AC210-1)>0.01))*('Recurring Items'!$H$17<>"Skip")*(DAY(AB210)='Recurring Items'!$F$17)*IFERROR(N('Recurring Items'!$D$17),0)+(IF(AC210=1,'Debt Tracker'!$P$15>0.01,INDEX('Debt Tracker'!$T$5:$AE$29,11,AC210-1)>0.01))*('Recurring Items'!$H$18<>"Skip")*(DAY(AB210)='Recurring Items'!$F$18)*IFERROR(N('Recurring Items'!$D$18),0)+(IF(AC210=1,'Debt Tracker'!$P$16>0.01,INDEX('Debt Tracker'!$T$5:$AE$29,12,AC210-1)>0.01))*('Recurring Items'!$H$19<>"Skip")*(DAY(AB210)='Recurring Items'!$F$19)*IFERROR(N('Recurring Items'!$D$19),0)+(IF(AC210=1,'Debt Tracker'!$P$17>0.01,INDEX('Debt Tracker'!$T$5:$AE$29,13,AC210-1)>0.01))*('Recurring Items'!$H$20<>"Skip")*(DAY(AB210)='Recurring Items'!$F$20)*IFERROR(N('Recurring Items'!$D$20),0)+(IF(AC210=1,'Debt Tracker'!$P$18>0.01,INDEX('Debt Tracker'!$T$5:$AE$29,14,AC210-1)>0.01))*('Recurring Items'!$H$21<>"Skip")*(DAY(AB210)='Recurring Items'!$F$21)*IFERROR(N('Recurring Items'!$D$21),0)+(IF(AC210=1,'Debt Tracker'!$P$19>0.01,INDEX('Debt Tracker'!$T$5:$AE$29,15,AC210-1)>0.01))*('Recurring Items'!$H$22<>"Skip")*(DAY(AB210)='Recurring Items'!$F$22)*IFERROR(N('Recurring Items'!$D$22),0)+(IF(AC210=1,'Debt Tracker'!$P$20>0.01,INDEX('Debt Tracker'!$T$5:$AE$29,16,AC210-1)>0.01))*('Recurring Items'!$H$23<>"Skip")*(DAY(AB210)='Recurring Items'!$F$23)*IFERROR(N('Recurring Items'!$D$23),0)+(IF(AC210=1,'Debt Tracker'!$P$21>0.01,INDEX('Debt Tracker'!$T$5:$AE$29,17,AC210-1)>0.01))*('Recurring Items'!$H$24<>"Skip")*(DAY(AB210)='Recurring Items'!$F$24)*IFERROR(N('Recurring Items'!$D$24),0)+(IF(AC210=1,'Debt Tracker'!$P$22>0.01,INDEX('Debt Tracker'!$T$5:$AE$29,18,AC210-1)>0.01))*('Recurring Items'!$H$25<>"Skip")*(DAY(AB210)='Recurring Items'!$F$25)*IFERROR(N('Recurring Items'!$D$25),0)+(IF(AC210=1,'Debt Tracker'!$P$23>0.01,INDEX('Debt Tracker'!$T$5:$AE$29,19,AC210-1)>0.01))*('Recurring Items'!$H$26<>"Skip")*(DAY(AB210)='Recurring Items'!$F$26)*IFERROR(N('Recurring Items'!$D$26),0)+(IF(AC210=1,'Debt Tracker'!$P$24>0.01,INDEX('Debt Tracker'!$T$5:$AE$29,20,AC210-1)>0.01))*('Recurring Items'!$H$27<>"Skip")*(DAY(AB210)='Recurring Items'!$F$27)*IFERROR(N('Recurring Items'!$D$27),0)+(IF(AC210=1,'Debt Tracker'!$P$25>0.01,INDEX('Debt Tracker'!$T$5:$AE$29,21,AC210-1)>0.01))*('Recurring Items'!$H$28<>"Skip")*(DAY(AB210)='Recurring Items'!$F$28)*IFERROR(N('Recurring Items'!$D$28),0)+(IF(AC210=1,'Debt Tracker'!$P$26>0.01,INDEX('Debt Tracker'!$T$5:$AE$29,22,AC210-1)>0.01))*('Recurring Items'!$H$29<>"Skip")*(DAY(AB210)='Recurring Items'!$F$29)*IFERROR(N('Recurring Items'!$D$29),0)+(IF(AC210=1,'Debt Tracker'!$P$27>0.01,INDEX('Debt Tracker'!$T$5:$AE$29,23,AC210-1)>0.01))*('Recurring Items'!$H$30<>"Skip")*(DAY(AB210)='Recurring Items'!$F$30)*IFERROR(N('Recurring Items'!$D$30),0)+(IF(AC210=1,'Debt Tracker'!$P$28>0.01,INDEX('Debt Tracker'!$T$5:$AE$29,24,AC210-1)>0.01))*('Recurring Items'!$H$31<>"Skip")*(DAY(AB210)='Recurring Items'!$F$31)*IFERROR(N('Recurring Items'!$D$31),0)+(IF(AC210=1,'Debt Tracker'!$P$29>0.01,INDEX('Debt Tracker'!$T$5:$AE$29,25,AC210-1)>0.01))*('Recurring Items'!$H$32<>"Skip")*(DAY(AB210)='Recurring Items'!$F$32)*IFERROR(N('Recurring Items'!$D$32),0) -> 0 | AG210: =AD210-AE210-AF210 -> 0 | AH210: =AH209+AG210 -> 3374.86
AA211: 11 | AB211: =$D$3+11 -> 46154 | AC211: =MIN(12,1+DATEDIF($D$3,AB211,"M")) -> 1 | AD211: =SUMPRODUCT(('Recurring Items'!$C$6:$C$56="Income")*('Recurring Items'!$H$6:$H$56<>"Skip")*IFERROR(N('Recurring Items'!$D$6:$D$56),0)*(('Recurring Items'!$E$6:$E$56="Monthly")*(DAY(AB211)='Recurring Items'!$F$6:$F$56)+('Recurring Items'!$E$6:$E$56="Bi-weekly")*(WEEKDAY(AB211)=IFERROR(WEEKDAY('Recurring Items'!$G$6:$G$56),0))*(MOD(AB211-IFERROR('Recurring Items'!$G$6:$G$56,0),14)=0)*(AB211>=IFERROR('Recurring Items'!$G$6:$G$56,9000000000))+('Recurring Items'!$E$6:$E$56="Weekly")*(WEEKDAY(AB211)=IFERROR(WEEKDAY('Recurring Items'!$G$6:$G$56),0))*(AB211>=IFERROR('Recurring Items'!$G$6:$G$56,9000000000))+('Recurring Items'!$E$6:$E$56="One-time")*(AB211='Recurring Items'!$G$6:$G$56))) -> 0 | AE211: =SUMPRODUCT(('Recurring Items'!$C$6:$C$56="Expense")*('Recurring Items'!$H$6:$H$56<>"Skip")*IFERROR(N('Recurring Items'!$D$6:$D$56),0)*(('Recurring Items'!$E$6:$E$56="Monthly")*(DAY(AB211)='Recurring Items'!$F$6:$F$56)+('Recurring Items'!$E$6:$E$56="Bi-weekly")*(WEEKDAY(AB211)=IFERROR(WEEKDAY('Recurring Items'!$G$6:$G$56),0))*(MOD(AB211-IFERROR('Recurring Items'!$G$6:$G$56,0),14)=0)*(AB211>=IFERROR('Recurring Items'!$G$6:$G$56,9000000000))+('Recurring Items'!$E$6:$E$56="Weekly")*(WEEKDAY(AB211)=IFERROR(WEEKDAY('Recurring Items'!$G$6:$G$56),0))*(AB211>=IFERROR('Recurring Items'!$G$6:$G$56,9000000000))+('Recurring Items'!$E$6:$E$56="One-time")*(AB211='Recurring Items'!$G$6:$G$56))) -> 167.68 | AF211: =(IF(AC211=1,'Debt Tracker'!$P$5>0.01,INDEX('Debt Tracker'!$T$5:$AE$29,1,AC211-1)>0.01))*('Recurring Items'!$H$8<>"Skip")*(DAY(AB211)='Recurring Items'!$F$8)*IFERROR(N('Recurring Items'!$D$8),0)+(IF(AC211=1,'Debt Tracker'!$P$6>0.01,INDEX('Debt Tracker'!$T$5:$AE$29,2,AC211-1)>0.01))*('Recurring Items'!$H$9<>"Skip")*(DAY(AB211)='Recurring Items'!$F$9)*IFERROR(N('Recurring Items'!$D$9),0)+(IF(AC211=1,'Debt Tracker'!$P$7>0.01,INDEX('Debt Tracker'!$T$5:$AE$29,3,AC211-1)>0.01))*('Recurring Items'!$H$10<>"Skip")*(DAY(AB211)='Recurring Items'!$F$10)*IFERROR(N('Recurring Items'!$D$10),0)+(IF(AC211=1,'Debt Tracker'!$P$8>0.01,INDEX('Debt Tracker'!$T$5:$AE$29,4,AC211-1)>0.01))*('Recurring Items'!$H$11<>"Skip")*(DAY(AB211)='Recurring Items'!$F$11)*IFERROR(N('Recurring Items'!$D$11),0)+(IF(AC211=1,'Debt Tracker'!$P$9>0.01,INDEX('Debt Tracker'!$T$5:$AE$29,5,AC211-1)>0.01))*('Recurring Items'!$H$12<>"Skip")*(DAY(AB211)='Recurring Items'!$F$12)*IFERROR(N('Recurring Items'!$D$12),0)+(IF(AC211=1,'Debt Tracker'!$P$10>0.01,INDEX('Debt Tracker'!$T$5:$AE$29,6,AC211-1)>0.01))*('Recurring Items'!$H$13<>"Skip")*(DAY(AB211)='Recurring Items'!$F$13)*IFERROR(N('Recurring Items'!$D$13),0)+(IF(AC211=1,'Debt Tracker'!$P$11>0.01,INDEX('Debt Tracker'!$T$5:$AE$29,7,AC211-1)>0.01))*('Recurring Items'!$H$14<>"Skip")*(DAY(AB211)='Recurring Items'!$F$14)*IFERROR(N('Recurring Items'!$D$14),0)+(IF(AC211=1,'Debt Tracker'!$P$12>0.01,INDEX('Debt Tracker'!$T$5:$AE$29,8,AC211-1)>0.01))*('Recurring Items'!$H$15<>"Skip")*(DAY(AB211)='Recurring Items'!$F$15)*IFERROR(N('Recurring Items'!$D$15),0)+(IF(AC211=1,'Debt Tracker'!$P$13>0.01,INDEX('Debt Tracker'!$T$5:$AE$29,9,AC211-1)>0.01))*('Recurring Items'!$H$16<>"Skip")*(DAY(AB211)='Recurring Items'!$F$16)*IFERROR(N('Recurring Items'!$D$16),0)+(IF(AC211=1,'Debt Tracker'!$P$14>0.01,INDEX('Debt Tracker'!$T$5:$AE$29,10,AC211-1)>0.01))*('Recurring Items'!$H$17<>"Skip")*(DAY(AB211)='Recurring Items'!$F$17)*IFERROR(N('Recurring Items'!$D$17),0)+(IF(AC211=1,'Debt Tracker'!$P$15>0.01,INDEX('Debt Tracker'!$T$5:$AE$29,11,AC211-1)>0.01))*('Recurring Items'!$H$18<>"Skip")*(DAY(AB211)='Recurring Items'!$F$18)*IFERROR(N('Recurring Items'!$D$18),0)+(IF(AC211=1,'Debt Tracker'!$P$16>0.01,INDEX('Debt Tracker'!$T$5:$AE$29,12,AC211-1)>0.01))*('Recurring Items'!$H$19<>"Skip")*(DAY(AB211)='Recurring Items'!$F$19)*IFERROR(N('Recurring Items'!$D$19),0)+(IF(AC211=1,'Debt Tracker'!$P$17>0.01,INDEX('Debt Tracker'!$T$5:$AE$29,13,AC211-1)>0.01))*('Recurring Items'!$H$20<>"Skip")*(DAY(AB211)='Recurring Items'!$F$20)*IFERROR(N('Recurring Items'!$D$20),0)+(IF(AC211=1,'Debt Tracker'!$P$18>0.01,INDEX('Debt Tracker'!$T$5:$AE$29,14,AC211-1)>0.01))*('Recurring Items'!$H$21<>"Skip")*(DAY(AB211)='Recurring Items'!$F$21)*IFERROR(N('Recurring Items'!$D$21),0)+(IF(AC211=1,'Debt Tracker'!$P$19>0.01,INDEX('Debt Tracker'!$T$5:$AE$29,15,AC211-1)>0.01))*('Recurring Items'!$H$22<>"Skip")*(DAY(AB211)='Recurring Items'!$F$22)*IFERROR(N('Recurring Items'!$D$22),0)+(IF(AC211=1,'Debt Tracker'!$P$20>0.01,INDEX('Debt Tracker'!$T$5:$AE$29,16,AC211-1)>0.01))*('Recurring Items'!$H$23<>"Skip")*(DAY(AB211)='Recurring Items'!$F$23)*IFERROR(N('Recurring Items'!$D$23),0)+(IF(AC211=1,'Debt Tracker'!$P$21>0.01,INDEX('Debt Tracker'!$T$5:$AE$29,17,AC211-1)>0.01))*('Recurring Items'!$H$24<>"Skip")*(DAY(AB211)='Recurring Items'!$F$24)*IFERROR(N('Recurring Items'!$D$24),0)+(IF(AC211=1,'Debt Tracker'!$P$22>0.01,INDEX('Debt Tracker'!$T$5:$AE$29,18,AC211-1)>0.01))*('Recurring Items'!$H$25<>"Skip")*(DAY(AB211)='Recurring Items'!$F$25)*IFERROR(N('Recurring Items'!$D$25),0)+(IF(AC211=1,'Debt Tracker'!$P$23>0.01,INDEX('Debt Tracker'!$T$5:$AE$29,19,AC211-1)>0.01))*('Recurring Items'!$H$26<>"Skip")*(DAY(AB211)='Recurring Items'!$F$26)*IFERROR(N('Recurring Items'!$D$26),0)+(IF(AC211=1,'Debt Tracker'!$P$24>0.01,INDEX('Debt Tracker'!$T$5:$AE$29,20,AC211-1)>0.01))*('Recurring Items'!$H$27<>"Skip")*(DAY(AB211)='Recurring Items'!$F$27)*IFERROR(N('Recurring Items'!$D$27),0)+(IF(AC211=1,'Debt Tracker'!$P$25>0.01,INDEX('Debt Tracker'!$T$5:$AE$29,21,AC211-1)>0.01))*('Recurring Items'!$H$28<>"Skip")*(DAY(AB211)='Recurring Items'!$F$28)*IFERROR(N('Recurring Items'!$D$28),0)+(IF(AC211=1,'Debt Tracker'!$P$26>0.01,INDEX('Debt Tracker'!$T$5:$AE$29,22,AC211-1)>0.01))*('Recurring Items'!$H$29<>"Skip")*(DAY(AB211)='Recurring Items'!$F$29)*IFERROR(N('Recurring Items'!$D$29),0)+(IF(AC211=1,'Debt Tracker'!$P$27>0.01,INDEX('Debt Tracker'!$T$5:$AE$29,23,AC211-1)>0.01))*('Recurring Items'!$H$30<>"Skip")*(DAY(AB211)='Recurring Items'!$F$30)*IFERROR(N('Recurring Items'!$D$30),0)+(IF(AC211=1,'Debt Tracker'!$P$28>0.01,INDEX('Debt Tracker'!$T$5:$AE$29,24,AC211-1)>0.01))*('Recurring Items'!$H$31<>"Skip")*(DAY(AB211)='Recurring Items'!$F$31)*IFERROR(N('Recurring Items'!$D$31),0)+(IF(AC211=1,'Debt Tracker'!$P$29>0.01,INDEX('Debt Tracker'!$T$5:$AE$29,25,AC211-1)>0.01))*('Recurring Items'!$H$32<>"Skip")*(DAY(AB211)='Recurring Items'!$F$32)*IFERROR(N('Recurring Items'!$D$32),0) -> 0 | AG211: =AD211-AE211-AF211 -> -167.68 | AH211: =AH210+AG211 -> 3207.18
AA212: 12 | AB212: =$D$3+12 -> 46155 | AC212: =MIN(12,1+DATEDIF($D$3,AB212,"M")) -> 1 | AD212: =SUMPRODUCT(('Recurring Items'!$C$6:$C$56="Income")*('Recurring Items'!$H$6:$H$56<>"Skip")*IFERROR(N('Recurring Items'!$D$6:$D$56),0)*(('Recurring Items'!$E$6:$E$56="Monthly")*(DAY(AB212)='Recurring Items'!$F$6:$F$56)+('Recurring Items'!$E$6:$E$56="Bi-weekly")*(WEEKDAY(AB212)=IFERROR(WEEKDAY('Recurring Items'!$G$6:$G$56),0))*(MOD(AB212-IFERROR('Recurring Items'!$G$6:$G$56,0),14)=0)*(AB212>=IFERROR('Recurring Items'!$G$6:$G$56,9000000000))+('Recurring Items'!$E$6:$E$56="Weekly")*(WEEKDAY(AB212)=IFERROR(WEEKDAY('Recurring Items'!$G$6:$G$56),0))*(AB212>=IFERROR('Recurring Items'!$G$6:$G$56,9000000000))+('Recurring Items'!$E$6:$E$56="One-time")*(AB212='Recurring Items'!$G$6:$G$56))) -> 0 | AE212: =SUMPRODUCT(('Recurring Items'!$C$6:$C$56="Expense")*('Recurring Items'!$H$6:$H$56<>"Skip")*IFERROR(N('Recurring Items'!$D$6:$D$56),0)*(('Recurring Items'!$E$6:$E$56="Monthly")*(DAY(AB212)='Recurring Items'!$F$6:$F$56)+('Recurring Items'!$E$6:$E$56="Bi-weekly")*(WEEKDAY(AB212)=IFERROR(WEEKDAY('Recurring Items'!$G$6:$G$56),0))*(MOD(AB212-IFERROR('Recurring Items'!$G$6:$G$56,0),14)=0)*(AB212>=IFERROR('Recurring Items'!$G$6:$G$56,9000000000))+('Recurring Items'!$E$6:$E$56="Weekly")*(WEEKDAY(AB212)=IFERROR(WEEKDAY('Recurring Items'!$G$6:$G$56),0))*(AB212>=IFERROR('Recurring Items'!$G$6:$G$56,9000000000))+('Recurring Items'!$E$6:$E$56="One-time")*(AB212='Recurring Items'!$G$6:$G$56))) -> 0 | AF212: =(IF(AC212=1,'Debt Tracker'!$P$5>0.01,INDEX('Debt Tracker'!$T$5:$AE$29,1,AC212-1)>0.01))*('Recurring Items'!$H$8<>"Skip")*(DAY(AB212)='Recurring Items'!$F$8)*IFERROR(N('Recurring Items'!$D$8),0)+(IF(AC212=1,'Debt Tracker'!$P$6>0.01,INDEX('Debt Tracker'!$T$5:$AE$29,2,AC212-1)>0.01))*('Recurring Items'!$H$9<>"Skip")*(DAY(AB212)='Recurring Items'!$F$9)*IFERROR(N('Recurring Items'!$D$9),0)+(IF(AC212=1,'Debt Tracker'!$P$7>0.01,INDEX('Debt Tracker'!$T$5:$AE$29,3,AC212-1)>0.01))*('Recurring Items'!$H$10<>"Skip")*(DAY(AB212)='Recurring Items'!$F$10)*IFERROR(N('Recurring Items'!$D$10),0)+(IF(AC212=1,'Debt Tracker'!$P$8>0.01,INDEX('Debt Tracker'!$T$5:$AE$29,4,AC212-1)>0.01))*('Recurring Items'!$H$11<>"Skip")*(DAY(AB212)='Recurring Items'!$F$11)*IFERROR(N('Recurring Items'!$D$11),0)+(IF(AC212=1,'Debt Tracker'!$P$9>0.01,INDEX('Debt Tracker'!$T$5:$AE$29,5,AC212-1)>0.01))*('Recurring Items'!$H$12<>"Skip")*(DAY(AB212)='Recurring Items'!$F$12)*IFERROR(N('Recurring Items'!$D$12),0)+(IF(AC212=1,'Debt Tracker'!$P$10>0.01,INDEX('Debt Tracker'!$T$5:$AE$29,6,AC212-1)>0.01))*('Recurring Items'!$H$13<>"Skip")*(DAY(AB212)='Recurring Items'!$F$13)*IFERROR(N('Recurring Items'!$D$13),0)+(IF(AC212=1,'Debt Tracker'!$P$11>0.01,INDEX('Debt Tracker'!$T$5:$AE$29,7,AC212-1)>0.01))*('Recurring Items'!$H$14<>"Skip")*(DAY(AB212)='Recurring Items'!$F$14)*IFERROR(N('Recurring Items'!$D$14),0)+(IF(AC212=1,'Debt Tracker'!$P$12>0.01,INDEX('Debt Tracker'!$T$5:$AE$29,8,AC212-1)>0.01))*('Recurring Items'!$H$15<>"Skip")*(DAY(AB212)='Recurring Items'!$F$15)*IFERROR(N('Recurring Items'!$D$15),0)+(IF(AC212=1,'Debt Tracker'!$P$13>0.01,INDEX('Debt Tracker'!$T$5:$AE$29,9,AC212-1)>0.01))*('Recurring Items'!$H$16<>"Skip")*(DAY(AB212)='Recurring Items'!$F$16)*IFERROR(N('Recurring Items'!$D$16),0)+(IF(AC212=1,'Debt Tracker'!$P$14>0.01,INDEX('Debt Tracker'!$T$5:$AE$29,10,AC212-1)>0.01))*('Recurring Items'!$H$17<>"Skip")*(DAY(AB212)='Recurring Items'!$F$17)*IFERROR(N('Recurring Items'!$D$17),0)+(IF(AC212=1,'Debt Tracker'!$P$15>0.01,INDEX('Debt Tracker'!$T$5:$AE$29,11,AC212-1)>0.01))*('Recurring Items'!$H$18<>"Skip")*(DAY(AB212)='Recurring Items'!$F$18)*IFERROR(N('Recurring Items'!$D$18),0)+(IF(AC212=1,'Debt Tracker'!$P$16>0.01,INDEX('Debt Tracker'!$T$5:$AE$29,12,AC212-1)>0.01))*('Recurring Items'!$H$19<>"Skip")*(DAY(AB212)='Recurring Items'!$F$19)*IFERROR(N('Recurring Items'!$D$19),0)+(IF(AC212=1,'Debt Tracker'!$P$17>0.01,INDEX('Debt Tracker'!$T$5:$AE$29,13,AC212-1)>0.01))*('Recurring Items'!$H$20<>"Skip")*(DAY(AB212)='Recurring Items'!$F$20)*IFERROR(N('Recurring Items'!$D$20),0)+(IF(AC212=1,'Debt Tracker'!$P$18>0.01,INDEX('Debt Tracker'!$T$5:$AE$29,14,AC212-1)>0.01))*('Recurring Items'!$H$21<>"Skip")*(DAY(AB212)='Recurring Items'!$F$21)*IFERROR(N('Recurring Items'!$D$21),0)+(IF(AC212=1,'Debt Tracker'!$P$19>0.01,INDEX('Debt Tracker'!$T$5:$AE$29,15,AC212-1)>0.01))*('Recurring Items'!$H$22<>"Skip")*(DAY(AB212)='Recurring Items'!$F$22)*IFERROR(N('Recurring Items'!$D$22),0)+(IF(AC212=1,'Debt Tracker'!$P$20>0.01,INDEX('Debt Tracker'!$T$5:$AE$29,16,AC212-1)>0.01))*('Recurring Items'!$H$23<>"Skip")*(DAY(AB212)='Recurring Items'!$F$23)*IFERROR(N('Recurring Items'!$D$23),0)+(IF(AC212=1,'Debt Tracker'!$P$21>0.01,INDEX('Debt Tracker'!$T$5:$AE$29,17,AC212-1)>0.01))*('Recurring Items'!$H$24<>"Skip")*(DAY(AB212)='Recurring Items'!$F$24)*IFERROR(N('Recurring Items'!$D$24),0)+(IF(AC212=1,'Debt Tracker'!$P$22>0.01,INDEX('Debt Tracker'!$T$5:$AE$29,18,AC212-1)>0.01))*('Recurring Items'!$H$25<>"Skip")*(DAY(AB212)='Recurring Items'!$F$25)*IFERROR(N('Recurring Items'!$D$25),0)+(IF(AC212=1,'Debt Tracker'!$P$23>0.01,INDEX('Debt Tracker'!$T$5:$AE$29,19,AC212-1)>0.01))*('Recurring Items'!$H$26<>"Skip")*(DAY(AB212)='Recurring Items'!$F$26)*IFERROR(N('Recurring Items'!$D$26),0)+(IF(AC212=1,'Debt Tracker'!$P$24>0.01,INDEX('Debt Tracker'!$T$5:$AE$29,20,AC212-1)>0.01))*('Recurring Items'!$H$27<>"Skip")*(DAY(AB212)='Recurring Items'!$F$27)*IFERROR(N('Recurring Items'!$D$27),0)+(IF(AC212=1,'Debt Tracker'!$P$25>0.01,INDEX('Debt Tracker'!$T$5:$AE$29,21,AC212-1)>0.01))*('Recurring Items'!$H$28<>"Skip")*(DAY(AB212)='Recurring Items'!$F$28)*IFERROR(N('Recurring Items'!$D$28),0)+(IF(AC212=1,'Debt Tracker'!$P$26>0.01,INDEX('Debt Tracker'!$T$5:$AE$29,22,AC212-1)>0.01))*('Recurring Items'!$H$29<>"Skip")*(DAY(AB212)='Recurring Items'!$F$29)*IFERROR(N('Recurring Items'!$D$29),0)+(IF(AC212=1,'Debt Tracker'!$P$27>0.01,INDEX('Debt Tracker'!$T$5:$AE$29,23,AC212-1)>0.01))*('Recurring Items'!$H$30<>"Skip")*(DAY(AB212)='Recurring Items'!$F$30)*IFERROR(N('Recurring Items'!$D$30),0)+(IF(AC212=1,'Debt Tracker'!$P$28>0.01,INDEX('Debt Tracker'!$T$5:$AE$29,24,AC212-1)>0.01))*('Recurring Items'!$H$31<>"Skip")*(DAY(AB212)='Recurring Items'!$F$31)*IFERROR(N('Recurring Items'!$D$31),0)+(IF(AC212=1,'Debt Tracker'!$P$29>0.01,INDEX('Debt Tracker'!$T$5:$AE$29,25,AC212-1)>0.01))*('Recurring Items'!$H$32<>"Skip")*(DAY(AB212)='Recurring Items'!$F$32)*IFERROR(N('Recurring Items'!$D$32),0) -> 80 | AG212: =AD212-AE212-AF212 -> -80 | AH212: =AH211+AG212 -> 3127.18
AA213: 13 | AB213: =$D$3+13 -> 46156 | AC213: =MIN(12,1+DATEDIF($D$3,AB213,"M")) -> 1 | AD213: =SUMPRODUCT(('Recurring Items'!$C$6:$C$56="Income")*('Recurring Items'!$H$6:$H$56<>"Skip")*IFERROR(N('Recurring Items'!$D$6:$D$56),0)*(('Recurring Items'!$E$6:$E$56="Monthly")*(DAY(AB213)='Recurring Items'!$F$6:$F$56)+('Recurring Items'!$E$6:$E$56="Bi-weekly")*(WEEKDAY(AB213)=IFERROR(WEEKDAY('Recurring Items'!$G$6:$G$56),0))*(MOD(AB213-IFERROR('Recurring Items'!$G$6:$G$56,0),14)=0)*(AB213>=IFERROR('Recurring Items'!$G$6:$G$56,9000000000))+('Recurring Items'!$E$6:$E$56="Weekly")*(WEEKDAY(AB213)=IFERROR(WEEKDAY('Recurring Items'!$G$6:$G$56),0))*(AB213>=IFERROR('Recurring Items'!$G$6:$G$56,9000000000))+('Recurring Items'!$E$6:$E$56="One-time")*(AB213='Recurring Items'!$G$6:$G$56))) -> 0 | AE213: =SUMPRODUCT(('Recurring Items'!$C$6:$C$56="Expense")*('Recurring Items'!$H$6:$H$56<>"Skip")*IFERROR(N('Recurring Items'!$D$6:$D$56),0)*(('Recurring Items'!$E$6:$E$56="Monthly")*(DAY(AB213)='Recurring Items'!$F$6:$F$56)+('Recurring Items'!$E$6:$E$56="Bi-weekly")*(WEEKDAY(AB213)=IFERROR(WEEKDAY('Recurring Items'!$G$6:$G$56),0))*(MOD(AB213-IFERROR('Recurring Items'!$G$6:$G$56,0),14)=0)*(AB213>=IFERROR('Recurring Items'!$G$6:$G$56,9000000000))+('Recurring Items'!$E$6:$E$56="Weekly")*(WEEKDAY(AB213)=IFERROR(WEEKDAY('Recurring Items'!$G$6:$G$56),0))*(AB213>=IFERROR('Recurring Items'!$G$6:$G$56,9000000000))+('Recurring Items'!$E$6:$E$56="One-time")*(AB213='Recurring Items'!$G$6:$G$56))) -> 0 | AF213: =(IF(AC213=1,'Debt Tracker'!$P$5>0.01,INDEX('Debt Tracker'!$T$5:$AE$29,1,AC213-1)>0.01))*('Recurring Items'!$H$8<>"Skip")*(DAY(AB213)='Recurring Items'!$F$8)*IFERROR(N('Recurring Items'!$D$8),0)+(IF(AC213=1,'Debt Tracker'!$P$6>0.01,INDEX('Debt Tracker'!$T$5:$AE$29,2,AC213-1)>0.01))*('Recurring Items'!$H$9<>"Skip")*(DAY(AB213)='Recurring Items'!$F$9)*IFERROR(N('Recurring Items'!$D$9),0)+(IF(AC213=1,'Debt Tracker'!$P$7>0.01,INDEX('Debt Tracker'!$T$5:$AE$29,3,AC213-1)>0.01))*('Recurring Items'!$H$10<>"Skip")*(DAY(AB213)='Recurring Items'!$F$10)*IFERROR(N('Recurring Items'!$D$10),0)+(IF(AC213=1,'Debt Tracker'!$P$8>0.01,INDEX('Debt Tracker'!$T$5:$AE$29,4,AC213-1)>0.01))*('Recurring Items'!$H$11<>"Skip")*(DAY(AB213)='Recurring Items'!$F$11)*IFERROR(N('Recurring Items'!$D$11),0)+(IF(AC213=1,'Debt Tracker'!$P$9>0.01,INDEX('Debt Tracker'!$T$5:$AE$29,5,AC213-1)>0.01))*('Recurring Items'!$H$12<>"Skip")*(DAY(AB213)='Recurring Items'!$F$12)*IFERROR(N('Recurring Items'!$D$12),0)+(IF(AC213=1,'Debt Tracker'!$P$10>0.01,INDEX('Debt Tracker'!$T$5:$AE$29,6,AC213-1)>0.01))*('Recurring Items'!$H$13<>"Skip")*(DAY(AB213)='Recurring Items'!$F$13)*IFERROR(N('Recurring Items'!$D$13),0)+(IF(AC213=1,'Debt Tracker'!$P$11>0.01,INDEX('Debt Tracker'!$T$5:$AE$29,7,AC213-1)>0.01))*('Recurring Items'!$H$14<>"Skip")*(DAY(AB213)='Recurring Items'!$F$14)*IFERROR(N('Recurring Items'!$D$14),0)+(IF(AC213=1,'Debt Tracker'!$P$12>0.01,INDEX('Debt Tracker'!$T$5:$AE$29,8,AC213-1)>0.01))*('Recurring Items'!$H$15<>"Skip")*(DAY(AB213)='Recurring Items'!$F$15)*IFERROR(N('Recurring Items'!$D$15),0)+(IF(AC213=1,'Debt Tracker'!$P$13>0.01,INDEX('Debt Tracker'!$T$5:$AE$29,9,AC213-1)>0.01))*('Recurring Items'!$H$16<>"Skip")*(DAY(AB213)='Recurring Items'!$F$16)*IFERROR(N('Recurring Items'!$D$16),0)+(IF(AC213=1,'Debt Tracker'!$P$14>0.01,INDEX('Debt Tracker'!$T$5:$AE$29,10,AC213-1)>0.01))*('Recurring Items'!$H$17<>"Skip")*(DAY(AB213)='Recurring Items'!$F$17)*IFERROR(N('Recurring Items'!$D$17),0)+(IF(AC213=1,'Debt Tracker'!$P$15>0.01,INDEX('Debt Tracker'!$T$5:$AE$29,11,AC213-1)>0.01))*('Recurring Items'!$H$18<>"Skip")*(DAY(AB213)='Recurring Items'!$F$18)*IFERROR(N('Recurring Items'!$D$18),0)+(IF(AC213=1,'Debt Tracker'!$P$16>0.01,INDEX('Debt Tracker'!$T$5:$AE$29,12,AC213-1)>0.01))*('Recurring Items'!$H$19<>"Skip")*(DAY(AB213)='Recurring Items'!$F$19)*IFERROR(N('Recurring Items'!$D$19),0)+(IF(AC213=1,'Debt Tracker'!$P$17>0.01,INDEX('Debt Tracker'!$T$5:$AE$29,13,AC213-1)>0.01))*('Recurring Items'!$H$20<>"Skip")*(DAY(AB213)='Recurring Items'!$F$20)*IFERROR(N('Recurring Items'!$D$20),0)+(IF(AC213=1,'Debt Tracker'!$P$18>0.01,INDEX('Debt Tracker'!$T$5:$AE$29,14,AC213-1)>0.01))*('Recurring Items'!$H$21<>"Skip")*(DAY(AB213)='Recurring Items'!$F$21)*IFERROR(N('Recurring Items'!$D$21),0)+(IF(AC213=1,'Debt Tracker'!$P$19>0.01,INDEX('Debt Tracker'!$T$5:$AE$29,15,AC213-1)>0.01))*('Recurring Items'!$H$22<>"Skip")*(DAY(AB213)='Recurring Items'!$F$22)*IFERROR(N('Recurring Items'!$D$22),0)+(IF(AC213=1,'Debt Tracker'!$P$20>0.01,INDEX('Debt Tracker'!$T$5:$AE$29,16,AC213-1)>0.01))*('Recurring Items'!$H$23<>"Skip")*(DAY(AB213)='Recurring Items'!$F$23)*IFERROR(N('Recurring Items'!$D$23),0)+(IF(AC213=1,'Debt Tracker'!$P$21>0.01,INDEX('Debt Tracker'!$T$5:$AE$29,17,AC213-1)>0.01))*('Recurring Items'!$H$24<>"Skip")*(DAY(AB213)='Recurring Items'!$F$24)*IFERROR(N('Recurring Items'!$D$24),0)+(IF(AC213=1,'Debt Tracker'!$P$22>0.01,INDEX('Debt Tracker'!$T$5:$AE$29,18,AC213-1)>0.01))*('Recurring Items'!$H$25<>"Skip")*(DAY(AB213)='Recurring Items'!$F$25)*IFERROR(N('Recurring Items'!$D$25),0)+(IF(AC213=1,'Debt Tracker'!$P$23>0.01,INDEX('Debt Tracker'!$T$5:$AE$29,19,AC213-1)>0.01))*('Recurring Items'!$H$26<>"Skip")*(DAY(AB213)='Recurring Items'!$F$26)*IFERROR(N('Recurring Items'!$D$26),0)+(IF(AC213=1,'Debt Tracker'!$P$24>0.01,INDEX('Debt Tracker'!$T$5:$AE$29,20,AC213-1)>0.01))*('Recurring Items'!$H$27<>"Skip")*(DAY(AB213)='Recurring Items'!$F$27)*IFERROR(N('Recurring Items'!$D$27),0)+(IF(AC213=1,'Debt Tracker'!$P$25>0.01,INDEX('Debt Tracker'!$T$5:$AE$29,21,AC213-1)>0.01))*('Recurring Items'!$H$28<>"Skip")*(DAY(AB213)='Recurring Items'!$F$28)*IFERROR(N('Recurring Items'!$D$28),0)+(IF(AC213=1,'Debt Tracker'!$P$26>0.01,INDEX('Debt Tracker'!$T$5:$AE$29,22,AC213-1)>0.01))*('Recurring Items'!$H$29<>"Skip")*(DAY(AB213)='Recurring Items'!$F$29)*IFERROR(N('Recurring Items'!$D$29),0)+(IF(AC213=1,'Debt Tracker'!$P$27>0.01,INDEX('Debt Tracker'!$T$5:$AE$29,23,AC213-1)>0.01))*('Recurring Items'!$H$30<>"Skip")*(DAY(AB213)='Recurring Items'!$F$30)*IFERROR(N('Recurring Items'!$D$30),0)+(IF(AC213=1,'Debt Tracker'!$P$28>0.01,INDEX('Debt Tracker'!$T$5:$AE$29,24,AC213-1)>0.01))*('Recurring Items'!$H$31<>"Skip")*(DAY(AB213)='Recurring Items'!$F$31)*IFERROR(N('Recurring Items'!$D$31),0)+(IF(AC213=1,'Debt Tracker'!$P$29>0.01,INDEX('Debt Tracker'!$T$5:$AE$29,25,AC213-1)>0.01))*('Recurring Items'!$H$32<>"Skip")*(DAY(AB213)='Recurring Items'!$F$32)*IFERROR(N('Recurring Items'!$D$32),0) -> 95.51 | AG213: =AD213-AE213-AF213 -> -95.51 | AH213: =AH212+AG213 -> 3031.67
AA214: 14 | AB214: =$D$3+14 -> 46157 | AC214: =MIN(12,1+DATEDIF($D$3,AB214,"M")) -> 1 | AD214: =SUMPRODUCT(('Recurring Items'!$C$6:$C$56="Income")*('Recurring Items'!$H$6:$H$56<>"Skip")*IFERROR(N('Recurring Items'!$D$6:$D$56),0)*(('Recurring Items'!$E$6:$E$56="Monthly")*(DAY(AB214)='Recurring Items'!$F$6:$F$56)+('Recurring Items'!$E$6:$E$56="Bi-weekly")*(WEEKDAY(AB214)=IFERROR(WEEKDAY('Recurring Items'!$G$6:$G$56),0))*(MOD(AB214-IFERROR('Recurring Items'!$G$6:$G$56,0),14)=0)*(AB214>=IFERROR('Recurring Items'!$G$6:$G$56,9000000000))+('Recurring Items'!$E$6:$E$56="Weekly")*(WEEKDAY(AB214)=IFERROR(WEEKDAY('Recurring Items'!$G$6:$G$56),0))*(AB214>=IFERROR('Recurring Items'!$G$6:$G$56,9000000000))+('Recurring Items'!$E$6:$E$56="One-time")*(AB214='Recurring Items'!$G$6:$G$56))) -> 3819.79 | AE214: =SUMPRODUCT(('Recurring Items'!$C$6:$C$56="Expense")*('Recurring Items'!$H$6:$H$56<>"Skip")*IFERROR(N('Recurring Items'!$D$6:$D$56),0)*(('Recurring Items'!$E$6:$E$56="Monthly")*(DAY(AB214)='Recurring Items'!$F$6:$F$56)+('Recurring Items'!$E$6:$E$56="Bi-weekly")*(WEEKDAY(AB214)=IFERROR(WEEKDAY('Recurring Items'!$G$6:$G$56),0))*(MOD(AB214-IFERROR('Recurring Items'!$G$6:$G$56,0),14)=0)*(AB214>=IFERROR('Recurring Items'!$G$6:$G$56,9000000000))+('Recurring Items'!$E$6:$E$56="Weekly")*(WEEKDAY(AB214)=IFERROR(WEEKDAY('Recurring Items'!$G$6:$G$56),0))*(AB214>=IFERROR('Recurring Items'!$G$6:$G$56,9000000000))+('Recurring Items'!$E$6:$E$56="One-time")*(AB214='Recurring Items'!$G$6:$G$56))) -> 3450.57 | AF214: =(IF(AC214=1,'Debt Tracker'!$P$5>0.01,INDEX('Debt Tracker'!$T$5:$AE$29,1,AC214-1)>0.01))*('Recurring Items'!$H$8<>"Skip")*(DAY(AB214)='Recurring Items'!$F$8)*IFERROR(N('Recurring Items'!$D$8),0)+(IF(AC214=1,'Debt Tracker'!$P$6>0.01,INDEX('Debt Tracker'!$T$5:$AE$29,2,AC214-1)>0.01))*('Recurring Items'!$H$9<>"Skip")*(DAY(AB214)='Recurring Items'!$F$9)*IFERROR(N('Recurring Items'!$D$9),0)+(IF(AC214=1,'Debt Tracker'!$P$7>0.01,INDEX('Debt Tracker'!$T$5:$AE$29,3,AC214-1)>0.01))*('Recurring Items'!$H$10<>"Skip")*(DAY(AB214)='Recurring Items'!$F$10)*IFERROR(N('Recurring Items'!$D$10),0)+(IF(AC214=1,'Debt Tracker'!$P$8>0.01,INDEX('Debt Tracker'!$T$5:$AE$29,4,AC214-1)>0.01))*('Recurring Items'!$H$11<>"Skip")*(DAY(AB214)='Recurring Items'!$F$11)*IFERROR(N('Recurring Items'!$D$11),0)+(IF(AC214=1,'Debt Tracker'!$P$9>0.01,INDEX('Debt Tracker'!$T$5:$AE$29,5,AC214-1)>0.01))*('Recurring Items'!$H$12<>"Skip")*(DAY(AB214)='Recurring Items'!$F$12)*IFERROR(N('Recurring Items'!$D$12),0)+(IF(AC214=1,'Debt Tracker'!$P$10>0.01,INDEX('Debt Tracker'!$T$5:$AE$29,6,AC214-1)>0.01))*('Recurring Items'!$H$13<>"Skip")*(DAY(AB214)='Recurring Items'!$F$13)*IFERROR(N('Recurring Items'!$D$13),0)+(IF(AC214=1,'Debt Tracker'!$P$11>0.01,INDEX('Debt Tracker'!$T$5:$AE$29,7,AC214-1)>0.01))*('Recurring Items'!$H$14<>"Skip")*(DAY(AB214)='Recurring Items'!$F$14)*IFERROR(N('Recurring Items'!$D$14),0)+(IF(AC214=1,'Debt Tracker'!$P$12>0.01,INDEX('Debt Tracker'!$T$5:$AE$29,8,AC214-1)>0.01))*('Recurring Items'!$H$15<>"Skip")*(DAY(AB214)='Recurring Items'!$F$15)*IFERROR(N('Recurring Items'!$D$15),0)+(IF(AC214=1,'Debt Tracker'!$P$13>0.01,INDEX('Debt Tracker'!$T$5:$AE$29,9,AC214-1)>0.01))*('Recurring Items'!$H$16<>"Skip")*(DAY(AB214)='Recurring Items'!$F$16)*IFERROR(N('Recurring Items'!$D$16),0)+(IF(AC214=1,'Debt Tracker'!$P$14>0.01,INDEX('Debt Tracker'!$T$5:$AE$29,10,AC214-1)>0.01))*('Recurring Items'!$H$17<>"Skip")*(DAY(AB214)='Recurring Items'!$F$17)*IFERROR(N('Recurring Items'!$D$17),0)+(IF(AC214=1,'Debt Tracker'!$P$15>0.01,INDEX('Debt Tracker'!$T$5:$AE$29,11,AC214-1)>0.01))*('Recurring Items'!$H$18<>"Skip")*(DAY(AB214)='Recurring Items'!$F$18)*IFERROR(N('Recurring Items'!$D$18),0)+(IF(AC214=1,'Debt Tracker'!$P$16>0.01,INDEX('Debt Tracker'!$T$5:$AE$29,12,AC214-1)>0.01))*('Recurring Items'!$H$19<>"Skip")*(DAY(AB214)='Recurring Items'!$F$19)*IFERROR(N('Recurring Items'!$D$19),0)+(IF(AC214=1,'Debt Tracker'!$P$17>0.01,INDEX('Debt Tracker'!$T$5:$AE$29,13,AC214-1)>0.01))*('Recurring Items'!$H$20<>"Skip")*(DAY(AB214)='Recurring Items'!$F$20)*IFERROR(N('Recurring Items'!$D$20),0)+(IF(AC214=1,'Debt Tracker'!$P$18>0.01,INDEX('Debt Tracker'!$T$5:$AE$29,14,AC214-1)>0.01))*('Recurring Items'!$H$21<>"Skip")*(DAY(AB214)='Recurring Items'!$F$21)*IFERROR(N('Recurring Items'!$D$21),0)+(IF(AC214=1,'Debt Tracker'!$P$19>0.01,INDEX('Debt Tracker'!$T$5:$AE$29,15,AC214-1)>0.01))*('Recurring Items'!$H$22<>"Skip")*(DAY(AB214)='Recurring Items'!$F$22)*IFERROR(N('Recurring Items'!$D$22),0)+(IF(AC214=1,'Debt Tracker'!$P$20>0.01,INDEX('Debt Tracker'!$T$5:$AE$29,16,AC214-1)>0.01))*('Recurring Items'!$H$23<>"Skip")*(DAY(AB214)='Recurring Items'!$F$23)*IFERROR(N('Recurring Items'!$D$23),0)+(IF(AC214=1,'Debt Tracker'!$P$21>0.01,INDEX('Debt Tracker'!$T$5:$AE$29,17,AC214-1)>0.01))*('Recurring Items'!$H$24<>"Skip")*(DAY(AB214)='Recurring Items'!$F$24)*IFERROR(N('Recurring Items'!$D$24),0)+(IF(AC214=1,'Debt Tracker'!$P$22>0.01,INDEX('Debt Tracker'!$T$5:$AE$29,18,AC214-1)>0.01))*('Recurring Items'!$H$25<>"Skip")*(DAY(AB214)='Recurring Items'!$F$25)*IFERROR(N('Recurring Items'!$D$25),0)+(IF(AC214=1,'Debt Tracker'!$P$23>0.01,INDEX('Debt Tracker'!$T$5:$AE$29,19,AC214-1)>0.01))*('Recurring Items'!$H$26<>"Skip")*(DAY(AB214)='Recurring Items'!$F$26)*IFERROR(N('Recurring Items'!$D$26),0)+(IF(AC214=1,'Debt Tracker'!$P$24>0.01,INDEX('Debt Tracker'!$T$5:$AE$29,20,AC214-1)>0.01))*('Recurring Items'!$H$27<>"Skip")*(DAY(AB214)='Recurring Items'!$F$27)*IFERROR(N('Recurring Items'!$D$27),0)+(IF(AC214=1,'Debt Tracker'!$P$25>0.01,INDEX('Debt Tracker'!$T$5:$AE$29,21,AC214-1)>0.01))*('Recurring Items'!$H$28<>"Skip")*(DAY(AB214)='Recurring Items'!$F$28)*IFERROR(N('Recurring Items'!$D$28),0)+(IF(AC214=1,'Debt Tracker'!$P$26>0.01,INDEX('Debt Tracker'!$T$5:$AE$29,22,AC214-1)>0.01))*('Recurring Items'!$H$29<>"Skip")*(DAY(AB214)='Recurring Items'!$F$29)*IFERROR(N('Recurring Items'!$D$29),0)+(IF(AC214=1,'Debt Tracker'!$P$27>0.01,INDEX('Debt Tracker'!$T$5:$AE$29,23,AC214-1)>0.01))*('Recurring Items'!$H$30<>"Skip")*(DAY(AB214)='Recurring Items'!$F$30)*IFERROR(N('Recurring Items'!$D$30),0)+(IF(AC214=1,'Debt Tracker'!$P$28>0.01,INDEX('Debt Tracker'!$T$5:$AE$29,24,AC214-1)>0.01))*('Recurring Items'!$H$31<>"Skip")*(DAY(AB214)='Recurring Items'!$F$31)*IFERROR(N('Recurring Items'!$D$31),0)+(IF(AC214=1,'Debt Tracker'!$P$29>0.01,INDEX('Debt Tracker'!$T$5:$AE$29,25,AC214-1)>0.01))*('Recurring Items'!$H$32<>"Skip")*(DAY(AB214)='Recurring Items'!$F$32)*IFERROR(N('Recurring Items'!$D$32),0) -> 136.75 | AG214: =AD214-AE214-AF214 -> 232.47 | AH214: =AH213+AG214 -> 3264.14
AA215: 15 | AB215: =$D$3+15 -> 46158 | AC215: =MIN(12,1+DATEDIF($D$3,AB215,"M")) -> 1 | AD215: =SUMPRODUCT(('Recurring Items'!$C$6:$C$56="Income")*('Recurring Items'!$H$6:$H$56<>"Skip")*IFERROR(N('Recurring Items'!$D$6:$D$56),0)*(('Recurring Items'!$E$6:$E$56="Monthly")*(DAY(AB215)='Recurring Items'!$F$6:$F$56)+('Recurring Items'!$E$6:$E$56="Bi-weekly")*(WEEKDAY(AB215)=IFERROR(WEEKDAY('Recurring Items'!$G$6:$G$56),0))*(MOD(AB215-IFERROR('Recurring Items'!$G$6:$G$56,0),14)=0)*(AB215>=IFERROR('Recurring Items'!$G$6:$G$56,9000000000))+('Recurring Items'!$E$6:$E$56="Weekly")*(WEEKDAY(AB215)=IFERROR(WEEKDAY('Recurring Items'!$G$6:$G$56),0))*(AB215>=IFERROR('Recurring Items'!$G$6:$G$56,9000000000))+('Recurring Items'!$E$6:$E$56="One-time")*(AB215='Recurring Items'!$G$6:$G$56))) -> 0 | AE215: =SUMPRODUCT(('Recurring Items'!$C$6:$C$56="Expense")*('Recurring Items'!$H$6:$H$56<>"Skip")*IFERROR(N('Recurring Items'!$D$6:$D$56),0)*(('Recurring Items'!$E$6:$E$56="Monthly")*(DAY(AB215)='Recurring Items'!$F$6:$F$56)+('Recurring Items'!$E$6:$E$56="Bi-weekly")*(WEEKDAY(AB215)=IFERROR(WEEKDAY('Recurring Items'!$G$6:$G$56),0))*(MOD(AB215-IFERROR('Recurring Items'!$G$6:$G$56,0),14)=0)*(AB215>=IFERROR('Recurring Items'!$G$6:$G$56,9000000000))+('Recurring Items'!$E$6:$E$56="Weekly")*(WEEKDAY(AB215)=IFERROR(WEEKDAY('Recurring Items'!$G$6:$G$56),0))*(AB215>=IFERROR('Recurring Items'!$G$6:$G$56,9000000000))+('Recurring Items'!$E$6:$E$56="One-time")*(AB215='Recurring Items'!$G$6:$G$56))) -> 342 | AF215: =(IF(AC215=1,'Debt Tracker'!$P$5>0.01,INDEX('Debt Tracker'!$T$5:$AE$29,1,AC215-1)>0.01))*('Recurring Items'!$H$8<>"Skip")*(DAY(AB215)='Recurring Items'!$F$8)*IFERROR(N('Recurring Items'!$D$8),0)+(IF(AC215=1,'Debt Tracker'!$P$6>0.01,INDEX('Debt Tracker'!$T$5:$AE$29,2,AC215-1)>0.01))*('Recurring Items'!$H$9<>"Skip")*(DAY(AB215)='Recurring Items'!$F$9)*IFERROR(N('Recurring Items'!$D$9),0)+(IF(AC215=1,'Debt Tracker'!$P$7>0.01,INDEX('Debt Tracker'!$T$5:$AE$29,3,AC215-1)>0.01))*('Recurring Items'!$H$10<>"Skip")*(DAY(AB215)='Recurring Items'!$F$10)*IFERROR(N('Recurring Items'!$D$10),0)+(IF(AC215=1,'Debt Tracker'!$P$8>0.01,INDEX('Debt Tracker'!$T$5:$AE$29,4,AC215-1)>0.01))*('Recurring Items'!$H$11<>"Skip")*(DAY(AB215)='Recurring Items'!$F$11)*IFERROR(N('Recurring Items'!$D$11),0)+(IF(AC215=1,'Debt Tracker'!$P$9>0.01,INDEX('Debt Tracker'!$T$5:$AE$29,5,AC215-1)>0.01))*('Recurring Items'!$H$12<>"Skip")*(DAY(AB215)='Recurring Items'!$F$12)*IFERROR(N('Recurring Items'!$D$12),0)+(IF(AC215=1,'Debt Tracker'!$P$10>0.01,INDEX('Debt Tracker'!$T$5:$AE$29,6,AC215-1)>0.01))*('Recurring Items'!$H$13<>"Skip")*(DAY(AB215)='Recurring Items'!$F$13)*IFERROR(N('Recurring Items'!$D$13),0)+(IF(AC215=1,'Debt Tracker'!$P$11>0.01,INDEX('Debt Tracker'!$T$5:$AE$29,7,AC215-1)>0.01))*('Recurring Items'!$H$14<>"Skip")*(DAY(AB215)='Recurring Items'!$F$14)*IFERROR(N('Recurring Items'!$D$14),0)+(IF(AC215=1,'Debt Tracker'!$P$12>0.01,INDEX('Debt Tracker'!$T$5:$AE$29,8,AC215-1)>0.01))*('Recurring Items'!$H$15<>"Skip")*(DAY(AB215)='Recurring Items'!$F$15)*IFERROR(N('Recurring Items'!$D$15),0)+(IF(AC215=1,'Debt Tracker'!$P$13>0.01,INDEX('Debt Tracker'!$T$5:$AE$29,9,AC215-1)>0.01))*('Recurring Items'!$H$16<>"Skip")*(DAY(AB215)='Recurring Items'!$F$16)*IFERROR(N('Recurring Items'!$D$16),0)+(IF(AC215=1,'Debt Tracker'!$P$14>0.01,INDEX('Debt Tracker'!$T$5:$AE$29,10,AC215-1)>0.01))*('Recurring Items'!$H$17<>"Skip")*(DAY(AB215)='Recurring Items'!$F$17)*IFERROR(N('Recurring Items'!$D$17),0)+(IF(AC215=1,'Debt Tracker'!$P$15>0.01,INDEX('Debt Tracker'!$T$5:$AE$29,11,AC215-1)>0.01))*('Recurring Items'!$H$18<>"Skip")*(DAY(AB215)='Recurring Items'!$F$18)*IFERROR(N('Recurring Items'!$D$18),0)+(IF(AC215=1,'Debt Tracker'!$P$16>0.01,INDEX('Debt Tracker'!$T$5:$AE$29,12,AC215-1)>0.01))*('Recurring Items'!$H$19<>"Skip")*(DAY(AB215)='Recurring Items'!$F$19)*IFERROR(N('Recurring Items'!$D$19),0)+(IF(AC215=1,'Debt Tracker'!$P$17>0.01,INDEX('Debt Tracker'!$T$5:$AE$29,13,AC215-1)>0.01))*('Recurring Items'!$H$20<>"Skip")*(DAY(AB215)='Recurring Items'!$F$20)*IFERROR(N('Recurring Items'!$D$20),0)+(IF(AC215=1,'Debt Tracker'!$P$18>0.01,INDEX('Debt Tracker'!$T$5:$AE$29,14,AC215-1)>0.01))*('Recurring Items'!$H$21<>"Skip")*(DAY(AB215)='Recurring Items'!$F$21)*IFERROR(N('Recurring Items'!$D$21),0)+(IF(AC215=1,'Debt Tracker'!$P$19>0.01,INDEX('Debt Tracker'!$T$5:$AE$29,15,AC215-1)>0.01))*('Recurring Items'!$H$22<>"Skip")*(DAY(AB215)='Recurring Items'!$F$22)*IFERROR(N('Recurring Items'!$D$22),0)+(IF(AC215=1,'Debt Tracker'!$P$20>0.01,INDEX('Debt Tracker'!$T$5:$AE$29,16,AC215-1)>0.01))*('Recurring Items'!$H$23<>"Skip")*(DAY(AB215)='Recurring Items'!$F$23)*IFERROR(N('Recurring Items'!$D$23),0)+(IF(AC215=1,'Debt Tracker'!$P$21>0.01,INDEX('Debt Tracker'!$T$5:$AE$29,17,AC215-1)>0.01))*('Recurring Items'!$H$24<>"Skip")*(DAY(AB215)='Recurring Items'!$F$24)*IFERROR(N('Recurring Items'!$D$24),0)+(IF(AC215=1,'Debt Tracker'!$P$22>0.01,INDEX('Debt Tracker'!$T$5:$AE$29,18,AC215-1)>0.01))*('Recurring Items'!$H$25<>"Skip")*(DAY(AB215)='Recurring Items'!$F$25)*IFERROR(N('Recurring Items'!$D$25),0)+(IF(AC215=1,'Debt Tracker'!$P$23>0.01,INDEX('Debt Tracker'!$T$5:$AE$29,19,AC215-1)>0.01))*('Recurring Items'!$H$26<>"Skip")*(DAY(AB215)='Recurring Items'!$F$26)*IFERROR(N('Recurring Items'!$D$26),0)+(IF(AC215=1,'Debt Tracker'!$P$24>0.01,INDEX('Debt Tracker'!$T$5:$AE$29,20,AC215-1)>0.01))*('Recurring Items'!$H$27<>"Skip")*(DAY(AB215)='Recurring Items'!$F$27)*IFERROR(N('Recurring Items'!$D$27),0)+(IF(AC215=1,'Debt Tracker'!$P$25>0.01,INDEX('Debt Tracker'!$T$5:$AE$29,21,AC215-1)>0.01))*('Recurring Items'!$H$28<>"Skip")*(DAY(AB215)='Recurring Items'!$F$28)*IFERROR(N('Recurring Items'!$D$28),0)+(IF(AC215=1,'Debt Tracker'!$P$26>0.01,INDEX('Debt Tracker'!$T$5:$AE$29,22,AC215-1)>0.01))*('Recurring Items'!$H$29<>"Skip")*(DAY(AB215)='Recurring Items'!$F$29)*IFERROR(N('Recurring Items'!$D$29),0)+(IF(AC215=1,'Debt Tracker'!$P$27>0.01,INDEX('Debt Tracker'!$T$5:$AE$29,23,AC215-1)>0.01))*('Recurring Items'!$H$30<>"Skip")*(DAY(AB215)='Recurring Items'!$F$30)*IFERROR(N('Recurring Items'!$D$30),0)+(IF(AC215=1,'Debt Tracker'!$P$28>0.01,INDEX('Debt Tracker'!$T$5:$AE$29,24,AC215-1)>0.01))*('Recurring Items'!$H$31<>"Skip")*(DAY(AB215)='Recurring Items'!$F$31)*IFERROR(N('Recurring Items'!$D$31),0)+(IF(AC215=1,'Debt Tracker'!$P$29>0.01,INDEX('Debt Tracker'!$T$5:$AE$29,25,AC215-1)>0.01))*('Recurring Items'!$H$32<>"Skip")*(DAY(AB215)='Recurring Items'!$F$32)*IFERROR(N('Recurring Items'!$D$32),0) -> 143 | AG215: =AD215-AE215-AF215 -> -485 | AH215: =AH214+AG215 -> 2779.14
AA216: 16 | AB216: =$D$3+16 -> 46159 | AC216: =MIN(12,1+DATEDIF($D$3,AB216,"M")) -> 1 | AD216: =SUMPRODUCT(('Recurring Items'!$C$6:$C$56="Income")*('Recurring Items'!$H$6:$H$56<>"Skip")*IFERROR(N('Recurring Items'!$D$6:$D$56),0)*(('Recurring Items'!$E$6:$E$56="Monthly")*(DAY(AB216)='Recurring Items'!$F$6:$F$56)+('Recurring Items'!$E$6:$E$56="Bi-weekly")*(WEEKDAY(AB216)=IFERROR(WEEKDAY('Recurring Items'!$G$6:$G$56),0))*(MOD(AB216-IFERROR('Recurring Items'!$G$6:$G$56,0),14)=0)*(AB216>=IFERROR('Recurring Items'!$G$6:$G$56,9000000000))+('Recurring Items'!$E$6:$E$56="Weekly")*(WEEKDAY(AB216)=IFERROR(WEEKDAY('Recurring Items'!$G$6:$G$56),0))*(AB216>=IFERROR('Recurring Items'!$G$6:$G$56,9000000000))+('Recurring Items'!$E$6:$E$56="One-time")*(AB216='Recurring Items'!$G$6:$G$56))) -> 0 | AE216: =SUMPRODUCT(('Recurring Items'!$C$6:$C$56="Expense")*('Recurring Items'!$H$6:$H$56<>"Skip")*IFERROR(N('Recurring Items'!$D$6:$D$56),0)*(('Recurring Items'!$E$6:$E$56="Monthly")*(DAY(AB216)='Recurring Items'!$F$6:$F$56)+('Recurring Items'!$E$6:$E$56="Bi-weekly")*(WEEKDAY(AB216)=IFERROR(WEEKDAY('Recurring Items'!$G$6:$G$56),0))*(MOD(AB216-IFERROR('Recurring Items'!$G$6:$G$56,0),14)=0)*(AB216>=IFERROR('Recurring Items'!$G$6:$G$56,9000000000))+('Recurring Items'!$E$6:$E$56="Weekly")*(WEEKDAY(AB216)=IFERROR(WEEKDAY('Recurring Items'!$G$6:$G$56),0))*(AB216>=IFERROR('Recurring Items'!$G$6:$G$56,9000000000))+('Recurring Items'!$E$6:$E$56="One-time")*(AB216='Recurring Items'!$G$6:$G$56))) -> 0 | AF216: =(IF(AC216=1,'Debt Tracker'!$P$5>0.01,INDEX('Debt Tracker'!$T$5:$AE$29,1,AC216-1)>0.01))*('Recurring Items'!$H$8<>"Skip")*(DAY(AB216)='Recurring Items'!$F$8)*IFERROR(N('Recurring Items'!$D$8),0)+(IF(AC216=1,'Debt Tracker'!$P$6>0.01,INDEX('Debt Tracker'!$T$5:$AE$29,2,AC216-1)>0.01))*('Recurring Items'!$H$9<>"Skip")*(DAY(AB216)='Recurring Items'!$F$9)*IFERROR(N('Recurring Items'!$D$9),0)+(IF(AC216=1,'Debt Tracker'!$P$7>0.01,INDEX('Debt Tracker'!$T$5:$AE$29,3,AC216-1)>0.01))*('Recurring Items'!$H$10<>"Skip")*(DAY(AB216)='Recurring Items'!$F$10)*IFERROR(N('Recurring Items'!$D$10),0)+(IF(AC216=1,'Debt Tracker'!$P$8>0.01,INDEX('Debt Tracker'!$T$5:$AE$29,4,AC216-1)>0.01))*('Recurring Items'!$H$11<>"Skip")*(DAY(AB216)='Recurring Items'!$F$11)*IFERROR(N('Recurring Items'!$D$11),0)+(IF(AC216=1,'Debt Tracker'!$P$9>0.01,INDEX('Debt Tracker'!$T$5:$AE$29,5,AC216-1)>0.01))*('Recurring Items'!$H$12<>"Skip")*(DAY(AB216)='Recurring Items'!$F$12)*IFERROR(N('Recurring Items'!$D$12),0)+(IF(AC216=1,'Debt Tracker'!$P$10>0.01,INDEX('Debt Tracker'!$T$5:$AE$29,6,AC216-1)>0.01))*('Recurring Items'!$H$13<>"Skip")*(DAY(AB216)='Recurring Items'!$F$13)*IFERROR(N('Recurring Items'!$D$13),0)+(IF(AC216=1,'Debt Tracker'!$P$11>0.01,INDEX('Debt Tracker'!$T$5:$AE$29,7,AC216-1)>0.01))*('Recurring Items'!$H$14<>"Skip")*(DAY(AB216)='Recurring Items'!$F$14)*IFERROR(N('Recurring Items'!$D$14),0)+(IF(AC216=1,'Debt Tracker'!$P$12>0.01,INDEX('Debt Tracker'!$T$5:$AE$29,8,AC216-1)>0.01))*('Recurring Items'!$H$15<>"Skip")*(DAY(AB216)='Recurring Items'!$F$15)*IFERROR(N('Recurring Items'!$D$15),0)+(IF(AC216=1,'Debt Tracker'!$P$13>0.01,INDEX('Debt Tracker'!$T$5:$AE$29,9,AC216-1)>0.01))*('Recurring Items'!$H$16<>"Skip")*(DAY(AB216)='Recurring Items'!$F$16)*IFERROR(N('Recurring Items'!$D$16),0)+(IF(AC216=1,'Debt Tracker'!$P$14>0.01,INDEX('Debt Tracker'!$T$5:$AE$29,10,AC216-1)>0.01))*('Recurring Items'!$H$17<>"Skip")*(DAY(AB216)='Recurring Items'!$F$17)*IFERROR(N('Recurring Items'!$D$17),0)+(IF(AC216=1,'Debt Tracker'!$P$15>0.01,INDEX('Debt Tracker'!$T$5:$AE$29,11,AC216-1)>0.01))*('Recurring Items'!$H$18<>"Skip")*(DAY(AB216)='Recurring Items'!$F$18)*IFERROR(N('Recurring Items'!$D$18),0)+(IF(AC216=1,'Debt Tracker'!$P$16>0.01,INDEX('Debt Tracker'!$T$5:$AE$29,12,AC216-1)>0.01))*('Recurring Items'!$H$19<>"Skip")*(DAY(AB216)='Recurring Items'!$F$19)*IFERROR(N('Recurring Items'!$D$19),0)+(IF(AC216=1,'Debt Tracker'!$P$17>0.01,INDEX('Debt Tracker'!$T$5:$AE$29,13,AC216-1)>0.01))*('Recurring Items'!$H$20<>"Skip")*(DAY(AB216)='Recurring Items'!$F$20)*IFERROR(N('Recurring Items'!$D$20),0)+(IF(AC216=1,'Debt Tracker'!$P$18>0.01,INDEX('Debt Tracker'!$T$5:$AE$29,14,AC216-1)>0.01))*('Recurring Items'!$H$21<>"Skip")*(DAY(AB216)='Recurring Items'!$F$21)*IFERROR(N('Recurring Items'!$D$21),0)+(IF(AC216=1,'Debt Tracker'!$P$19>0.01,INDEX('Debt Tracker'!$T$5:$AE$29,15,AC216-1)>0.01))*('Recurring Items'!$H$22<>"Skip")*(DAY(AB216)='Recurring Items'!$F$22)*IFERROR(N('Recurring Items'!$D$22),0)+(IF(AC216=1,'Debt Tracker'!$P$20>0.01,INDEX('Debt Tracker'!$T$5:$AE$29,16,AC216-1)>0.01))*('Recurring Items'!$H$23<>"Skip")*(DAY(AB216)='Recurring Items'!$F$23)*IFERROR(N('Recurring Items'!$D$23),0)+(IF(AC216=1,'Debt Tracker'!$P$21>0.01,INDEX('Debt Tracker'!$T$5:$AE$29,17,AC216-1)>0.01))*('Recurring Items'!$H$24<>"Skip")*(DAY(AB216)='Recurring Items'!$F$24)*IFERROR(N('Recurring Items'!$D$24),0)+(IF(AC216=1,'Debt Tracker'!$P$22>0.01,INDEX('Debt Tracker'!$T$5:$AE$29,18,AC216-1)>0.01))*('Recurring Items'!$H$25<>"Skip")*(DAY(AB216)='Recurring Items'!$F$25)*IFERROR(N('Recurring Items'!$D$25),0)+(IF(AC216=1,'Debt Tracker'!$P$23>0.01,INDEX('Debt Tracker'!$T$5:$AE$29,19,AC216-1)>0.01))*('Recurring Items'!$H$26<>"Skip")*(DAY(AB216)='Recurring Items'!$F$26)*IFERROR(N('Recurring Items'!$D$26),0)+(IF(AC216=1,'Debt Tracker'!$P$24>0.01,INDEX('Debt Tracker'!$T$5:$AE$29,20,AC216-1)>0.01))*('Recurring Items'!$H$27<>"Skip")*(DAY(AB216)='Recurring Items'!$F$27)*IFERROR(N('Recurring Items'!$D$27),0)+(IF(AC216=1,'Debt Tracker'!$P$25>0.01,INDEX('Debt Tracker'!$T$5:$AE$29,21,AC216-1)>0.01))*('Recurring Items'!$H$28<>"Skip")*(DAY(AB216)='Recurring Items'!$F$28)*IFERROR(N('Recurring Items'!$D$28),0)+(IF(AC216=1,'Debt Tracker'!$P$26>0.01,INDEX('Debt Tracker'!$T$5:$AE$29,22,AC216-1)>0.01))*('Recurring Items'!$H$29<>"Skip")*(DAY(AB216)='Recurring Items'!$F$29)*IFERROR(N('Recurring Items'!$D$29),0)+(IF(AC216=1,'Debt Tracker'!$P$27>0.01,INDEX('Debt Tracker'!$T$5:$AE$29,23,AC216-1)>0.01))*('Recurring Items'!$H$30<>"Skip")*(DAY(AB216)='Recurring Items'!$F$30)*IFERROR(N('Recurring Items'!$D$30),0)+(IF(AC216=1,'Debt Tracker'!$P$28>0.01,INDEX('Debt Tracker'!$T$5:$AE$29,24,AC216-1)>0.01))*('Recurring Items'!$H$31<>"Skip")*(DAY(AB216)='Recurring Items'!$F$31)*IFERROR(N('Recurring Items'!$D$31),0)+(IF(AC216=1,'Debt Tracker'!$P$29>0.01,INDEX('Debt Tracker'!$T$5:$AE$29,25,AC216-1)>0.01))*('Recurring Items'!$H$32<>"Skip")*(DAY(AB216)='Recurring Items'!$F$32)*IFERROR(N('Recurring Items'!$D$32),0) -> 0 | AG216: =AD216-AE216-AF216 -> 0 | AH216: =AH215+AG216 -> 2779.14
AA217: 17 | AB217: =$D$3+17 -> 46160 | AC217: =MIN(12,1+DATEDIF($D$3,AB217,"M")) -> 1 | AD217: =SUMPRODUCT(('Recurring Items'!$C$6:$C$56="Income")*('Recurring Items'!$H$6:$H$56<>"Skip")*IFERROR(N('Recurring Items'!$D$6:$D$56),0)*(('Recurring Items'!$E$6:$E$56="Monthly")*(DAY(AB217)='Recurring Items'!$F$6:$F$56)+('Recurring Items'!$E$6:$E$56="Bi-weekly")*(WEEKDAY(AB217)=IFERROR(WEEKDAY('Recurring Items'!$G$6:$G$56),0))*(MOD(AB217-IFERROR('Recurring Items'!$G$6:$G$56,0),14)=0)*(AB217>=IFERROR('Recurring Items'!$G$6:$G$56,9000000000))+('Recurring Items'!$E$6:$E$56="Weekly")*(WEEKDAY(AB217)=IFERROR(WEEKDAY('Recurring Items'!$G$6:$G$56),0))*(AB217>=IFERROR('Recurring Items'!$G$6:$G$56,9000000000))+('Recurring Items'!$E$6:$E$56="One-time")*(AB217='Recurring Items'!$G$6:$G$56))) -> 0 | AE217: =SUMPRODUCT(('Recurring Items'!$C$6:$C$56="Expense")*('Recurring Items'!$H$6:$H$56<>"Skip")*IFERROR(N('Recurring Items'!$D$6:$D$56),0)*(('Recurring Items'!$E$6:$E$56="Monthly")*(DAY(AB217)='Recurring Items'!$F$6:$F$56)+('Recurring Items'!$E$6:$E$56="Bi-weekly")*(WEEKDAY(AB217)=IFERROR(WEEKDAY('Recurring Items'!$G$6:$G$56),0))*(MOD(AB217-IFERROR('Recurring Items'!$G$6:$G$56,0),14)=0)*(AB217>=IFERROR('Recurring Items'!$G$6:$G$56,9000000000))+('Recurring Items'!$E$6:$E$56="Weekly")*(WEEKDAY(AB217)=IFERROR(WEEKDAY('Recurring Items'!$G$6:$G$56),0))*(AB217>=IFERROR('Recurring Items'!$G$6:$G$56,9000000000))+('Recurring Items'!$E$6:$E$56="One-time")*(AB217='Recurring Items'!$G$6:$G$56))) -> 0 | AF217: =(IF(AC217=1,'Debt Tracker'!$P$5>0.01,INDEX('Debt Tracker'!$T$5:$AE$29,1,AC217-1)>0.01))*('Recurring Items'!$H$8<>"Skip")*(DAY(AB217)='Recurring Items'!$F$8)*IFERROR(N('Recurring Items'!$D$8),0)+(IF(AC217=1,'Debt Tracker'!$P$6>0.01,INDEX('Debt Tracker'!$T$5:$AE$29,2,AC217-1)>0.01))*('Recurring Items'!$H$9<>"Skip")*(DAY(AB217)='Recurring Items'!$F$9)*IFERROR(N('Recurring Items'!$D$9),0)+(IF(AC217=1,'Debt Tracker'!$P$7>0.01,INDEX('Debt Tracker'!$T$5:$AE$29,3,AC217-1)>0.01))*('Recurring Items'!$H$10<>"Skip")*(DAY(AB217)='Recurring Items'!$F$10)*IFERROR(N('Recurring Items'!$D$10),0)+(IF(AC217=1,'Debt Tracker'!$P$8>0.01,INDEX('Debt Tracker'!$T$5:$AE$29,4,AC217-1)>0.01))*('Recurring Items'!$H$11<>"Skip")*(DAY(AB217)='Recurring Items'!$F$11)*IFERROR(N('Recurring Items'!$D$11),0)+(IF(AC217=1,'Debt Tracker'!$P$9>0.01,INDEX('Debt Tracker'!$T$5:$AE$29,5,AC217-1)>0.01))*('Recurring Items'!$H$12<>"Skip")*(DAY(AB217)='Recurring Items'!$F$12)*IFERROR(N('Recurring Items'!$D$12),0)+(IF(AC217=1,'Debt Tracker'!$P$10>0.01,INDEX('Debt Tracker'!$T$5:$AE$29,6,AC217-1)>0.01))*('Recurring Items'!$H$13<>"Skip")*(DAY(AB217)='Recurring Items'!$F$13)*IFERROR(N('Recurring Items'!$D$13),0)+(IF(AC217=1,'Debt Tracker'!$P$11>0.01,INDEX('Debt Tracker'!$T$5:$AE$29,7,AC217-1)>0.01))*('Recurring Items'!$H$14<>"Skip")*(DAY(AB217)='Recurring Items'!$F$14)*IFERROR(N('Recurring Items'!$D$14),0)+(IF(AC217=1,'Debt Tracker'!$P$12>0.01,INDEX('Debt Tracker'!$T$5:$AE$29,8,AC217-1)>0.01))*('Recurring Items'!$H$15<>"Skip")*(DAY(AB217)='Recurring Items'!$F$15)*IFERROR(N('Recurring Items'!$D$15),0)+(IF(AC217=1,'Debt Tracker'!$P$13>0.01,INDEX('Debt Tracker'!$T$5:$AE$29,9,AC217-1)>0.01))*('Recurring Items'!$H$16<>"Skip")*(DAY(AB217)='Recurring Items'!$F$16)*IFERROR(N('Recurring Items'!$D$16),0)+(IF(AC217=1,'Debt Tracker'!$P$14>0.01,INDEX('Debt Tracker'!$T$5:$AE$29,10,AC217-1)>0.01))*('Recurring Items'!$H$17<>"Skip")*(DAY(AB217)='Recurring Items'!$F$17)*IFERROR(N('Recurring Items'!$D$17),0)+(IF(AC217=1,'Debt Tracker'!$P$15>0.01,INDEX('Debt Tracker'!$T$5:$AE$29,11,AC217-1)>0.01))*('Recurring Items'!$H$18<>"Skip")*(DAY(AB217)='Recurring Items'!$F$18)*IFERROR(N('Recurring Items'!$D$18),0)+(IF(AC217=1,'Debt Tracker'!$P$16>0.01,INDEX('Debt Tracker'!$T$5:$AE$29,12,AC217-1)>0.01))*('Recurring Items'!$H$19<>"Skip")*(DAY(AB217)='Recurring Items'!$F$19)*IFERROR(N('Recurring Items'!$D$19),0)+(IF(AC217=1,'Debt Tracker'!$P$17>0.01,INDEX('Debt Tracker'!$T$5:$AE$29,13,AC217-1)>0.01))*('Recurring Items'!$H$20<>"Skip")*(DAY(AB217)='Recurring Items'!$F$20)*IFERROR(N('Recurring Items'!$D$20),0)+(IF(AC217=1,'Debt Tracker'!$P$18>0.01,INDEX('Debt Tracker'!$T$5:$AE$29,14,AC217-1)>0.01))*('Recurring Items'!$H$21<>"Skip")*(DAY(AB217)='Recurring Items'!$F$21)*IFERROR(N('Recurring Items'!$D$21),0)+(IF(AC217=1,'Debt Tracker'!$P$19>0.01,INDEX('Debt Tracker'!$T$5:$AE$29,15,AC217-1)>0.01))*('Recurring Items'!$H$22<>"Skip")*(DAY(AB217)='Recurring Items'!$F$22)*IFERROR(N('Recurring Items'!$D$22),0)+(IF(AC217=1,'Debt Tracker'!$P$20>0.01,INDEX('Debt Tracker'!$T$5:$AE$29,16,AC217-1)>0.01))*('Recurring Items'!$H$23<>"Skip")*(DAY(AB217)='Recurring Items'!$F$23)*IFERROR(N('Recurring Items'!$D$23),0)+(IF(AC217=1,'Debt Tracker'!$P$21>0.01,INDEX('Debt Tracker'!$T$5:$AE$29,17,AC217-1)>0.01))*('Recurring Items'!$H$24<>"Skip")*(DAY(AB217)='Recurring Items'!$F$24)*IFERROR(N('Recurring Items'!$D$24),0)+(IF(AC217=1,'Debt Tracker'!$P$22>0.01,INDEX('Debt Tracker'!$T$5:$AE$29,18,AC217-1)>0.01))*('Recurring Items'!$H$25<>"Skip")*(DAY(AB217)='Recurring Items'!$F$25)*IFERROR(N('Recurring Items'!$D$25),0)+(IF(AC217=1,'Debt Tracker'!$P$23>0.01,INDEX('Debt Tracker'!$T$5:$AE$29,19,AC217-1)>0.01))*('Recurring Items'!$H$26<>"Skip")*(DAY(AB217)='Recurring Items'!$F$26)*IFERROR(N('Recurring Items'!$D$26),0)+(IF(AC217=1,'Debt Tracker'!$P$24>0.01,INDEX('Debt Tracker'!$T$5:$AE$29,20,AC217-1)>0.01))*('Recurring Items'!$H$27<>"Skip")*(DAY(AB217)='Recurring Items'!$F$27)*IFERROR(N('Recurring Items'!$D$27),0)+(IF(AC217=1,'Debt Tracker'!$P$25>0.01,INDEX('Debt Tracker'!$T$5:$AE$29,21,AC217-1)>0.01))*('Recurring Items'!$H$28<>"Skip")*(DAY(AB217)='Recurring Items'!$F$28)*IFERROR(N('Recurring Items'!$D$28),0)+(IF(AC217=1,'Debt Tracker'!$P$26>0.01,INDEX('Debt Tracker'!$T$5:$AE$29,22,AC217-1)>0.01))*('Recurring Items'!$H$29<>"Skip")*(DAY(AB217)='Recurring Items'!$F$29)*IFERROR(N('Recurring Items'!$D$29),0)+(IF(AC217=1,'Debt Tracker'!$P$27>0.01,INDEX('Debt Tracker'!$T$5:$AE$29,23,AC217-1)>0.01))*('Recurring Items'!$H$30<>"Skip")*(DAY(AB217)='Recurring Items'!$F$30)*IFERROR(N('Recurring Items'!$D$30),0)+(IF(AC217=1,'Debt Tracker'!$P$28>0.01,INDEX('Debt Tracker'!$T$5:$AE$29,24,AC217-1)>0.01))*('Recurring Items'!$H$31<>"Skip")*(DAY(AB217)='Recurring Items'!$F$31)*IFERROR(N('Recurring Items'!$D$31),0)+(IF(AC217=1,'Debt Tracker'!$P$29>0.01,INDEX('Debt Tracker'!$T$5:$AE$29,25,AC217-1)>0.01))*('Recurring Items'!$H$32<>"Skip")*(DAY(AB217)='Recurring Items'!$F$32)*IFERROR(N('Recurring Items'!$D$32),0) -> 0 | AG217: =AD217-AE217-AF217 -> 0 | AH217: =AH216+AG217 -> 2779.14
AA218: 18 | AB218: =$D$3+18 -> 46161 | AC218: =MIN(12,1+DATEDIF($D$3,AB218,"M")) -> 1 | AD218: =SUMPRODUCT(('Recurring Items'!$C$6:$C$56="Income")*('Recurring Items'!$H$6:$H$56<>"Skip")*IFERROR(N('Recurring Items'!$D$6:$D$56),0)*(('Recurring Items'!$E$6:$E$56="Monthly")*(DAY(AB218)='Recurring Items'!$F$6:$F$56)+('Recurring Items'!$E$6:$E$56="Bi-weekly")*(WEEKDAY(AB218)=IFERROR(WEEKDAY('Recurring Items'!$G$6:$G$56),0))*(MOD(AB218-IFERROR('Recurring Items'!$G$6:$G$56,0),14)=0)*(AB218>=IFERROR('Recurring Items'!$G$6:$G$56,9000000000))+('Recurring Items'!$E$6:$E$56="Weekly")*(WEEKDAY(AB218)=IFERROR(WEEKDAY('Recurring Items'!$G$6:$G$56),0))*(AB218>=IFERROR('Recurring Items'!$G$6:$G$56,9000000000))+('Recurring Items'!$E$6:$E$56="One-time")*(AB218='Recurring Items'!$G$6:$G$56))) -> 0 | AE218: =SUMPRODUCT(('Recurring Items'!$C$6:$C$56="Expense")*('Recurring Items'!$H$6:$H$56<>"Skip")*IFERROR(N('Recurring Items'!$D$6:$D$56),0)*(('Recurring Items'!$E$6:$E$56="Monthly")*(DAY(AB218)='Recurring Items'!$F$6:$F$56)+('Recurring Items'!$E$6:$E$56="Bi-weekly")*(WEEKDAY(AB218)=IFERROR(WEEKDAY('Recurring Items'!$G$6:$G$56),0))*(MOD(AB218-IFERROR('Recurring Items'!$G$6:$G$56,0),14)=0)*(AB218>=IFERROR('Recurring Items'!$G$6:$G$56,9000000000))+('Recurring Items'!$E$6:$E$56="Weekly")*(WEEKDAY(AB218)=IFERROR(WEEKDAY('Recurring Items'!$G$6:$G$56),0))*(AB218>=IFERROR('Recurring Items'!$G$6:$G$56,9000000000))+('Recurring Items'!$E$6:$E$56="One-time")*(AB218='Recurring Items'!$G$6:$G$56))) -> 0 | AF218: =(IF(AC218=1,'Debt Tracker'!$P$5>0.01,INDEX('Debt Tracker'!$T$5:$AE$29,1,AC218-1)>0.01))*('Recurring Items'!$H$8<>"Skip")*(DAY(AB218)='Recurring Items'!$F$8)*IFERROR(N('Recurring Items'!$D$8),0)+(IF(AC218=1,'Debt Tracker'!$P$6>0.01,INDEX('Debt Tracker'!$T$5:$AE$29,2,AC218-1)>0.01))*('Recurring Items'!$H$9<>"Skip")*(DAY(AB218)='Recurring Items'!$F$9)*IFERROR(N('Recurring Items'!$D$9),0)+(IF(AC218=1,'Debt Tracker'!$P$7>0.01,INDEX('Debt Tracker'!$T$5:$AE$29,3,AC218-1)>0.01))*('Recurring Items'!$H$10<>"Skip")*(DAY(AB218)='Recurring Items'!$F$10)*IFERROR(N('Recurring Items'!$D$10),0)+(IF(AC218=1,'Debt Tracker'!$P$8>0.01,INDEX('Debt Tracker'!$T$5:$AE$29,4,AC218-1)>0.01))*('Recurring Items'!$H$11<>"Skip")*(DAY(AB218)='Recurring Items'!$F$11)*IFERROR(N('Recurring Items'!$D$11),0)+(IF(AC218=1,'Debt Tracker'!$P$9>0.01,INDEX('Debt Tracker'!$T$5:$AE$29,5,AC218-1)>0.01))*('Recurring Items'!$H$12<>"Skip")*(DAY(AB218)='Recurring Items'!$F$12)*IFERROR(N('Recurring Items'!$D$12),0)+(IF(AC218=1,'Debt Tracker'!$P$10>0.01,INDEX('Debt Tracker'!$T$5:$AE$29,6,AC218-1)>0.01))*('Recurring Items'!$H$13<>"Skip")*(DAY(AB218)='Recurring Items'!$F$13)*IFERROR(N('Recurring Items'!$D$13),0)+(IF(AC218=1,'Debt Tracker'!$P$11>0.01,INDEX('Debt Tracker'!$T$5:$AE$29,7,AC218-1)>0.01))*('Recurring Items'!$H$14<>"Skip")*(DAY(AB218)='Recurring Items'!$F$14)*IFERROR(N('Recurring Items'!$D$14),0)+(IF(AC218=1,'Debt Tracker'!$P$12>0.01,INDEX('Debt Tracker'!$T$5:$AE$29,8,AC218-1)>0.01))*('Recurring Items'!$H$15<>"Skip")*(DAY(AB218)='Recurring Items'!$F$15)*IFERROR(N('Recurring Items'!$D$15),0)+(IF(AC218=1,'Debt Tracker'!$P$13>0.01,INDEX('Debt Tracker'!$T$5:$AE$29,9,AC218-1)>0.01))*('Recurring Items'!$H$16<>"Skip")*(DAY(AB218)='Recurring Items'!$F$16)*IFERROR(N('Recurring Items'!$D$16),0)+(IF(AC218=1,'Debt Tracker'!$P$14>0.01,INDEX('Debt Tracker'!$T$5:$AE$29,10,AC218-1)>0.01))*('Recurring Items'!$H$17<>"Skip")*(DAY(AB218)='Recurring Items'!$F$17)*IFERROR(N('Recurring Items'!$D$17),0)+(IF(AC218=1,'Debt Tracker'!$P$15>0.01,INDEX('Debt Tracker'!$T$5:$AE$29,11,AC218-1)>0.01))*('Recurring Items'!$H$18<>"Skip")*(DAY(AB218)='Recurring Items'!$F$18)*IFERROR(N('Recurring Items'!$D$18),0)+(IF(AC218=1,'Debt Tracker'!$P$16>0.01,INDEX('Debt Tracker'!$T$5:$AE$29,12,AC218-1)>0.01))*('Recurring Items'!$H$19<>"Skip")*(DAY(AB218)='Recurring Items'!$F$19)*IFERROR(N('Recurring Items'!$D$19),0)+(IF(AC218=1,'Debt Tracker'!$P$17>0.01,INDEX('Debt Tracker'!$T$5:$AE$29,13,AC218-1)>0.01))*('Recurring Items'!$H$20<>"Skip")*(DAY(AB218)='Recurring Items'!$F$20)*IFERROR(N('Recurring Items'!$D$20),0)+(IF(AC218=1,'Debt Tracker'!$P$18>0.01,INDEX('Debt Tracker'!$T$5:$AE$29,14,AC218-1)>0.01))*('Recurring Items'!$H$21<>"Skip")*(DAY(AB218)='Recurring Items'!$F$21)*IFERROR(N('Recurring Items'!$D$21),0)+(IF(AC218=1,'Debt Tracker'!$P$19>0.01,INDEX('Debt Tracker'!$T$5:$AE$29,15,AC218-1)>0.01))*('Recurring Items'!$H$22<>"Skip")*(DAY(AB218)='Recurring Items'!$F$22)*IFERROR(N('Recurring Items'!$D$22),0)+(IF(AC218=1,'Debt Tracker'!$P$20>0.01,INDEX('Debt Tracker'!$T$5:$AE$29,16,AC218-1)>0.01))*('Recurring Items'!$H$23<>"Skip")*(DAY(AB218)='Recurring Items'!$F$23)*IFERROR(N('Recurring Items'!$D$23),0)+(IF(AC218=1,'Debt Tracker'!$P$21>0.01,INDEX('Debt Tracker'!$T$5:$AE$29,17,AC218-1)>0.01))*('Recurring Items'!$H$24<>"Skip")*(DAY(AB218)='Recurring Items'!$F$24)*IFERROR(N('Recurring Items'!$D$24),0)+(IF(AC218=1,'Debt Tracker'!$P$22>0.01,INDEX('Debt Tracker'!$T$5:$AE$29,18,AC218-1)>0.01))*('Recurring Items'!$H$25<>"Skip")*(DAY(AB218)='Recurring Items'!$F$25)*IFERROR(N('Recurring Items'!$D$25),0)+(IF(AC218=1,'Debt Tracker'!$P$23>0.01,INDEX('Debt Tracker'!$T$5:$AE$29,19,AC218-1)>0.01))*('Recurring Items'!$H$26<>"Skip")*(DAY(AB218)='Recurring Items'!$F$26)*IFERROR(N('Recurring Items'!$D$26),0)+(IF(AC218=1,'Debt Tracker'!$P$24>0.01,INDEX('Debt Tracker'!$T$5:$AE$29,20,AC218-1)>0.01))*('Recurring Items'!$H$27<>"Skip")*(DAY(AB218)='Recurring Items'!$F$27)*IFERROR(N('Recurring Items'!$D$27),0)+(IF(AC218=1,'Debt Tracker'!$P$25>0.01,INDEX('Debt Tracker'!$T$5:$AE$29,21,AC218-1)>0.01))*('Recurring Items'!$H$28<>"Skip")*(DAY(AB218)='Recurring Items'!$F$28)*IFERROR(N('Recurring Items'!$D$28),0)+(IF(AC218=1,'Debt Tracker'!$P$26>0.01,INDEX('Debt Tracker'!$T$5:$AE$29,22,AC218-1)>0.01))*('Recurring Items'!$H$29<>"Skip")*(DAY(AB218)='Recurring Items'!$F$29)*IFERROR(N('Recurring Items'!$D$29),0)+(IF(AC218=1,'Debt Tracker'!$P$27>0.01,INDEX('Debt Tracker'!$T$5:$AE$29,23,AC218-1)>0.01))*('Recurring Items'!$H$30<>"Skip")*(DAY(AB218)='Recurring Items'!$F$30)*IFERROR(N('Recurring Items'!$D$30),0)+(IF(AC218=1,'Debt Tracker'!$P$28>0.01,INDEX('Debt Tracker'!$T$5:$AE$29,24,AC218-1)>0.01))*('Recurring Items'!$H$31<>"Skip")*(DAY(AB218)='Recurring Items'!$F$31)*IFERROR(N('Recurring Items'!$D$31),0)+(IF(AC218=1,'Debt Tracker'!$P$29>0.01,INDEX('Debt Tracker'!$T$5:$AE$29,25,AC218-1)>0.01))*('Recurring Items'!$H$32<>"Skip")*(DAY(AB218)='Recurring Items'!$F$32)*IFERROR(N('Recurring Items'!$D$32),0) -> 0 | AG218: =AD218-AE218-AF218 -> 0 | AH218: =AH217+AG218 -> 2779.14
